Workbook

Sheet 【１】キーワード
B1: キーワード | D1: 済月 | E1: 46043 | F1: 過去キーワード一覧
A2: 1 | B2: figma Lancer Altria Pendragon DX Edition Fate Grand Order Max Factory Japan Neu | D2: 4月 | E2: 46278 | F2: ポケモンジム ヤマブキシティ
A3: 2 | D3: 5月 | F3: ANA フライングホヌ
A4: 3 | D4: 6月 | F4: 大久保篤画集
A5: 4 | D5: 7月 | F5: 星のカービィ ぬいぐるみ
A6: 5 | D6: 8月 | F6: セガサターン ストリートファイター
A7: 6 | D7: 3月 | F7: ハリーポッター レプリカ 教科書
A8: 7 | D8: 2月 | F8: THE BLUE HEARTS レコード
A9: 8 | F9: スタートレック コレクション ボーグキューブ
A10: 9 | F10: スキャンティ ニーソックス
A11: 10 | F11: ケナー ロストワールド レックス | I11: 46181
A12: 11 | F12: デジモンテイマーズ くたキャラ ギルモン ぬいぐるみ
A13: 12 | F13: 暁月のフィナーレ コレクターズ（アルミボトルも）
A14: 13 | F14: ミュウツーの逆襲 ピカチュウ プロも
A15: 14 | F15: ワンピース ハイパーバトル ルフィの帽子
A16: 15 | F16: リンチェイス ジャガージャングル プレート
A17: 16 | F17: トイストーリー ラウンドアップ絵皿
A18: 17 | F18: HUNTER×HUNTER グリードアイランド パーフェクトコレクタブル
A19: 18 | F19: IsatPhone Pro
A20: 19 | F20: U.S.S. NCC-1701-D | I20: 46189
A21: 20 | F21: 小澤征爾 グラモフォン録音全集
F22: デビルっちのたまごっち ピンク
F23: ラビュリンス デュエルセット
F24: SHODO SUPER 五星戦隊ダイレンジャー
F25: Ultimate Breaks Complete Collection CD
F26: Williams FW14 SENNA
F27: 三日月閑 フィギュア
F28: ねんどろいど デスストランディング クリフ DX
F29: ヴァリエイブルヒーローズ ナミ
F30: 刀装具 町彫 名品聚成 | I30: 46199
F31: 大久保篤画集 SOUL EATER SOUL ART
F32: バナナフィッシュ サウンドトラック レコード
F33: ねんどろいど ラルセイ
F34: ワンピース カードダス C07 ゾロ
F35: ノワール 寝起きフィギュア
F36: 精神壊しの罠 foil
F37: DAVID BOWIE FIVE YEARS 1969-1973 CD
F38: スーパーファミコン HAGANE
F39: Charlotte プレミアムフィギュア 友利奈緒
F40: QWER Beyond the Discord | I40: 46146
F41: ねんどろいど ウマ娘 オグリキャップ
F42: Siltech Ruby Hill II 1.5m
F43: RAH ジーン・シモンズ
F44: PS ガンナーズヘヴン
F45: 春日野穹 ふもふもそら
F46: ポケモンスクラッチ 第1弾
F47: ビッパ スツール オス
F48: チェンソーマン レゼ篇 特装盤
F49: YES HIGH VIBRATION SACD BOX
F50: Snail Shell 三猿 見ざる・聞かざる・言わざる | I50: 46154
F51: ゴジラ生誕70周年記念 4KリマスターBOX
F52: PRISMA WING Flower Imitation. Flower
F53: レゴ ハリーポッター コカコーラ
F54: figma UMP45
F55: イーグレットツー ミニ アーケードメモリーズVOL.2
F56: Charles Munch Complete RCA
F57: PREMIUM DX レイジングソード
F58: ゴーカイサーベル ゴーカイガン MEMORIAL EDITION
F59: S.H.フィギュアーツ 天道あかね
F60: ショドウフォン memorial edition | I60: 46162
F61: キングダムハーツ 20th プレート
F62: 超像可動 ディエゴ・ブランドー セカンド
F63: Dollfie アリゼー
F64: 幕之内一歩 fighting pose フィギュア
F65: 吉田遠志 Black panther | I65: 46163
F66: Devil May Cry Visions of Ⅴ
F67: Mad Max 2 The Road Warrior
F68: Bloodborne TORCH TORCH カインの証
F69: swatch MOMA ゴッホ
F70: s.h.figuarts うちはオビト
F71: ナルニア国物語 ワードローブ ミニチュア
F72: メモリアルヴィジョンドライバー
F73: 宮本麗 フィギュア
F74: スタートレック・スターシップコレクション ボーグキューブ
F75: Roland EDIROL P-10 | I75: 46171
F76: ポケモントランプ Part2 銀
F77: ワンピース カードダス C07 ゾロ
F78: 魔女の宅急便 B2 ポスター 劇場
F79: RGB ソルスタンド
F80: ジブリパーク マグネット
F81: U.S.S. NCC-1701-D
F82: ARTFX J 緑谷出久 黒デク
F83: 通常ぬいぐるみ アグネスタキオン ウマ娘
F84: スーパーファミコン ファイアーエムブレム トラキア776
F85: 弥海砂 フィギュア RED | I85: 46115
F86: ワンピース DRAMATIC SHOWCASE 3rd
F87: DJI Pocket 2 Creator Combo
F88: アビランド リモージュ ヴューパリヴェール プレート
F89: くじ ラストワン 弥海砂 フィギュア
F90: Mitutoyo 187-901-10
F91: 天童木工 椅子 かぶと
F92: Pomera DM250
F93: スーパーファミコン ファイアーエムブレム トラキア776
F94: Tamagotchi Uni Angel
F95: ハナダシティジム カスミ | I95: 46125
F96: 暁月のフィナーレ コレクターズ（アルミボトルも）
F97: アビランド リモージュ ヴューパリヴェール プレート
F98: ハリーポッター レプリカ 魔法薬学 教科書 Alarm Eighteen
F99: SHODO SUPER 救急戦隊ゴーゴーファイブ
F100: ART OF GHIBLI 魔女の宅急便
...

Sheet 【２】結果
A1: 数式 | B1: ● | C1: ● | D1: ● 各種数字→ | E1: 1 | F1: 2 | G1: 3 | H1: 4 | I1: 5 | J1: 6 | K1: 7 | L1: 8 | M1: 9 | N1: 10 | O1: 11 | P1: 12 | Q1: 13 | R1: 14 | S1: 15 | T1: 16 | U1: 17 | V1: 18 | W1: 19 | X1: 20
A2: 商品番号 | B2: 全コピー | C2: 件数 | D2: タイトル | E2: 1語目-1 | F2: 1語目-2 | G2: 1語目-3 | H2: 1語目-4 | I2: 1語目-5 | J2: 2語目-1 | K2: 2語目-2 | L2: 2語目-3 | M2: 2語目-4 | N2: 2語目-5 | O2: 3語目-1 | P2: 3語目-2 | Q2: 3語目-3 | R2: 3語目-4 | S2: 3語目-5 | T2: 4語目-1 | U2: 4語目-2 | V2: 4語目-3 | W2: 4語目-4 | X2: 4語目-5 | Z2: キーワード1
A3: 1 | B3: =MID(IF(E3="","",CHAR(10)&E3)&IF(F3="","",CHAR(10)&F3)&IF(G3="","",CHAR(10)&G3)&IF(H3="","",CHAR(10)&H3)&IF(I3="","",CHAR(10)&I3)&IF(J3="","",CHAR(10)&J3)&IF(K3="","",CHAR(10)&K3)&IF(L3="","",CHAR(10)&L3)&IF(M3="","",CHAR(10)&M3)&IF(N3="","",CHAR(10)&N3)&IF(O3="","",CHAR(10)&O3)&IF(P3="","",CHAR(10)&P3)&IF(Q3="","",CHAR(10)&Q3)&IF(R3="","",CHAR(10)&R3)&IF(S3="","",CHAR(10)&S3)&IF(T3="","",CHAR(10)&T3)&IF(U3="","",CHAR(10)&U3)&IF(V3="","",CHAR(10)&V3)&IF(W3="","",CHAR(10)&W3)&IF(X3="","",CHAR(10)&X3),2,30000) | C3: =COUNTIF(E3:X3,"http*") -> 0 | D3: =IF(【１】キーワード!B2="","",【１】キーワード!B2) -> figma Lancer Altria Pendragon DX Edition Fate Grand Order Max Factory Japan Neu | Z3: 1語目
A4: 2 | B4: =MID(IF(E4="","",CHAR(10)&E4)&IF(F4="","",CHAR(10)&F4)&IF(G4="","",CHAR(10)&G4)&IF(H4="","",CHAR(10)&H4)&IF(I4="","",CHAR(10)&I4)&IF(J4="","",CHAR(10)&J4)&IF(K4="","",CHAR(10)&K4)&IF(L4="","",CHAR(10)&L4)&IF(M4="","",CHAR(10)&M4)&IF(N4="","",CHAR(10)&N4)&IF(O4="","",CHAR(10)&O4)&IF(P4="","",CHAR(10)&P4)&IF(Q4="","",CHAR(10)&Q4)&IF(R4="","",CHAR(10)&R4)&IF(S4="","",CHAR(10)&S4)&IF(T4="","",CHAR(10)&T4)&IF(U4="","",CHAR(10)&U4)&IF(V4="","",CHAR(10)&V4)&IF(W4="","",CHAR(10)&W4)&IF(X4="","",CHAR(10)&X4),2,30000) | C4: =COUNTIF(E4:X4,"http*") -> 0 | D4: =IF(【１】キーワード!B3="","",【１】キーワード!B3) | Z4: 2語目
A5: 3 | B5: =MID(IF(E5="","",CHAR(10)&E5)&IF(F5="","",CHAR(10)&F5)&IF(G5="","",CHAR(10)&G5)&IF(H5="","",CHAR(10)&H5)&IF(I5="","",CHAR(10)&I5)&IF(J5="","",CHAR(10)&J5)&IF(K5="","",CHAR(10)&K5)&IF(L5="","",CHAR(10)&L5)&IF(M5="","",CHAR(10)&M5)&IF(N5="","",CHAR(10)&N5)&IF(O5="","",CHAR(10)&O5)&IF(P5="","",CHAR(10)&P5)&IF(Q5="","",CHAR(10)&Q5)&IF(R5="","",CHAR(10)&R5)&IF(S5="","",CHAR(10)&S5)&IF(T5="","",CHAR(10)&T5)&IF(U5="","",CHAR(10)&U5)&IF(V5="","",CHAR(10)&V5)&IF(W5="","",CHAR(10)&W5)&IF(X5="","",CHAR(10)&X5),2,30000) | C5: =COUNTIF(E5:X5,"http*") -> 0 | D5: =IF(【１】キーワード!B4="","",【１】キーワード!B4) | Z5: 3語目
A6: 4 | B6: =MID(IF(E6="","",CHAR(10)&E6)&IF(F6="","",CHAR(10)&F6)&IF(G6="","",CHAR(10)&G6)&IF(H6="","",CHAR(10)&H6)&IF(I6="","",CHAR(10)&I6)&IF(J6="","",CHAR(10)&J6)&IF(K6="","",CHAR(10)&K6)&IF(L6="","",CHAR(10)&L6)&IF(M6="","",CHAR(10)&M6)&IF(N6="","",CHAR(10)&N6)&IF(O6="","",CHAR(10)&O6)&IF(P6="","",CHAR(10)&P6)&IF(Q6="","",CHAR(10)&Q6)&IF(R6="","",CHAR(10)&R6)&IF(S6="","",CHAR(10)&S6)&IF(T6="","",CHAR(10)&T6)&IF(U6="","",CHAR(10)&U6)&IF(V6="","",CHAR(10)&V6)&IF(W6="","",CHAR(10)&W6)&IF(X6="","",CHAR(10)&X6),2,30000) | C6: =COUNTIF(E6:X6,"http*") -> 0 | D6: =IF(【１】キーワード!B5="","",【１】キーワード!B5) | Z6: 4語目
A7: 5 | B7: =MID(IF(E7="","",CHAR(10)&E7)&IF(F7="","",CHAR(10)&F7)&IF(G7="","",CHAR(10)&G7)&IF(H7="","",CHAR(10)&H7)&IF(I7="","",CHAR(10)&I7)&IF(J7="","",CHAR(10)&J7)&IF(K7="","",CHAR(10)&K7)&IF(L7="","",CHAR(10)&L7)&IF(M7="","",CHAR(10)&M7)&IF(N7="","",CHAR(10)&N7)&IF(O7="","",CHAR(10)&O7)&IF(P7="","",CHAR(10)&P7)&IF(Q7="","",CHAR(10)&Q7)&IF(R7="","",CHAR(10)&R7)&IF(S7="","",CHAR(10)&S7)&IF(T7="","",CHAR(10)&T7)&IF(U7="","",CHAR(10)&U7)&IF(V7="","",CHAR(10)&V7)&IF(W7="","",CHAR(10)&W7)&IF(X7="","",CHAR(10)&X7),2,30000) | C7: =COUNTIF(E7:X7,"http*") -> 0 | D7: =IF(【１】キーワード!B6="","",【１】キーワード!B6)
A8: 6 | B8: =MID(IF(E8="","",CHAR(10)&E8)&IF(F8="","",CHAR(10)&F8)&IF(G8="","",CHAR(10)&G8)&IF(H8="","",CHAR(10)&H8)&IF(I8="","",CHAR(10)&I8)&IF(J8="","",CHAR(10)&J8)&IF(K8="","",CHAR(10)&K8)&IF(L8="","",CHAR(10)&L8)&IF(M8="","",CHAR(10)&M8)&IF(N8="","",CHAR(10)&N8)&IF(O8="","",CHAR(10)&O8)&IF(P8="","",CHAR(10)&P8)&IF(Q8="","",CHAR(10)&Q8)&IF(R8="","",CHAR(10)&R8)&IF(S8="","",CHAR(10)&S8)&IF(T8="","",CHAR(10)&T8)&IF(U8="","",CHAR(10)&U8)&IF(V8="","",CHAR(10)&V8)&IF(W8="","",CHAR(10)&W8)&IF(X8="","",CHAR(10)&X8),2,30000) | C8: =COUNTIF(E8:X8,"http*") -> 0 | D8: =IF(【１】キーワード!B7="","",【１】キーワード!B7) | Z8: キーワード2
A9: 7 | B9: =MID(IF(E9="","",CHAR(10)&E9)&IF(F9="","",CHAR(10)&F9)&IF(G9="","",CHAR(10)&G9)&IF(H9="","",CHAR(10)&H9)&IF(I9="","",CHAR(10)&I9)&IF(J9="","",CHAR(10)&J9)&IF(K9="","",CHAR(10)&K9)&IF(L9="","",CHAR(10)&L9)&IF(M9="","",CHAR(10)&M9)&IF(N9="","",CHAR(10)&N9)&IF(O9="","",CHAR(10)&O9)&IF(P9="","",CHAR(10)&P9)&IF(Q9="","",CHAR(10)&Q9)&IF(R9="","",CHAR(10)&R9)&IF(S9="","",CHAR(10)&S9)&IF(T9="","",CHAR(10)&T9)&IF(U9="","",CHAR(10)&U9)&IF(V9="","",CHAR(10)&V9)&IF(W9="","",CHAR(10)&W9)&IF(X9="","",CHAR(10)&X9),2,30000) | C9: =COUNTIF(E9:X9,"http*") -> 0 | D9: =IF(【１】キーワード!B8="","",【１】キーワード!B8) | Z9: 1語目
A10: 8 | B10: =MID(IF(E10="","",CHAR(10)&E10)&IF(F10="","",CHAR(10)&F10)&IF(G10="","",CHAR(10)&G10)&IF(H10="","",CHAR(10)&H10)&IF(I10="","",CHAR(10)&I10)&IF(J10="","",CHAR(10)&J10)&IF(K10="","",CHAR(10)&K10)&IF(L10="","",CHAR(10)&L10)&IF(M10="","",CHAR(10)&M10)&IF(N10="","",CHAR(10)&N10)&IF(O10="","",CHAR(10)&O10)&IF(P10="","",CHAR(10)&P10)&IF(Q10="","",CHAR(10)&Q10)&IF(R10="","",CHAR(10)&R10)&IF(S10="","",CHAR(10)&S10)&IF(T10="","",CHAR(10)&T10)&IF(U10="","",CHAR(10)&U10)&IF(V10="","",CHAR(10)&V10)&IF(W10="","",CHAR(10)&W10)&IF(X10="","",CHAR(10)&X10),2,30000) | C10: =COUNTIF(E10:X10,"http*") -> 0 | D10: =IF(【１】キーワード!B9="","",【１】キーワード!B9) | Z10: 2語目
A11: 9 | B11: =MID(IF(E11="","",CHAR(10)&E11)&IF(F11="","",CHAR(10)&F11)&IF(G11="","",CHAR(10)&G11)&IF(H11="","",CHAR(10)&H11)&IF(I11="","",CHAR(10)&I11)&IF(J11="","",CHAR(10)&J11)&IF(K11="","",CHAR(10)&K11)&IF(L11="","",CHAR(10)&L11)&IF(M11="","",CHAR(10)&M11)&IF(N11="","",CHAR(10)&N11)&IF(O11="","",CHAR(10)&O11)&IF(P11="","",CHAR(10)&P11)&IF(Q11="","",CHAR(10)&Q11)&IF(R11="","",CHAR(10)&R11)&IF(S11="","",CHAR(10)&S11)&IF(T11="","",CHAR(10)&T11)&IF(U11="","",CHAR(10)&U11)&IF(V11="","",CHAR(10)&V11)&IF(W11="","",CHAR(10)&W11)&IF(X11="","",CHAR(10)&X11),2,30000) | C11: =COUNTIF(E11:X11,"http*") -> 0 | D11: =IF(【１】キーワード!B10="","",【１】キーワード!B10) | Z11: 3語目
A12: 10 | B12: =MID(IF(E12="","",CHAR(10)&E12)&IF(F12="","",CHAR(10)&F12)&IF(G12="","",CHAR(10)&G12)&IF(H12="","",CHAR(10)&H12)&IF(I12="","",CHAR(10)&I12)&IF(J12="","",CHAR(10)&J12)&IF(K12="","",CHAR(10)&K12)&IF(L12="","",CHAR(10)&L12)&IF(M12="","",CHAR(10)&M12)&IF(N12="","",CHAR(10)&N12)&IF(O12="","",CHAR(10)&O12)&IF(P12="","",CHAR(10)&P12)&IF(Q12="","",CHAR(10)&Q12)&IF(R12="","",CHAR(10)&R12)&IF(S12="","",CHAR(10)&S12)&IF(T12="","",CHAR(10)&T12)&IF(U12="","",CHAR(10)&U12)&IF(V12="","",CHAR(10)&V12)&IF(W12="","",CHAR(10)&W12)&IF(X12="","",CHAR(10)&X12),2,30000) | C12: =COUNTIF(E12:X12,"http*") -> 0 | D12: =IF(【１】キーワード!B11="","",【１】キーワード!B11) | Z12: 4語目
A13: 11 | B13: =MID(IF(E13="","",CHAR(10)&E13)&IF(F13="","",CHAR(10)&F13)&IF(G13="","",CHAR(10)&G13)&IF(H13="","",CHAR(10)&H13)&IF(I13="","",CHAR(10)&I13)&IF(J13="","",CHAR(10)&J13)&IF(K13="","",CHAR(10)&K13)&IF(L13="","",CHAR(10)&L13)&IF(M13="","",CHAR(10)&M13)&IF(N13="","",CHAR(10)&N13)&IF(O13="","",CHAR(10)&O13)&IF(P13="","",CHAR(10)&P13)&IF(Q13="","",CHAR(10)&Q13)&IF(R13="","",CHAR(10)&R13)&IF(S13="","",CHAR(10)&S13)&IF(T13="","",CHAR(10)&T13)&IF(U13="","",CHAR(10)&U13)&IF(V13="","",CHAR(10)&V13)&IF(W13="","",CHAR(10)&W13)&IF(X13="","",CHAR(10)&X13),2,30000) | C13: =COUNTIF(E13:X13,"http*") -> 0 | D13: =IF(【１】キーワード!B12="","",【１】キーワード!B12)
A14: 12 | B14: =MID(IF(E14="","",CHAR(10)&E14)&IF(F14="","",CHAR(10)&F14)&IF(G14="","",CHAR(10)&G14)&IF(H14="","",CHAR(10)&H14)&IF(I14="","",CHAR(10)&I14)&IF(J14="","",CHAR(10)&J14)&IF(K14="","",CHAR(10)&K14)&IF(L14="","",CHAR(10)&L14)&IF(M14="","",CHAR(10)&M14)&IF(N14="","",CHAR(10)&N14)&IF(O14="","",CHAR(10)&O14)&IF(P14="","",CHAR(10)&P14)&IF(Q14="","",CHAR(10)&Q14)&IF(R14="","",CHAR(10)&R14)&IF(S14="","",CHAR(10)&S14)&IF(T14="","",CHAR(10)&T14)&IF(U14="","",CHAR(10)&U14)&IF(V14="","",CHAR(10)&V14)&IF(W14="","",CHAR(10)&W14)&IF(X14="","",CHAR(10)&X14),2,30000) | C14: =COUNTIF(E14:X14,"http*") -> 0 | D14: =IF(【１】キーワード!B13="","",【１】キーワード!B13) | Z14: キーワード3
A15: 13 | B15: =MID(IF(E15="","",CHAR(10)&E15)&IF(F15="","",CHAR(10)&F15)&IF(G15="","",CHAR(10)&G15)&IF(H15="","",CHAR(10)&H15)&IF(I15="","",CHAR(10)&I15)&IF(J15="","",CHAR(10)&J15)&IF(K15="","",CHAR(10)&K15)&IF(L15="","",CHAR(10)&L15)&IF(M15="","",CHAR(10)&M15)&IF(N15="","",CHAR(10)&N15)&IF(O15="","",CHAR(10)&O15)&IF(P15="","",CHAR(10)&P15)&IF(Q15="","",CHAR(10)&Q15)&IF(R15="","",CHAR(10)&R15)&IF(S15="","",CHAR(10)&S15)&IF(T15="","",CHAR(10)&T15)&IF(U15="","",CHAR(10)&U15)&IF(V15="","",CHAR(10)&V15)&IF(W15="","",CHAR(10)&W15)&IF(X15="","",CHAR(10)&X15),2,30000) | C15: =COUNTIF(E15:X15,"http*") -> 0 | D15: =IF(【１】キーワード!B14="","",【１】キーワード!B14) | Z15: 1語目
A16: 14 | B16: =MID(IF(E16="","",CHAR(10)&E16)&IF(F16="","",CHAR(10)&F16)&IF(G16="","",CHAR(10)&G16)&IF(H16="","",CHAR(10)&H16)&IF(I16="","",CHAR(10)&I16)&IF(J16="","",CHAR(10)&J16)&IF(K16="","",CHAR(10)&K16)&IF(L16="","",CHAR(10)&L16)&IF(M16="","",CHAR(10)&M16)&IF(N16="","",CHAR(10)&N16)&IF(O16="","",CHAR(10)&O16)&IF(P16="","",CHAR(10)&P16)&IF(Q16="","",CHAR(10)&Q16)&IF(R16="","",CHAR(10)&R16)&IF(S16="","",CHAR(10)&S16)&IF(T16="","",CHAR(10)&T16)&IF(U16="","",CHAR(10)&U16)&IF(V16="","",CHAR(10)&V16)&IF(W16="","",CHAR(10)&W16)&IF(X16="","",CHAR(10)&X16),2,30000) | C16: =COUNTIF(E16:X16,"http*") -> 0 | D16: =IF(【１】キーワード!B15="","",【１】キーワード!B15) | Z16: 2語目
A17: 15 | B17: =MID(IF(E17="","",CHAR(10)&E17)&IF(F17="","",CHAR(10)&F17)&IF(G17="","",CHAR(10)&G17)&IF(H17="","",CHAR(10)&H17)&IF(I17="","",CHAR(10)&I17)&IF(J17="","",CHAR(10)&J17)&IF(K17="","",CHAR(10)&K17)&IF(L17="","",CHAR(10)&L17)&IF(M17="","",CHAR(10)&M17)&IF(N17="","",CHAR(10)&N17)&IF(O17="","",CHAR(10)&O17)&IF(P17="","",CHAR(10)&P17)&IF(Q17="","",CHAR(10)&Q17)&IF(R17="","",CHAR(10)&R17)&IF(S17="","",CHAR(10)&S17)&IF(T17="","",CHAR(10)&T17)&IF(U17="","",CHAR(10)&U17)&IF(V17="","",CHAR(10)&V17)&IF(W17="","",CHAR(10)&W17)&IF(X17="","",CHAR(10)&X17),2,30000) | C17: =COUNTIF(E17:X17,"http*") -> 0 | D17: =IF(【１】キーワード!B16="","",【１】キーワード!B16) | Z17: 3語目
A18: 16 | B18: =MID(IF(E18="","",CHAR(10)&E18)&IF(F18="","",CHAR(10)&F18)&IF(G18="","",CHAR(10)&G18)&IF(H18="","",CHAR(10)&H18)&IF(I18="","",CHAR(10)&I18)&IF(J18="","",CHAR(10)&J18)&IF(K18="","",CHAR(10)&K18)&IF(L18="","",CHAR(10)&L18)&IF(M18="","",CHAR(10)&M18)&IF(N18="","",CHAR(10)&N18)&IF(O18="","",CHAR(10)&O18)&IF(P18="","",CHAR(10)&P18)&IF(Q18="","",CHAR(10)&Q18)&IF(R18="","",CHAR(10)&R18)&IF(S18="","",CHAR(10)&S18)&IF(T18="","",CHAR(10)&T18)&IF(U18="","",CHAR(10)&U18)&IF(V18="","",CHAR(10)&V18)&IF(W18="","",CHAR(10)&W18)&IF(X18="","",CHAR(10)&X18),2,30000) | C18: =COUNTIF(E18:X18,"http*") -> 0 | D18: =IF(【１】キーワード!B17="","",【１】キーワード!B17) | Z18: 4語目
A19: 17 | B19: =MID(IF(E19="","",CHAR(10)&E19)&IF(F19="","",CHAR(10)&F19)&IF(G19="","",CHAR(10)&G19)&IF(H19="","",CHAR(10)&H19)&IF(I19="","",CHAR(10)&I19)&IF(J19="","",CHAR(10)&J19)&IF(K19="","",CHAR(10)&K19)&IF(L19="","",CHAR(10)&L19)&IF(M19="","",CHAR(10)&M19)&IF(N19="","",CHAR(10)&N19)&IF(O19="","",CHAR(10)&O19)&IF(P19="","",CHAR(10)&P19)&IF(Q19="","",CHAR(10)&Q19)&IF(R19="","",CHAR(10)&R19)&IF(S19="","",CHAR(10)&S19)&IF(T19="","",CHAR(10)&T19)&IF(U19="","",CHAR(10)&U19)&IF(V19="","",CHAR(10)&V19)&IF(W19="","",CHAR(10)&W19)&IF(X19="","",CHAR(10)&X19),2,30000) | C19: =COUNTIF(E19:X19,"http*") -> 0 | D19: =IF(【１】キーワード!B18="","",【１】キーワード!B18)
A20: 18 | B20: =MID(IF(E20="","",CHAR(10)&E20)&IF(F20="","",CHAR(10)&F20)&IF(G20="","",CHAR(10)&G20)&IF(H20="","",CHAR(10)&H20)&IF(I20="","",CHAR(10)&I20)&IF(J20="","",CHAR(10)&J20)&IF(K20="","",CHAR(10)&K20)&IF(L20="","",CHAR(10)&L20)&IF(M20="","",CHAR(10)&M20)&IF(N20="","",CHAR(10)&N20)&IF(O20="","",CHAR(10)&O20)&IF(P20="","",CHAR(10)&P20)&IF(Q20="","",CHAR(10)&Q20)&IF(R20="","",CHAR(10)&R20)&IF(S20="","",CHAR(10)&S20)&IF(T20="","",CHAR(10)&T20)&IF(U20="","",CHAR(10)&U20)&IF(V20="","",CHAR(10)&V20)&IF(W20="","",CHAR(10)&W20)&IF(X20="","",CHAR(10)&X20),2,30000) | C20: =COUNTIF(E20:X20,"http*") -> 0 | D20: =IF(【１】キーワード!B19="","",【１】キーワード!B19) | Z20: キーワード4
A21: 19 | B21: =MID(IF(E21="","",CHAR(10)&E21)&IF(F21="","",CHAR(10)&F21)&IF(G21="","",CHAR(10)&G21)&IF(H21="","",CHAR(10)&H21)&IF(I21="","",CHAR(10)&I21)&IF(J21="","",CHAR(10)&J21)&IF(K21="","",CHAR(10)&K21)&IF(L21="","",CHAR(10)&L21)&IF(M21="","",CHAR(10)&M21)&IF(N21="","",CHAR(10)&N21)&IF(O21="","",CHAR(10)&O21)&IF(P21="","",CHAR(10)&P21)&IF(Q21="","",CHAR(10)&Q21)&IF(R21="","",CHAR(10)&R21)&IF(S21="","",CHAR(10)&S21)&IF(T21="","",CHAR(10)&T21)&IF(U21="","",CHAR(10)&U21)&IF(V21="","",CHAR(10)&V21)&IF(W21="","",CHAR(10)&W21)&IF(X21="","",CHAR(10)&X21),2,30000) | C21: =COUNTIF(E21:X21,"http*") -> 0 | D21: =IF(【１】キーワード!B20="","",【１】キーワード!B20) | Z21: 1語目
A22: 20 | B22: =MID(IF(E22="","",CHAR(10)&E22)&IF(F22="","",CHAR(10)&F22)&IF(G22="","",CHAR(10)&G22)&IF(H22="","",CHAR(10)&H22)&IF(I22="","",CHAR(10)&I22)&IF(J22="","",CHAR(10)&J22)&IF(K22="","",CHAR(10)&K22)&IF(L22="","",CHAR(10)&L22)&IF(M22="","",CHAR(10)&M22)&IF(N22="","",CHAR(10)&N22)&IF(O22="","",CHAR(10)&O22)&IF(P22="","",CHAR(10)&P22)&IF(Q22="","",CHAR(10)&Q22)&IF(R22="","",CHAR(10)&R22)&IF(S22="","",CHAR(10)&S22)&IF(T22="","",CHAR(10)&T22)&IF(U22="","",CHAR(10)&U22)&IF(V22="","",CHAR(10)&V22)&IF(W22="","",CHAR(10)&W22)&IF(X22="","",CHAR(10)&X22),2,30000) | C22: =COUNTIF(E22:X22,"http*") -> 0 | D22: =IF(【１】キーワード!B21="","",【１】キーワード!B21) | Z22: 2語目
Z23: 3語目
Z24: 4語目
Z26: キーワード5
Z27: 1語目
Z28: 2語目
Z29: 3語目
Z30: 4語目
Z32: キーワード6
Z33: 1語目
Z34: 2語目
Z35: 3語目
Z36: 4語目
... Z66: 4語目

Sheet 【３】出品リスト候補
B1: 仕入れ先候補 | C1: チェック | D1: 仕入れ先価格 | E1: 日本語タイトル | F1: 英語タイトル | G1: 抽出URL | H1: メルカリ | I1: ラクマ | J1: 楽天市場 | K1: ヤフオク | L1: ヤフーショッピング | M1: 結果 | N1: 予想 最安値($) | O1: 商品 重量(kg) | P1: 商品の 長さ(cm) | Q1: 商品の 幅(cm) | R1: 商品の 高さ(cm) | S1: 現在の米ドル円 為替($) | T1: 実重量 | U1: 容積重量 | V1: 大きい方 | W1: 繰り上げ | X1: 結果 | Y1: 予想送料 | Z1: 予想手数料 | AA1: 予想関税1 | AB1: 予想関税2 | AC1: 仕入値+ 送料+ 関税+ 手数料 | AD1: 予想最安値*為替 | AE1: 利益 （8500～9500円） | AG1: https://www.ebay.com/sch/i.html?_nkw=test&_sacat=0&_from=R40&_sop=15&rt=nc&_udlo=20000
A2: 1-1 | B2: =【２】結果!E3 -> 0 | T2: =O2 -> 0 | U2: =(P2*Q2*R2)/5000 -> 0 | V2: =MAX(T2,U2) -> 0 | W2: =CEILING(ROUNDDOWN(V2,2),0.5) -> 0 | X2: =VLOOKUP(W2,送料!$J$3:$K$42,2,FALSE) -> #N/A | Y2: =VLOOKUP(X2,送料!$A$1:$B$40,2,FALSE) -> #N/A | Z2: =(N2*S2)*0.16 -> 0 | AA2: =(N2*0.15)+4.5 -> 4.5 | AB2: =S2*AA2 -> 0 | AC2: =Y2+Z2+AB2+D2 -> #N/A | AD2: =N2*S2 -> 0 | AE2: =AD2-AC2 -> #N/A
A3: 1-2 | B3: =【２】結果!F3 -> 0 | T3: =O3 -> 0 | U3: =(P3*Q3*R3)/5000 -> 0 | V3: =MAX(T3,U3) -> 0 | W3: =CEILING(ROUNDDOWN(V3,2),0.5) -> 0 | X3: =VLOOKUP(W3,送料!$J$3:$K$42,2,FALSE) -> #N/A | Y3: =VLOOKUP(X3,送料!$A$1:$B$40,2,FALSE) -> #N/A | Z3: =(N3*S3)*0.16 -> 0 | AA3: =(N3*0.15)+4.5 -> 4.5 | AB3: =S3*AA3 -> 0 | AC3: =Y3+Z3+AB3+D3 -> #N/A | AD3: =N3*S3 -> 0 | AE3: =AD3-AC3 -> #N/A
A4: 1-3 | B4: =【２】結果!G3 -> 0 | T4: =O4 -> 0 | U4: =(P4*Q4*R4)/5000 -> 0 | V4: =MAX(T4,U4) -> 0 | W4: =CEILING(ROUNDDOWN(V4,2),0.5) -> 0 | X4: =VLOOKUP(W4,送料!$J$3:$K$42,2,FALSE) -> #N/A | Y4: =VLOOKUP(X4,送料!$A$1:$B$40,2,FALSE) -> #N/A | Z4: =(N4*S4)*0.16 -> 0 | AA4: =(N4*0.15)+4.5 -> 4.5 | AB4: =S4*AA4 -> 0 | AC4: =Y4+Z4+AB4+D4 -> #N/A | AD4: =N4*S4 -> 0 | AE4: =AD4-AC4 -> #N/A
A5: 1-4 | B5: =【２】結果!H3 -> 0 | T5: =O5 -> 0 | U5: =(P5*Q5*R5)/5000 -> 0 | V5: =MAX(T5,U5) -> 0 | W5: =CEILING(ROUNDDOWN(V5,2),0.5) -> 0 | X5: =VLOOKUP(W5,送料!$J$3:$K$42,2,FALSE) -> #N/A | Y5: =VLOOKUP(X5,送料!$A$1:$B$40,2,FALSE) -> #N/A | Z5: =(N5*S5)*0.16 -> 0 | AA5: =(N5*0.15)+4.5 -> 4.5 | AB5: =S5*AA5 -> 0 | AC5: =Y5+Z5+AB5+D5 -> #N/A | AD5: =N5*S5 -> 0 | AE5: =AD5-AC5 -> #N/A
A6: 1-5 | B6: =【２】結果!I3 -> 0 | T6: =O6 -> 0 | U6: =(P6*Q6*R6)/5000 -> 0 | V6: =MAX(T6,U6) -> 0 | W6: =CEILING(ROUNDDOWN(V6,2),0.5) -> 0 | X6: =VLOOKUP(W6,送料!$J$3:$K$42,2,FALSE) -> #N/A | Y6: =VLOOKUP(X6,送料!$A$1:$B$40,2,FALSE) -> #N/A | Z6: =(N6*S6)*0.16 -> 0 | AA6: =(N6*0.15)+4.5 -> 4.5 | AB6: =S6*AA6 -> 0 | AC6: =Y6+Z6+AB6+D6 -> #N/A | AD6: =N6*S6 -> 0 | AE6: =AD6-AC6 -> #N/A
A7: 1-6 | B7: =【２】結果!J3 -> 0 | T7: =O7 -> 0 | U7: =(P7*Q7*R7)/5000 -> 0 | V7: =MAX(T7,U7) -> 0 | W7: =CEILING(ROUNDDOWN(V7,2),0.5) -> 0 | X7: =VLOOKUP(W7,送料!$J$3:$K$42,2,FALSE) -> #N/A | Y7: =VLOOKUP(X7,送料!$A$1:$B$40,2,FALSE) -> #N/A | Z7: =(N7*S7)*0.16 -> 0 | AA7: =(N7*0.15)+4.5 -> 4.5 | AB7: =S7*AA7 -> 0 | AC7: =Y7+Z7+AB7+D7 -> #N/A | AD7: =N7*S7 -> 0 | AE7: =AD7-AC7 -> #N/A
A8: 1-7 | B8: =【２】結果!K3 -> 0 | T8: =O8 -> 0 | U8: =(P8*Q8*R8)/5000 -> 0 | V8: =MAX(T8,U8) -> 0 | W8: =CEILING(ROUNDDOWN(V8,2),0.5) -> 0 | X8: =VLOOKUP(W8,送料!$J$3:$K$42,2,FALSE) -> #N/A | Y8: =VLOOKUP(X8,送料!$A$1:$B$40,2,FALSE) -> #N/A | Z8: =(N8*S8)*0.16 -> 0 | AA8: =(N8*0.15)+4.5 -> 4.5 | AB8: =S8*AA8 -> 0 | AC8: =Y8+Z8+AB8+D8 -> #N/A | AD8: =N8*S8 -> 0 | AE8: =AD8-AC8 -> #N/A
A9: 1-8 | B9: =【２】結果!L3 -> 0 | T9: =O9 -> 0 | U9: =(P9*Q9*R9)/5000 -> 0 | V9: =MAX(T9,U9) -> 0 | W9: =CEILING(ROUNDDOWN(V9,2),0.5) -> 0 | X9: =VLOOKUP(W9,送料!$J$3:$K$42,2,FALSE) -> #N/A | Y9: =VLOOKUP(X9,送料!$A$1:$B$40,2,FALSE) -> #N/A | Z9: =(N9*S9)*0.16 -> 0 | AA9: =(N9*0.15)+4.5 -> 4.5 | AB9: =S9*AA9 -> 0 | AC9: =Y9+Z9+AB9+D9 -> #N/A | AD9: =N9*S9 -> 0 | AE9: =AD9-AC9 -> #N/A
A10: 1-9 | B10: =【２】結果!M3 -> 0 | T10: =O10 -> 0 | U10: =(P10*Q10*R10)/5000 -> 0 | V10: =MAX(T10,U10) -> 0 | W10: =CEILING(ROUNDDOWN(V10,2),0.5) -> 0 | X10: =VLOOKUP(W10,送料!$J$3:$K$42,2,FALSE) -> #N/A | Y10: =VLOOKUP(X10,送料!$A$1:$B$40,2,FALSE) -> #N/A | Z10: =(N10*S10)*0.16 -> 0 | AA10: =(N10*0.15)+4.5 -> 4.5 | AB10: =S10*AA10 -> 0 | AC10: =Y10+Z10+AB10+D10 -> #N/A | AD10: =N10*S10 -> 0 | AE10: =AD10-AC10 -> #N/A
A11: 1-10 | B11: =【２】結果!N3 -> 0 | T11: =O11 -> 0 | U11: =(P11*Q11*R11)/5000 -> 0 | V11: =MAX(T11,U11) -> 0 | W11: =CEILING(ROUNDDOWN(V11,2),0.5) -> 0 | X11: =VLOOKUP(W11,送料!$J$3:$K$42,2,FALSE) -> #N/A | Y11: =VLOOKUP(X11,送料!$A$1:$B$40,2,FALSE) -> #N/A | Z11: =(N11*S11)*0.16 -> 0 | AA11: =(N11*0.15)+4.5 -> 4.5 | AB11: =S11*AA11 -> 0 | AC11: =Y11+Z11+AB11+D11 -> #N/A | AD11: =N11*S11 -> 0 | AE11: =AD11-AC11 -> #N/A
A12: 1-11 | B12: =【２】結果!O3 -> 0 | T12: =O12 -> 0 | U12: =(P12*Q12*R12)/5000 -> 0 | V12: =MAX(T12,U12) -> 0 | W12: =CEILING(ROUNDDOWN(V12,2),0.5) -> 0 | X12: =VLOOKUP(W12,送料!$J$3:$K$42,2,FALSE) -> #N/A | Y12: =VLOOKUP(X12,送料!$A$1:$B$40,2,FALSE) -> #N/A | Z12: =(N12*S12)*0.16 -> 0 | AA12: =(N12*0.15)+4.5 -> 4.5 | AB12: =S12*AA12 -> 0 | AC12: =Y12+Z12+AB12+D12 -> #N/A | AD12: =N12*S12 -> 0 | AE12: =AD12-AC12 -> #N/A
A13: 1-12 | B13: =【２】結果!P3 -> 0 | T13: =O13 -> 0 | U13: =(P13*Q13*R13)/5000 -> 0 | V13: =MAX(T13,U13) -> 0 | W13: =CEILING(ROUNDDOWN(V13,2),0.5) -> 0 | X13: =VLOOKUP(W13,送料!$J$3:$K$42,2,FALSE) -> #N/A | Y13: =VLOOKUP(X13,送料!$A$1:$B$40,2,FALSE) -> #N/A | Z13: =(N13*S13)*0.16 -> 0 | AA13: =(N13*0.15)+4.5 -> 4.5 | AB13: =S13*AA13 -> 0 | AC13: =Y13+Z13+AB13+D13 -> #N/A | AD13: =N13*S13 -> 0 | AE13: =AD13-AC13 -> #N/A
A14: 1-13 | B14: =【２】結果!Q3 -> 0 | T14: =O14 -> 0 | U14: =(P14*Q14*R14)/5000 -> 0 | V14: =MAX(T14,U14) -> 0 | W14: =CEILING(ROUNDDOWN(V14,2),0.5) -> 0 | X14: =VLOOKUP(W14,送料!$J$3:$K$42,2,FALSE) -> #N/A | Y14: =VLOOKUP(X14,送料!$A$1:$B$40,2,FALSE) -> #N/A | Z14: =(N14*S14)*0.16 -> 0 | AA14: =(N14*0.15)+4.5 -> 4.5 | AB14: =S14*AA14 -> 0 | AC14: =Y14+Z14+AB14+D14 -> #N/A | AD14: =N14*S14 -> 0 | AE14: =AD14-AC14 -> #N/A
A15: 1-14 | B15: =【２】結果!R3 -> 0 | T15: =O15 -> 0 | U15: =(P15*Q15*R15)/5000 -> 0 | V15: =MAX(T15,U15) -> 0 | W15: =CEILING(ROUNDDOWN(V15,2),0.5) -> 0 | X15: =VLOOKUP(W15,送料!$J$3:$K$42,2,FALSE) -> #N/A | Y15: =VLOOKUP(X15,送料!$A$1:$B$40,2,FALSE) -> #N/A | Z15: =(N15*S15)*0.16 -> 0 | AA15: =(N15*0.15)+4.5 -> 4.5 | AB15: =S15*AA15 -> 0 | AC15: =Y15+Z15+AB15+D15 -> #N/A | AD15: =N15*S15 -> 0 | AE15: =AD15-AC15 -> #N/A
A16: 1-15 | B16: =【２】結果!S3 -> 0 | T16: =O16 -> 0 | U16: =(P16*Q16*R16)/5000 -> 0 | V16: =MAX(T16,U16) -> 0 | W16: =CEILING(ROUNDDOWN(V16,2),0.5) -> 0 | X16: =VLOOKUP(W16,送料!$J$3:$K$42,2,FALSE) -> #N/A | Y16: =VLOOKUP(X16,送料!$A$1:$B$40,2,FALSE) -> #N/A | Z16: =(N16*S16)*0.16 -> 0 | AA16: =(N16*0.15)+4.5 -> 4.5 | AB16: =S16*AA16 -> 0 | AC16: =Y16+Z16+AB16+D16 -> #N/A | AD16: =N16*S16 -> 0 | AE16: =AD16-AC16 -> #N/A
A17: 1-16 | B17: =【２】結果!T3 -> 0 | T17: =O17 -> 0 | U17: =(P17*Q17*R17)/5000 -> 0 | V17: =MAX(T17,U17) -> 0 | W17: =CEILING(ROUNDDOWN(V17,2),0.5) -> 0 | X17: =VLOOKUP(W17,送料!$J$3:$K$42,2,FALSE) -> #N/A | Y17: =VLOOKUP(X17,送料!$A$1:$B$40,2,FALSE) -> #N/A | Z17: =(N17*S17)*0.16 -> 0 | AA17: =(N17*0.15)+4.5 -> 4.5 | AB17: =S17*AA17 -> 0 | AC17: =Y17+Z17+AB17+D17 -> #N/A | AD17: =N17*S17 -> 0 | AE17: =AD17-AC17 -> #N/A
A18: 1-17 | B18: =【２】結果!U3 -> 0 | T18: =O18 -> 0 | U18: =(P18*Q18*R18)/5000 -> 0 | V18: =MAX(T18,U18) -> 0 | W18: =CEILING(ROUNDDOWN(V18,2),0.5) -> 0 | X18: =VLOOKUP(W18,送料!$J$3:$K$42,2,FALSE) -> #N/A | Y18: =VLOOKUP(X18,送料!$A$1:$B$40,2,FALSE) -> #N/A | Z18: =(N18*S18)*0.16 -> 0 | AA18: =(N18*0.15)+4.5 -> 4.5 | AB18: =S18*AA18 -> 0 | AC18: =Y18+Z18+AB18+D18 -> #N/A | AD18: =N18*S18 -> 0 | AE18: =AD18-AC18 -> #N/A
A19: 1-18 | B19: =【２】結果!V3 -> 0 | T19: =O19 -> 0 | U19: =(P19*Q19*R19)/5000 -> 0 | V19: =MAX(T19,U19) -> 0 | W19: =CEILING(ROUNDDOWN(V19,2),0.5) -> 0 | X19: =VLOOKUP(W19,送料!$J$3:$K$42,2,FALSE) -> #N/A | Y19: =VLOOKUP(X19,送料!$A$1:$B$40,2,FALSE) -> #N/A | Z19: =(N19*S19)*0.16 -> 0 | AA19: =(N19*0.15)+4.5 -> 4.5 | AB19: =S19*AA19 -> 0 | AC19: =Y19+Z19+AB19+D19 -> #N/A | AD19: =N19*S19 -> 0 | AE19: =AD19-AC19 -> #N/A
A20: 1-19 | B20: =【２】結果!W3 -> 0 | T20: =O20 -> 0 | U20: =(P20*Q20*R20)/5000 -> 0 | V20: =MAX(T20,U20) -> 0 | W20: =CEILING(ROUNDDOWN(V20,2),0.5) -> 0 | X20: =VLOOKUP(W20,送料!$J$3:$K$42,2,FALSE) -> #N/A | Y20: =VLOOKUP(X20,送料!$A$1:$B$40,2,FALSE) -> #N/A | Z20: =(N20*S20)*0.16 -> 0 | AA20: =(N20*0.15)+4.5 -> 4.5 | AB20: =S20*AA20 -> 0 | AC20: =Y20+Z20+AB20+D20 -> #N/A | AD20: =N20*S20 -> 0 | AE20: =AD20-AC20 -> #N/A
A21: 1-20 | B21: =【２】結果!X3 -> 0 | T21: =O21 -> 0 | U21: =(P21*Q21*R21)/5000 -> 0 | V21: =MAX(T21,U21) -> 0 | W21: =CEILING(ROUNDDOWN(V21,2),0.5) -> 0 | X21: =VLOOKUP(W21,送料!$J$3:$K$42,2,FALSE) -> #N/A | Y21: =VLOOKUP(X21,送料!$A$1:$B$40,2,FALSE) -> #N/A | Z21: =(N21*S21)*0.16 -> 0 | AA21: =(N21*0.15)+4.5 -> 4.5 | AB21: =S21*AA21 -> 0 | AC21: =Y21+Z21+AB21+D21 -> #N/A | AD21: =N21*S21 -> 0 | AE21: =AD21-AC21 -> #N/A
A22: 2-1 | B22: =【２】結果!E4 -> 0 | T22: =O22 -> 0 | U22: =(P22*Q22*R22)/5000 -> 0 | V22: =MAX(T22,U22) -> 0 | W22: =CEILING(ROUNDDOWN(V22,2),0.5) -> 0 | X22: =VLOOKUP(W22,送料!$J$3:$K$42,2,FALSE) -> #N/A | Y22: =VLOOKUP(X22,送料!$A$1:$B$40,2,FALSE) -> #N/A | Z22: =(N22*S22)*0.16 -> 0 | AA22: =(N22*0.15)+4.5 -> 4.5 | AB22: =S22*AA22 -> 0 | AC22: =Y22+Z22+AB22+D22 -> #N/A | AD22: =N22*S22 -> 0 | AE22: =AD22-AC22 -> #N/A
A23: 2-2 | B23: =【２】結果!F4 -> 0 | T23: =O23 -> 0 | U23: =(P23*Q23*R23)/5000 -> 0 | V23: =MAX(T23,U23) -> 0 | W23: =CEILING(ROUNDDOWN(V23,2),0.5) -> 0 | X23: =VLOOKUP(W23,送料!$J$3:$K$42,2,FALSE) -> #N/A | Y23: =VLOOKUP(X23,送料!$A$1:$B$40,2,FALSE) -> #N/A | Z23: =(N23*S23)*0.16 -> 0 | AA23: =(N23*0.15)+4.5 -> 4.5 | AB23: =S23*AA23 -> 0 | AC23: =Y23+Z23+AB23+D23 -> #N/A | AD23: =N23*S23 -> 0 | AE23: =AD23-AC23 -> #N/A
A24: 2-3 | B24: =【２】結果!G4 -> 0 | T24: =O24 -> 0 | U24: =(P24*Q24*R24)/5000 -> 0 | V24: =MAX(T24,U24) -> 0 | W24: =CEILING(ROUNDDOWN(V24,2),0.5) -> 0 | X24: =VLOOKUP(W24,送料!$J$3:$K$42,2,FALSE) -> #N/A | Y24: =VLOOKUP(X24,送料!$A$1:$B$40,2,FALSE) -> #N/A | Z24: =(N24*S24)*0.16 -> 0 | AA24: =(N24*0.15)+4.5 -> 4.5 | AB24: =S24*AA24 -> 0 | AC24: =Y24+Z24+AB24+D24 -> #N/A | AD24: =N24*S24 -> 0 | AE24: =AD24-AC24 -> #N/A
A25: 2-4 | B25: =【２】結果!H4 -> 0 | T25: =O25 -> 0 | U25: =(P25*Q25*R25)/5000 -> 0 | V25: =MAX(T25,U25) -> 0 | W25: =CEILING(ROUNDDOWN(V25,2),0.5) -> 0 | X25: =VLOOKUP(W25,送料!$J$3:$K$42,2,FALSE) -> #N/A | Y25: =VLOOKUP(X25,送料!$A$1:$B$40,2,FALSE) -> #N/A | Z25: =(N25*S25)*0.16 -> 0 | AA25: =(N25*0.15)+4.5 -> 4.5 | AB25: =S25*AA25 -> 0 | AC25: =Y25+Z25+AB25+D25 -> #N/A | AD25: =N25*S25 -> 0 | AE25: =AD25-AC25 -> #N/A
A26: 2-5 | B26: =【２】結果!I4 -> 0 | T26: =O26 -> 0 | U26: =(P26*Q26*R26)/5000 -> 0 | V26: =MAX(T26,U26) -> 0 | W26: =CEILING(ROUNDDOWN(V26,2),0.5) -> 0 | X26: =VLOOKUP(W26,送料!$J$3:$K$42,2,FALSE) -> #N/A | Y26: =VLOOKUP(X26,送料!$A$1:$B$40,2,FALSE) -> #N/A | Z26: =(N26*S26)*0.16 -> 0 | AA26: =(N26*0.15)+4.5 -> 4.5 | AB26: =S26*AA26 -> 0 | AC26: =Y26+Z26+AB26+D26 -> #N/A | AD26: =N26*S26 -> 0 | AE26: =AD26-AC26 -> #N/A
A27: 2-6 | B27: =【２】結果!J4 -> 0 | T27: =O27 -> 0 | U27: =(P27*Q27*R27)/5000 -> 0 | V27: =MAX(T27,U27) -> 0 | W27: =CEILING(ROUNDDOWN(V27,2),0.5) -> 0 | X27: =VLOOKUP(W27,送料!$J$3:$K$42,2,FALSE) -> #N/A | Y27: =VLOOKUP(X27,送料!$A$1:$B$40,2,FALSE) -> #N/A | Z27: =(N27*S27)*0.16 -> 0 | AA27: =(N27*0.15)+4.5 -> 4.5 | AB27: =S27*AA27 -> 0 | AC27: =Y27+Z27+AB27+D27 -> #N/A | AD27: =N27*S27 -> 0 | AE27: =AD27-AC27 -> #N/A
A28: 2-7 | B28: =【２】結果!K4 -> 0 | T28: =O28 -> 0 | U28: =(P28*Q28*R28)/5000 -> 0 | V28: =MAX(T28,U28) -> 0 | W28: =CEILING(ROUNDDOWN(V28,2),0.5) -> 0 | X28: =VLOOKUP(W28,送料!$J$3:$K$42,2,FALSE) -> #N/A | Y28: =VLOOKUP(X28,送料!$A$1:$B$40,2,FALSE) -> #N/A | Z28: =(N28*S28)*0.16 -> 0 | AA28: =(N28*0.15)+4.5 -> 4.5 | AB28: =S28*AA28 -> 0 | AC28: =Y28+Z28+AB28+D28 -> #N/A | AD28: =N28*S28 -> 0 | AE28: =AD28-AC28 -> #N/A
A29: 2-8 | B29: =【２】結果!L4 -> 0 | T29: =O29 -> 0 | U29: =(P29*Q29*R29)/5000 -> 0 | V29: =MAX(T29,U29) -> 0 | W29: =CEILING(ROUNDDOWN(V29,2),0.5) -> 0 | X29: =VLOOKUP(W29,送料!$J$3:$K$42,2,FALSE) -> #N/A | Y29: =VLOOKUP(X29,送料!$A$1:$B$40,2,FALSE) -> #N/A | Z29: =(N29*S29)*0.16 -> 0 | AA29: =(N29*0.15)+4.5 -> 4.5 | AB29: =S29*AA29 -> 0 | AC29: =Y29+Z29+AB29+D29 -> #N/A | AD29: =N29*S29 -> 0 | AE29: =AD29-AC29 -> #N/A
A30: 2-9 | B30: =【２】結果!M4 -> 0 | T30: =O30 -> 0 | U30: =(P30*Q30*R30)/5000 -> 0 | V30: =MAX(T30,U30) -> 0 | W30: =CEILING(ROUNDDOWN(V30,2),0.5) -> 0 | X30: =VLOOKUP(W30,送料!$J$3:$K$42,2,FALSE) -> #N/A | Y30: =VLOOKUP(X30,送料!$A$1:$B$40,2,FALSE) -> #N/A | Z30: =(N30*S30)*0.16 -> 0 | AA30: =(N30*0.15)+4.5 -> 4.5 | AB30: =S30*AA30 -> 0 | AC30: =Y30+Z30+AB30+D30 -> #N/A | AD30: =N30*S30 -> 0 | AE30: =AD30-AC30 -> #N/A
A31: 2-10 | B31: =【２】結果!N4 -> 0 | T31: =O31 -> 0 | U31: =(P31*Q31*R31)/5000 -> 0 | V31: =MAX(T31,U31) -> 0 | W31: =CEILING(ROUNDDOWN(V31,2),0.5) -> 0 | X31: =VLOOKUP(W31,送料!$J$3:$K$42,2,FALSE) -> #N/A | Y31: =VLOOKUP(X31,送料!$A$1:$B$40,2,FALSE) -> #N/A | Z31: =(N31*S31)*0.16 -> 0 | AA31: =(N31*0.15)+4.5 -> 4.5 | AB31: =S31*AA31 -> 0 | AC31: =Y31+Z31+AB31+D31 -> #N/A | AD31: =N31*S31 -> 0 | AE31: =AD31-AC31 -> #N/A
A32: 2-11 | B32: =【２】結果!O4 -> 0 | T32: =O32 -> 0 | U32: =(P32*Q32*R32)/5000 -> 0 | V32: =MAX(T32,U32) -> 0 | W32: =CEILING(ROUNDDOWN(V32,2),0.5) -> 0 | X32: =VLOOKUP(W32,送料!$J$3:$K$42,2,FALSE) -> #N/A | Y32: =VLOOKUP(X32,送料!$A$1:$B$40,2,FALSE) -> #N/A | Z32: =(N32*S32)*0.16 -> 0 | AA32: =(N32*0.15)+4.5 -> 4.5 | AB32: =S32*AA32 -> 0 | AC32: =Y32+Z32+AB32+D32 -> #N/A | AD32: =N32*S32 -> 0 | AE32: =AD32-AC32 -> #N/A
A33: 2-12 | B33: =【２】結果!P4 -> 0 | T33: =O33 -> 0 | U33: =(P33*Q33*R33)/5000 -> 0 | V33: =MAX(T33,U33) -> 0 | W33: =CEILING(ROUNDDOWN(V33,2),0.5) -> 0 | X33: =VLOOKUP(W33,送料!$J$3:$K$42,2,FALSE) -> #N/A | Y33: =VLOOKUP(X33,送料!$A$1:$B$40,2,FALSE) -> #N/A | Z33: =(N33*S33)*0.16 -> 0 | AA33: =(N33*0.15)+4.5 -> 4.5 | AB33: =S33*AA33 -> 0 | AC33: =Y33+Z33+AB33+D33 -> #N/A | AD33: =N33*S33 -> 0 | AE33: =AD33-AC33 -> #N/A
A34: 2-13 | B34: =【２】結果!Q4 -> 0 | T34: =O34 -> 0 | U34: =(P34*Q34*R34)/5000 -> 0 | V34: =MAX(T34,U34) -> 0 | W34: =CEILING(ROUNDDOWN(V34,2),0.5) -> 0 | X34: =VLOOKUP(W34,送料!$J$3:$K$42,2,FALSE) -> #N/A | Y34: =VLOOKUP(X34,送料!$A$1:$B$40,2,FALSE) -> #N/A | Z34: =(N34*S34)*0.16 -> 0 | AA34: =(N34*0.15)+4.5 -> 4.5 | AB34: =S34*AA34 -> 0 | AC34: =Y34+Z34+AB34+D34 -> #N/A | AD34: =N34*S34 -> 0 | AE34: =AD34-AC34 -> #N/A
A35: 2-14 | B35: =【２】結果!R4 -> 0 | T35: =O35 -> 0 | U35: =(P35*Q35*R35)/5000 -> 0 | V35: =MAX(T35,U35) -> 0 | W35: =CEILING(ROUNDDOWN(V35,2),0.5) -> 0 | X35: =VLOOKUP(W35,送料!$J$3:$K$42,2,FALSE) -> #N/A | Y35: =VLOOKUP(X35,送料!$A$1:$B$40,2,FALSE) -> #N/A | Z35: =(N35*S35)*0.16 -> 0 | AA35: =(N35*0.15)+4.5 -> 4.5 | AB35: =S35*AA35 -> 0 | AC35: =Y35+Z35+AB35+D35 -> #N/A | AD35: =N35*S35 -> 0 | AE35: =AD35-AC35 -> #N/A
A36: 2-15 | B36: =【２】結果!S4 -> 0 | T36: =O36 -> 0 | U36: =(P36*Q36*R36)/5000 -> 0 | V36: =MAX(T36,U36) -> 0 | W36: =CEILING(ROUNDDOWN(V36,2),0.5) -> 0 | X36: =VLOOKUP(W36,送料!$J$3:$K$42,2,FALSE) -> #N/A | Y36: =VLOOKUP(X36,送料!$A$1:$B$40,2,FALSE) -> #N/A | Z36: =(N36*S36)*0.16 -> 0 | AA36: =(N36*0.15)+4.5 -> 4.5 | AB36: =S36*AA36 -> 0 | AC36: =Y36+Z36+AB36+D36 -> #N/A | AD36: =N36*S36 -> 0 | AE36: =AD36-AC36 -> #N/A
A37: 2-16 | B37: =【２】結果!T4 -> 0 | T37: =O37 -> 0 | U37: =(P37*Q37*R37)/5000 -> 0 | V37: =MAX(T37,U37) -> 0 | W37: =CEILING(ROUNDDOWN(V37,2),0.5) -> 0 | X37: =VLOOKUP(W37,送料!$J$3:$K$42,2,FALSE) -> #N/A | Y37: =VLOOKUP(X37,送料!$A$1:$B$40,2,FALSE) -> #N/A | Z37: =(N37*S37)*0.16 -> 0 | AA37: =(N37*0.15)+4.5 -> 4.5 | AB37: =S37*AA37 -> 0 | AC37: =Y37+Z37+AB37+D37 -> #N/A | AD37: =N37*S37 -> 0 | AE37: =AD37-AC37 -> #N/A
A38: 2-17 | B38: =【２】結果!U4 -> 0 | T38: =O38 -> 0 | U38: =(P38*Q38*R38)/5000 -> 0 | V38: =MAX(T38,U38) -> 0 | W38: =CEILING(ROUNDDOWN(V38,2),0.5) -> 0 | X38: =VLOOKUP(W38,送料!$J$3:$K$42,2,FALSE) -> #N/A | Y38: =VLOOKUP(X38,送料!$A$1:$B$40,2,FALSE) -> #N/A | Z38: =(N38*S38)*0.16 -> 0 | AA38: =(N38*0.15)+4.5 -> 4.5 | AB38: =S38*AA38 -> 0 | AC38: =Y38+Z38+AB38+D38 -> #N/A | AD38: =N38*S38 -> 0 | AE38: =AD38-AC38 -> #N/A
A39: 2-18 | B39: =【２】結果!V4 -> 0 | T39: =O39 -> 0 | U39: =(P39*Q39*R39)/5000 -> 0 | V39: =MAX(T39,U39) -> 0 | W39: =CEILING(ROUNDDOWN(V39,2),0.5) -> 0 | X39: =VLOOKUP(W39,送料!$J$3:$K$42,2,FALSE) -> #N/A | Y39: =VLOOKUP(X39,送料!$A$1:$B$40,2,FALSE) -> #N/A | Z39: =(N39*S39)*0.16 -> 0 | AA39: =(N39*0.15)+4.5 -> 4.5 | AB39: =S39*AA39 -> 0 | AC39: =Y39+Z39+AB39+D39 -> #N/A | AD39: =N39*S39 -> 0 | AE39: =AD39-AC39 -> #N/A
A40: 2-19 | B40: =【２】結果!W4 -> 0 | T40: =O40 -> 0 | U40: =(P40*Q40*R40)/5000 -> 0 | V40: =MAX(T40,U40) -> 0 | W40: =CEILING(ROUNDDOWN(V40,2),0.5) -> 0 | X40: =VLOOKUP(W40,送料!$J$3:$K$42,2,FALSE) -> #N/A | Y40: =VLOOKUP(X40,送料!$A$1:$B$40,2,FALSE) -> #N/A | Z40: =(N40*S40)*0.16 -> 0 | AA40: =(N40*0.15)+4.5 -> 4.5 | AB40: =S40*AA40 -> 0 | AC40: =Y40+Z40+AB40+D40 -> #N/A | AD40: =N40*S40 -> 0 | AE40: =AD40-AC40 -> #N/A
A41: 2-20 | B41: =【２】結果!X4 -> 0 | T41: =O41 -> 0 | U41: =(P41*Q41*R41)/5000 -> 0 | V41: =MAX(T41,U41) -> 0 | W41: =CEILING(ROUNDDOWN(V41,2),0.5) -> 0 | X41: =VLOOKUP(W41,送料!$J$3:$K$42,2,FALSE) -> #N/A | Y41: =VLOOKUP(X41,送料!$A$1:$B$40,2,FALSE) -> #N/A | Z41: =(N41*S41)*0.16 -> 0 | AA41: =(N41*0.15)+4.5 -> 4.5 | AB41: =S41*AA41 -> 0 | AC41: =Y41+Z41+AB41+D41 -> #N/A | AD41: =N41*S41 -> 0 | AE41: =AD41-AC41 -> #N/A
A42: 3-1 | B42: =【２】結果!E5 -> 0 | T42: =O42 -> 0 | U42: =(P42*Q42*R42)/5000 -> 0 | V42: =MAX(T42,U42) -> 0 | W42: =CEILING(ROUNDDOWN(V42,2),0.5) -> 0 | X42: =VLOOKUP(W42,送料!$J$3:$K$42,2,FALSE) -> #N/A | Y42: =VLOOKUP(X42,送料!$A$1:$B$40,2,FALSE) -> #N/A | Z42: =(N42*S42)*0.16 -> 0 | AA42: =(N42*0.15)+4.5 -> 4.5 | AB42: =S42*AA42 -> 0 | AC42: =Y42+Z42+AB42+D42 -> #N/A | AD42: =N42*S42 -> 0 | AE42: =AD42-AC42 -> #N/A
A43: 3-2 | B43: =【２】結果!F5 -> 0 | T43: =O43 -> 0 | U43: =(P43*Q43*R43)/5000 -> 0 | V43: =MAX(T43,U43) -> 0 | W43: =CEILING(ROUNDDOWN(V43,2),0.5) -> 0 | X43: =VLOOKUP(W43,送料!$J$3:$K$42,2,FALSE) -> #N/A | Y43: =VLOOKUP(X43,送料!$A$1:$B$40,2,FALSE) -> #N/A | Z43: =(N43*S43)*0.16 -> 0 | AA43: =(N43*0.15)+4.5 -> 4.5 | AB43: =S43*AA43 -> 0 | AC43: =Y43+Z43+AB43+D43 -> #N/A | AD43: =N43*S43 -> 0 | AE43: =AD43-AC43 -> #N/A
A44: 3-3 | B44: =【２】結果!G5 -> 0 | T44: =O44 -> 0 | U44: =(P44*Q44*R44)/5000 -> 0 | V44: =MAX(T44,U44) -> 0 | W44: =CEILING(ROUNDDOWN(V44,2),0.5) -> 0 | X44: =VLOOKUP(W44,送料!$J$3:$K$42,2,FALSE) -> #N/A | Y44: =VLOOKUP(X44,送料!$A$1:$B$40,2,FALSE) -> #N/A | Z44: =(N44*S44)*0.16 -> 0 | AA44: =(N44*0.15)+4.5 -> 4.5 | AB44: =S44*AA44 -> 0 | AC44: =Y44+Z44+AB44+D44 -> #N/A | AD44: =N44*S44 -> 0 | AE44: =AD44-AC44 -> #N/A
A45: 3-4 | B45: =【２】結果!H5 -> 0 | T45: =O45 -> 0 | U45: =(P45*Q45*R45)/5000 -> 0 | V45: =MAX(T45,U45) -> 0 | W45: =CEILING(ROUNDDOWN(V45,2),0.5) -> 0 | X45: =VLOOKUP(W45,送料!$J$3:$K$42,2,FALSE) -> #N/A | Y45: =VLOOKUP(X45,送料!$A$1:$B$40,2,FALSE) -> #N/A | Z45: =(N45*S45)*0.16 -> 0 | AA45: =(N45*0.15)+4.5 -> 4.5 | AB45: =S45*AA45 -> 0 | AC45: =Y45+Z45+AB45+D45 -> #N/A | AD45: =N45*S45 -> 0 | AE45: =AD45-AC45 -> #N/A
A46: 3-5 | B46: =【２】結果!I5 -> 0 | T46: =O46 -> 0 | U46: =(P46*Q46*R46)/5000 -> 0 | V46: =MAX(T46,U46) -> 0 | W46: =CEILING(ROUNDDOWN(V46,2),0.5) -> 0 | X46: =VLOOKUP(W46,送料!$J$3:$K$42,2,FALSE) -> #N/A | Y46: =VLOOKUP(X46,送料!$A$1:$B$40,2,FALSE) -> #N/A | Z46: =(N46*S46)*0.16 -> 0 | AA46: =(N46*0.15)+4.5 -> 4.5 | AB46: =S46*AA46 -> 0 | AC46: =Y46+Z46+AB46+D46 -> #N/A | AD46: =N46*S46 -> 0 | AE46: =AD46-AC46 -> #N/A
A47: 3-6 | B47: =【２】結果!J5 -> 0 | T47: =O47 -> 0 | U47: =(P47*Q47*R47)/5000 -> 0 | V47: =MAX(T47,U47) -> 0 | W47: =CEILING(ROUNDDOWN(V47,2),0.5) -> 0 | X47: =VLOOKUP(W47,送料!$J$3:$K$42,2,FALSE) -> #N/A | Y47: =VLOOKUP(X47,送料!$A$1:$B$40,2,FALSE) -> #N/A | Z47: =(N47*S47)*0.16 -> 0 | AA47: =(N47*0.15)+4.5 -> 4.5 | AB47: =S47*AA47 -> 0 | AC47: =Y47+Z47+AB47+D47 -> #N/A | AD47: =N47*S47 -> 0 | AE47: =AD47-AC47 -> #N/A
A48: 3-7 | B48: =【２】結果!K5 -> 0 | T48: =O48 -> 0 | U48: =(P48*Q48*R48)/5000 -> 0 | V48: =MAX(T48,U48) -> 0 | W48: =CEILING(ROUNDDOWN(V48,2),0.5) -> 0 | X48: =VLOOKUP(W48,送料!$J$3:$K$42,2,FALSE) -> #N/A | Y48: =VLOOKUP(X48,送料!$A$1:$B$40,2,FALSE) -> #N/A | Z48: =(N48*S48)*0.16 -> 0 | AA48: =(N48*0.15)+4.5 -> 4.5 | AB48: =S48*AA48 -> 0 | AC48: =Y48+Z48+AB48+D48 -> #N/A | AD48: =N48*S48 -> 0 | AE48: =AD48-AC48 -> #N/A
A49: 3-8 | B49: =【２】結果!L5 -> 0 | T49: =O49 -> 0 | U49: =(P49*Q49*R49)/5000 -> 0 | V49: =MAX(T49,U49) -> 0 | W49: =CEILING(ROUNDDOWN(V49,2),0.5) -> 0 | X49: =VLOOKUP(W49,送料!$J$3:$K$42,2,FALSE) -> #N/A | Y49: =VLOOKUP(X49,送料!$A$1:$B$40,2,FALSE) -> #N/A | Z49: =(N49*S49)*0.16 -> 0 | AA49: =(N49*0.15)+4.5 -> 4.5 | AB49: =S49*AA49 -> 0 | AC49: =Y49+Z49+AB49+D49 -> #N/A | AD49: =N49*S49 -> 0 | AE49: =AD49-AC49 -> #N/A
A50: 3-9 | B50: =【２】結果!M5 -> 0 | T50: =O50 -> 0 | U50: =(P50*Q50*R50)/5000 -> 0 | V50: =MAX(T50,U50) -> 0 | W50: =CEILING(ROUNDDOWN(V50,2),0.5) -> 0 | X50: =VLOOKUP(W50,送料!$J$3:$K$42,2,FALSE) -> #N/A | Y50: =VLOOKUP(X50,送料!$A$1:$B$40,2,FALSE) -> #N/A | Z50: =(N50*S50)*0.16 -> 0 | AA50: =(N50*0.15)+4.5 -> 4.5 | AB50: =S50*AA50 -> 0 | AC50: =Y50+Z50+AB50+D50 -> #N/A | AD50: =N50*S50 -> 0 | AE50: =AD50-AC50 -> #N/A
A51: 3-10 | B51: =【２】結果!N5 -> 0 | T51: =O51 -> 0 | U51: =(P51*Q51*R51)/5000 -> 0 | V51: =MAX(T51,U51) -> 0 | W51: =CEILING(ROUNDDOWN(V51,2),0.5) -> 0 | X51: =VLOOKUP(W51,送料!$J$3:$K$42,2,FALSE) -> #N/A | Y51: =VLOOKUP(X51,送料!$A$1:$B$40,2,FALSE) -> #N/A | Z51: =(N51*S51)*0.16 -> 0 | AA51: =(N51*0.15)+4.5 -> 4.5 | AB51: =S51*AA51 -> 0 | AC51: =Y51+Z51+AB51+D51 -> #N/A | AD51: =N51*S51 -> 0 | AE51: =AD51-AC51 -> #N/A
A52: 3-11 | B52: =【２】結果!O5 -> 0 | T52: =O52 -> 0 | U52: =(P52*Q52*R52)/5000 -> 0 | V52: =MAX(T52,U52) -> 0 | W52: =CEILING(ROUNDDOWN(V52,2),0.5) -> 0 | X52: =VLOOKUP(W52,送料!$J$3:$K$42,2,FALSE) -> #N/A | Y52: =VLOOKUP(X52,送料!$A$1:$B$40,2,FALSE) -> #N/A | Z52: =(N52*S52)*0.16 -> 0 | AA52: =(N52*0.15)+4.5 -> 4.5 | AB52: =S52*AA52 -> 0 | AC52: =Y52+Z52+AB52+D52 -> #N/A | AD52: =N52*S52 -> 0 | AE52: =AD52-AC52 -> #N/A
A53: 3-12 | B53: =【２】結果!P5 -> 0 | T53: =O53 -> 0 | U53: =(P53*Q53*R53)/5000 -> 0 | V53: =MAX(T53,U53) -> 0 | W53: =CEILING(ROUNDDOWN(V53,2),0.5) -> 0 | X53: =VLOOKUP(W53,送料!$J$3:$K$42,2,FALSE) -> #N/A | Y53: =VLOOKUP(X53,送料!$A$1:$B$40,2,FALSE) -> #N/A | Z53: =(N53*S53)*0.16 -> 0 | AA53: =(N53*0.15)+4.5 -> 4.5 | AB53: =S53*AA53 -> 0 | AC53: =Y53+Z53+AB53+D53 -> #N/A | AD53: =N53*S53 -> 0 | AE53: =AD53-AC53 -> #N/A
A54: 3-13 | B54: =【２】結果!Q5 -> 0 | T54: =O54 -> 0 | U54: =(P54*Q54*R54)/5000 -> 0 | V54: =MAX(T54,U54) -> 0 | W54: =CEILING(ROUNDDOWN(V54,2),0.5) -> 0 | X54: =VLOOKUP(W54,送料!$J$3:$K$42,2,FALSE) -> #N/A | Y54: =VLOOKUP(X54,送料!$A$1:$B$40,2,FALSE) -> #N/A | Z54: =(N54*S54)*0.16 -> 0 | AA54: =(N54*0.15)+4.5 -> 4.5 | AB54: =S54*AA54 -> 0 | AC54: =Y54+Z54+AB54+D54 -> #N/A | AD54: =N54*S54 -> 0 | AE54: =AD54-AC54 -> #N/A
A55: 3-14 | B55: =【２】結果!R5 -> 0 | T55: =O55 -> 0 | U55: =(P55*Q55*R55)/5000 -> 0 | V55: =MAX(T55,U55) -> 0 | W55: =CEILING(ROUNDDOWN(V55,2),0.5) -> 0 | X55: =VLOOKUP(W55,送料!$J$3:$K$42,2,FALSE) -> #N/A | Y55: =VLOOKUP(X55,送料!$A$1:$B$40,2,FALSE) -> #N/A | Z55: =(N55*S55)*0.16 -> 0 | AA55: =(N55*0.15)+4.5 -> 4.5 | AB55: =S55*AA55 -> 0 | AC55: =Y55+Z55+AB55+D55 -> #N/A | AD55: =N55*S55 -> 0 | AE55: =AD55-AC55 -> #N/A
A56: 3-15 | B56: =【２】結果!S5 -> 0 | T56: =O56 -> 0 | U56: =(P56*Q56*R56)/5000 -> 0 | V56: =MAX(T56,U56) -> 0 | W56: =CEILING(ROUNDDOWN(V56,2),0.5) -> 0 | X56: =VLOOKUP(W56,送料!$J$3:$K$42,2,FALSE) -> #N/A | Y56: =VLOOKUP(X56,送料!$A$1:$B$40,2,FALSE) -> #N/A | Z56: =(N56*S56)*0.16 -> 0 | AA56: =(N56*0.15)+4.5 -> 4.5 | AB56: =S56*AA56 -> 0 | AC56: =Y56+Z56+AB56+D56 -> #N/A | AD56: =N56*S56 -> 0 | AE56: =AD56-AC56 -> #N/A
A57: 3-16 | B57: =【２】結果!T5 -> 0 | T57: =O57 -> 0 | U57: =(P57*Q57*R57)/5000 -> 0 | V57: =MAX(T57,U57) -> 0 | W57: =CEILING(ROUNDDOWN(V57,2),0.5) -> 0 | X57: =VLOOKUP(W57,送料!$J$3:$K$42,2,FALSE) -> #N/A | Y57: =VLOOKUP(X57,送料!$A$1:$B$40,2,FALSE) -> #N/A | Z57: =(N57*S57)*0.16 -> 0 | AA57: =(N57*0.15)+4.5 -> 4.5 | AB57: =S57*AA57 -> 0 | AC57: =Y57+Z57+AB57+D57 -> #N/A | AD57: =N57*S57 -> 0 | AE57: =AD57-AC57 -> #N/A
A58: 3-17 | B58: =【２】結果!U5 -> 0 | T58: =O58 -> 0 | U58: =(P58*Q58*R58)/5000 -> 0 | V58: =MAX(T58,U58) -> 0 | W58: =CEILING(ROUNDDOWN(V58,2),0.5) -> 0 | X58: =VLOOKUP(W58,送料!$J$3:$K$42,2,FALSE) -> #N/A | Y58: =VLOOKUP(X58,送料!$A$1:$B$40,2,FALSE) -> #N/A | Z58: =(N58*S58)*0.16 -> 0 | AA58: =(N58*0.15)+4.5 -> 4.5 | AB58: =S58*AA58 -> 0 | AC58: =Y58+Z58+AB58+D58 -> #N/A | AD58: =N58*S58 -> 0 | AE58: =AD58-AC58 -> #N/A
A59: 3-18 | B59: =【２】結果!V5 -> 0 | T59: =O59 -> 0 | U59: =(P59*Q59*R59)/5000 -> 0 | V59: =MAX(T59,U59) -> 0 | W59: =CEILING(ROUNDDOWN(V59,2),0.5) -> 0 | X59: =VLOOKUP(W59,送料!$J$3:$K$42,2,FALSE) -> #N/A | Y59: =VLOOKUP(X59,送料!$A$1:$B$40,2,FALSE) -> #N/A | Z59: =(N59*S59)*0.16 -> 0 | AA59: =(N59*0.15)+4.5 -> 4.5 | AB59: =S59*AA59 -> 0 | AC59: =Y59+Z59+AB59+D59 -> #N/A | AD59: =N59*S59 -> 0 | AE59: =AD59-AC59 -> #N/A
A60: 3-19 | B60: =【２】結果!W5 -> 0 | T60: =O60 -> 0 | U60: =(P60*Q60*R60)/5000 -> 0 | V60: =MAX(T60,U60) -> 0 | W60: =CEILING(ROUNDDOWN(V60,2),0.5) -> 0 | X60: =VLOOKUP(W60,送料!$J$3:$K$42,2,FALSE) -> #N/A | Y60: =VLOOKUP(X60,送料!$A$1:$B$40,2,FALSE) -> #N/A | Z60: =(N60*S60)*0.16 -> 0 | AA60: =(N60*0.15)+4.5 -> 4.5 | AB60: =S60*AA60 -> 0 | AC60: =Y60+Z60+AB60+D60 -> #N/A | AD60: =N60*S60 -> 0 | AE60: =AD60-AC60 -> #N/A
A61: 3-20 | B61: =【２】結果!X5 -> 0 | T61: =O61 -> 0 | U61: =(P61*Q61*R61)/5000 -> 0 | V61: =MAX(T61,U61) -> 0 | W61: =CEILING(ROUNDDOWN(V61,2),0.5) -> 0 | X61: =VLOOKUP(W61,送料!$J$3:$K$42,2,FALSE) -> #N/A | Y61: =VLOOKUP(X61,送料!$A$1:$B$40,2,FALSE) -> #N/A | Z61: =(N61*S61)*0.16 -> 0 | AA61: =(N61*0.15)+4.5 -> 4.5 | AB61: =S61*AA61 -> 0 | AC61: =Y61+Z61+AB61+D61 -> #N/A | AD61: =N61*S61 -> 0 | AE61: =AD61-AC61 -> #N/A
A62: 4-1 | B62: =【２】結果!E6 -> 0 | T62: =O62 -> 0 | U62: =(P62*Q62*R62)/5000 -> 0 | V62: =MAX(T62,U62) -> 0 | W62: =CEILING(ROUNDDOWN(V62,2),0.5) -> 0 | X62: =VLOOKUP(W62,送料!$J$3:$K$42,2,FALSE) -> #N/A | Y62: =VLOOKUP(X62,送料!$A$1:$B$40,2,FALSE) -> #N/A | Z62: =(N62*S62)*0.16 -> 0 | AA62: =(N62*0.15)+4.5 -> 4.5 | AB62: =S62*AA62 -> 0 | AC62: =Y62+Z62+AB62+D62 -> #N/A | AD62: =N62*S62 -> 0 | AE62: =AD62-AC62 -> #N/A
A63: 4-2 | B63: =【２】結果!F6 -> 0 | T63: =O63 -> 0 | U63: =(P63*Q63*R63)/5000 -> 0 | V63: =MAX(T63,U63) -> 0 | W63: =CEILING(ROUNDDOWN(V63,2),0.5) -> 0 | X63: =VLOOKUP(W63,送料!$J$3:$K$42,2,FALSE) -> #N/A | Y63: =VLOOKUP(X63,送料!$A$1:$B$40,2,FALSE) -> #N/A | Z63: =(N63*S63)*0.16 -> 0 | AA63: =(N63*0.15)+4.5 -> 4.5 | AB63: =S63*AA63 -> 0 | AC63: =Y63+Z63+AB63+D63 -> #N/A | AD63: =N63*S63 -> 0 | AE63: =AD63-AC63 -> #N/A
A64: 4-3 | B64: =【２】結果!G6 -> 0 | T64: =O64 -> 0 | U64: =(P64*Q64*R64)/5000 -> 0 | V64: =MAX(T64,U64) -> 0 | W64: =CEILING(ROUNDDOWN(V64,2),0.5) -> 0 | X64: =VLOOKUP(W64,送料!$J$3:$K$42,2,FALSE) -> #N/A | Y64: =VLOOKUP(X64,送料!$A$1:$B$40,2,FALSE) -> #N/A | Z64: =(N64*S64)*0.16 -> 0 | AA64: =(N64*0.15)+4.5 -> 4.5 | AB64: =S64*AA64 -> 0 | AC64: =Y64+Z64+AB64+D64 -> #N/A | AD64: =N64*S64 -> 0 | AE64: =AD64-AC64 -> #N/A
A65: 4-4 | B65: =【２】結果!H6 -> 0 | T65: =O65 -> 0 | U65: =(P65*Q65*R65)/5000 -> 0 | V65: =MAX(T65,U65) -> 0 | W65: =CEILING(ROUNDDOWN(V65,2),0.5) -> 0 | X65: =VLOOKUP(W65,送料!$J$3:$K$42,2,FALSE) -> #N/A | Y65: =VLOOKUP(X65,送料!$A$1:$B$40,2,FALSE) -> #N/A | Z65: =(N65*S65)*0.16 -> 0 | AA65: =(N65*0.15)+4.5 -> 4.5 | AB65: =S65*AA65 -> 0 | AC65: =Y65+Z65+AB65+D65 -> #N/A | AD65: =N65*S65 -> 0 | AE65: =AD65-AC65 -> #N/A
A66: 4-5 | B66: =【２】結果!I6 -> 0 | T66: =O66 -> 0 | U66: =(P66*Q66*R66)/5000 -> 0 | V66: =MAX(T66,U66) -> 0 | W66: =CEILING(ROUNDDOWN(V66,2),0.5) -> 0 | X66: =VLOOKUP(W66,送料!$J$3:$K$42,2,FALSE) -> #N/A | Y66: =VLOOKUP(X66,送料!$A$1:$B$40,2,FALSE) -> #N/A | Z66: =(N66*S66)*0.16 -> 0 | AA66: =(N66*0.15)+4.5 -> 4.5 | AB66: =S66*AA66 -> 0 | AC66: =Y66+Z66+AB66+D66 -> #N/A | AD66: =N66*S66 -> 0 | AE66: =AD66-AC66 -> #N/A
A67: 4-6 | B67: =【２】結果!J6 -> 0 | T67: =O67 -> 0 | U67: =(P67*Q67*R67)/5000 -> 0 | V67: =MAX(T67,U67) -> 0 | W67: =CEILING(ROUNDDOWN(V67,2),0.5) -> 0 | X67: =VLOOKUP(W67,送料!$J$3:$K$42,2,FALSE) -> #N/A | Y67: =VLOOKUP(X67,送料!$A$1:$B$40,2,FALSE) -> #N/A | Z67: =(N67*S67)*0.16 -> 0 | AA67: =(N67*0.15)+4.5 -> 4.5 | AB67: =S67*AA67 -> 0 | AC67: =Y67+Z67+AB67+D67 -> #N/A | AD67: =N67*S67 -> 0 | AE67: =AD67-AC67 -> #N/A
A68: 4-7 | B68: =【２】結果!K6 -> 0 | T68: =O68 -> 0 | U68: =(P68*Q68*R68)/5000 -> 0 | V68: =MAX(T68,U68) -> 0 | W68: =CEILING(ROUNDDOWN(V68,2),0.5) -> 0 | X68: =VLOOKUP(W68,送料!$J$3:$K$42,2,FALSE) -> #N/A | Y68: =VLOOKUP(X68,送料!$A$1:$B$40,2,FALSE) -> #N/A | Z68: =(N68*S68)*0.16 -> 0 | AA68: =(N68*0.15)+4.5 -> 4.5 | AB68: =S68*AA68 -> 0 | AC68: =Y68+Z68+AB68+D68 -> #N/A | AD68: =N68*S68 -> 0 | AE68: =AD68-AC68 -> #N/A
A69: 4-8 | B69: =【２】結果!L6 -> 0 | T69: =O69 -> 0 | U69: =(P69*Q69*R69)/5000 -> 0 | V69: =MAX(T69,U69) -> 0 | W69: =CEILING(ROUNDDOWN(V69,2),0.5) -> 0 | X69: =VLOOKUP(W69,送料!$J$3:$K$42,2,FALSE) -> #N/A | Y69: =VLOOKUP(X69,送料!$A$1:$B$40,2,FALSE) -> #N/A | Z69: =(N69*S69)*0.16 -> 0 | AA69: =(N69*0.15)+4.5 -> 4.5 | AB69: =S69*AA69 -> 0 | AC69: =Y69+Z69+AB69+D69 -> #N/A | AD69: =N69*S69 -> 0 | AE69: =AD69-AC69 -> #N/A
A70: 4-9 | B70: =【２】結果!M6 -> 0 | T70: =O70 -> 0 | U70: =(P70*Q70*R70)/5000 -> 0 | V70: =MAX(T70,U70) -> 0 | W70: =CEILING(ROUNDDOWN(V70,2),0.5) -> 0 | X70: =VLOOKUP(W70,送料!$J$3:$K$42,2,FALSE) -> #N/A | Y70: =VLOOKUP(X70,送料!$A$1:$B$40,2,FALSE) -> #N/A | Z70: =(N70*S70)*0.16 -> 0 | AA70: =(N70*0.15)+4.5 -> 4.5 | AB70: =S70*AA70 -> 0 | AC70: =Y70+Z70+AB70+D70 -> #N/A | AD70: =N70*S70 -> 0 | AE70: =AD70-AC70 -> #N/A
A71: 4-10 | B71: =【２】結果!N6 -> 0 | T71: =O71 -> 0 | U71: =(P71*Q71*R71)/5000 -> 0 | V71: =MAX(T71,U71) -> 0 | W71: =CEILING(ROUNDDOWN(V71,2),0.5) -> 0 | X71: =VLOOKUP(W71,送料!$J$3:$K$42,2,FALSE) -> #N/A | Y71: =VLOOKUP(X71,送料!$A$1:$B$40,2,FALSE) -> #N/A | Z71: =(N71*S71)*0.16 -> 0 | AA71: =(N71*0.15)+4.5 -> 4.5 | AB71: =S71*AA71 -> 0 | AC71: =Y71+Z71+AB71+D71 -> #N/A | AD71: =N71*S71 -> 0 | AE71: =AD71-AC71 -> #N/A
A72: 4-11 | B72: =【２】結果!O6 -> 0 | T72: =O72 -> 0 | U72: =(P72*Q72*R72)/5000 -> 0 | V72: =MAX(T72,U72) -> 0 | W72: =CEILING(ROUNDDOWN(V72,2),0.5) -> 0 | X72: =VLOOKUP(W72,送料!$J$3:$K$42,2,FALSE) -> #N/A | Y72: =VLOOKUP(X72,送料!$A$1:$B$40,2,FALSE) -> #N/A | Z72: =(N72*S72)*0.16 -> 0 | AA72: =(N72*0.15)+4.5 -> 4.5 | AB72: =S72*AA72 -> 0 | AC72: =Y72+Z72+AB72+D72 -> #N/A | AD72: =N72*S72 -> 0 | AE72: =AD72-AC72 -> #N/A
A73: 4-12 | B73: =【２】結果!P6 -> 0 | T73: =O73 -> 0 | U73: =(P73*Q73*R73)/5000 -> 0 | V73: =MAX(T73,U73) -> 0 | W73: =CEILING(ROUNDDOWN(V73,2),0.5) -> 0 | X73: =VLOOKUP(W73,送料!$J$3:$K$42,2,FALSE) -> #N/A | Y73: =VLOOKUP(X73,送料!$A$1:$B$40,2,FALSE) -> #N/A | Z73: =(N73*S73)*0.16 -> 0 | AA73: =(N73*0.15)+4.5 -> 4.5 | AB73: =S73*AA73 -> 0 | AC73: =Y73+Z73+AB73+D73 -> #N/A | AD73: =N73*S73 -> 0 | AE73: =AD73-AC73 -> #N/A
A74: 4-13 | B74: =【２】結果!Q6 -> 0 | T74: =O74 -> 0 | U74: =(P74*Q74*R74)/5000 -> 0 | V74: =MAX(T74,U74) -> 0 | W74: =CEILING(ROUNDDOWN(V74,2),0.5) -> 0 | X74: =VLOOKUP(W74,送料!$J$3:$K$42,2,FALSE) -> #N/A | Y74: =VLOOKUP(X74,送料!$A$1:$B$40,2,FALSE) -> #N/A | Z74: =(N74*S74)*0.16 -> 0 | AA74: =(N74*0.15)+4.5 -> 4.5 | AB74: =S74*AA74 -> 0 | AC74: =Y74+Z74+AB74+D74 -> #N/A | AD74: =N74*S74 -> 0 | AE74: =AD74-AC74 -> #N/A
A75: 4-14 | B75: =【２】結果!R6 -> 0 | T75: =O75 -> 0 | U75: =(P75*Q75*R75)/5000 -> 0 | V75: =MAX(T75,U75) -> 0 | W75: =CEILING(ROUNDDOWN(V75,2),0.5) -> 0 | X75: =VLOOKUP(W75,送料!$J$3:$K$42,2,FALSE) -> #N/A | Y75: =VLOOKUP(X75,送料!$A$1:$B$40,2,FALSE) -> #N/A | Z75: =(N75*S75)*0.16 -> 0 | AA75: =(N75*0.15)+4.5 -> 4.5 | AB75: =S75*AA75 -> 0 | AC75: =Y75+Z75+AB75+D75 -> #N/A | AD75: =N75*S75 -> 0 | AE75: =AD75-AC75 -> #N/A
A76: 4-15 | B76: =【２】結果!S6 -> 0 | T76: =O76 -> 0 | U76: =(P76*Q76*R76)/5000 -> 0 | V76: =MAX(T76,U76) -> 0 | W76: =CEILING(ROUNDDOWN(V76,2),0.5) -> 0 | X76: =VLOOKUP(W76,送料!$J$3:$K$42,2,FALSE) -> #N/A | Y76: =VLOOKUP(X76,送料!$A$1:$B$40,2,FALSE) -> #N/A | Z76: =(N76*S76)*0.16 -> 0 | AA76: =(N76*0.15)+4.5 -> 4.5 | AB76: =S76*AA76 -> 0 | AC76: =Y76+Z76+AB76+D76 -> #N/A | AD76: =N76*S76 -> 0 | AE76: =AD76-AC76 -> #N/A
A77: 4-16 | B77: =【２】結果!T6 -> 0 | T77: =O77 -> 0 | U77: =(P77*Q77*R77)/5000 -> 0 | V77: =MAX(T77,U77) -> 0 | W77: =CEILING(ROUNDDOWN(V77,2),0.5) -> 0 | X77: =VLOOKUP(W77,送料!$J$3:$K$42,2,FALSE) -> #N/A | Y77: =VLOOKUP(X77,送料!$A$1:$B$40,2,FALSE) -> #N/A | Z77: =(N77*S77)*0.16 -> 0 | AA77: =(N77*0.15)+4.5 -> 4.5 | AB77: =S77*AA77 -> 0 | AC77: =Y77+Z77+AB77+D77 -> #N/A | AD77: =N77*S77 -> 0 | AE77: =AD77-AC77 -> #N/A
A78: 4-17 | B78: =【２】結果!U6 -> 0 | T78: =O78 -> 0 | U78: =(P78*Q78*R78)/5000 -> 0 | V78: =MAX(T78,U78) -> 0 | W78: =CEILING(ROUNDDOWN(V78,2),0.5) -> 0 | X78: =VLOOKUP(W78,送料!$J$3:$K$42,2,FALSE) -> #N/A | Y78: =VLOOKUP(X78,送料!$A$1:$B$40,2,FALSE) -> #N/A | Z78: =(N78*S78)*0.16 -> 0 | AA78: =(N78*0.15)+4.5 -> 4.5 | AB78: =S78*AA78 -> 0 | AC78: =Y78+Z78+AB78+D78 -> #N/A | AD78: =N78*S78 -> 0 | AE78: =AD78-AC78 -> #N/A
A79: 4-18 | B79: =【２】結果!V6 -> 0 | T79: =O79 -> 0 | U79: =(P79*Q79*R79)/5000 -> 0 | V79: =MAX(T79,U79) -> 0 | W79: =CEILING(ROUNDDOWN(V79,2),0.5) -> 0 | X79: =VLOOKUP(W79,送料!$J$3:$K$42,2,FALSE) -> #N/A | Y79: =VLOOKUP(X79,送料!$A$1:$B$40,2,FALSE) -> #N/A | Z79: =(N79*S79)*0.16 -> 0 | AA79: =(N79*0.15)+4.5 -> 4.5 | AB79: =S79*AA79 -> 0 | AC79: =Y79+Z79+AB79+D79 -> #N/A | AD79: =N79*S79 -> 0 | AE79: =AD79-AC79 -> #N/A
A80: 4-19 | B80: =【２】結果!W6 -> 0 | T80: =O80 -> 0 | U80: =(P80*Q80*R80)/5000 -> 0 | V80: =MAX(T80,U80) -> 0 | W80: =CEILING(ROUNDDOWN(V80,2),0.5) -> 0 | X80: =VLOOKUP(W80,送料!$J$3:$K$42,2,FALSE) -> #N/A | Y80: =VLOOKUP(X80,送料!$A$1:$B$40,2,FALSE) -> #N/A | Z80: =(N80*S80)*0.16 -> 0 | AA80: =(N80*0.15)+4.5 -> 4.5 | AB80: =S80*AA80 -> 0 | AC80: =Y80+Z80+AB80+D80 -> #N/A | AD80: =N80*S80 -> 0 | AE80: =AD80-AC80 -> #N/A
A81: 4-20 | B81: =【２】結果!X6 -> 0 | T81: =O81 -> 0 | U81: =(P81*Q81*R81)/5000 -> 0 | V81: =MAX(T81,U81) -> 0 | W81: =CEILING(ROUNDDOWN(V81,2),0.5) -> 0 | X81: =VLOOKUP(W81,送料!$J$3:$K$42,2,FALSE) -> #N/A | Y81: =VLOOKUP(X81,送料!$A$1:$B$40,2,FALSE) -> #N/A | Z81: =(N81*S81)*0.16 -> 0 | AA81: =(N81*0.15)+4.5 -> 4.5 | AB81: =S81*AA81 -> 0 | AC81: =Y81+Z81+AB81+D81 -> #N/A | AD81: =N81*S81 -> 0 | AE81: =AD81-AC81 -> #N/A
A82: 5-1 | B82: =【２】結果!E7 -> 0 | T82: =O82 -> 0 | U82: =(P82*Q82*R82)/5000 -> 0 | V82: =MAX(T82,U82) -> 0 | W82: =CEILING(ROUNDDOWN(V82,2),0.5) -> 0 | X82: =VLOOKUP(W82,送料!$J$3:$K$42,2,FALSE) -> #N/A | Y82: =VLOOKUP(X82,送料!$A$1:$B$40,2,FALSE) -> #N/A | Z82: =(N82*S82)*0.16 -> 0 | AA82: =(N82*0.15)+4.5 -> 4.5 | AB82: =S82*AA82 -> 0 | AC82: =Y82+Z82+AB82+D82 -> #N/A | AD82: =N82*S82 -> 0 | AE82: =AD82-AC82 -> #N/A
A83: 5-2 | B83: =【２】結果!F7 -> 0 | T83: =O83 -> 0 | U83: =(P83*Q83*R83)/5000 -> 0 | V83: =MAX(T83,U83) -> 0 | W83: =CEILING(ROUNDDOWN(V83,2),0.5) -> 0 | X83: =VLOOKUP(W83,送料!$J$3:$K$42,2,FALSE) -> #N/A | Y83: =VLOOKUP(X83,送料!$A$1:$B$40,2,FALSE) -> #N/A | Z83: =(N83*S83)*0.16 -> 0 | AA83: =(N83*0.15)+4.5 -> 4.5 | AB83: =S83*AA83 -> 0 | AC83: =Y83+Z83+AB83+D83 -> #N/A | AD83: =N83*S83 -> 0 | AE83: =AD83-AC83 -> #N/A
A84: 5-3 | B84: =【２】結果!G7 -> 0 | T84: =O84 -> 0 | U84: =(P84*Q84*R84)/5000 -> 0 | V84: =MAX(T84,U84) -> 0 | W84: =CEILING(ROUNDDOWN(V84,2),0.5) -> 0 | X84: =VLOOKUP(W84,送料!$J$3:$K$42,2,FALSE) -> #N/A | Y84: =VLOOKUP(X84,送料!$A$1:$B$40,2,FALSE) -> #N/A | Z84: =(N84*S84)*0.16 -> 0 | AA84: =(N84*0.15)+4.5 -> 4.5 | AB84: =S84*AA84 -> 0 | AC84: =Y84+Z84+AB84+D84 -> #N/A | AD84: =N84*S84 -> 0 | AE84: =AD84-AC84 -> #N/A
A85: 5-4 | B85: =【２】結果!H7 -> 0 | T85: =O85 -> 0 | U85: =(P85*Q85*R85)/5000 -> 0 | V85: =MAX(T85,U85) -> 0 | W85: =CEILING(ROUNDDOWN(V85,2),0.5) -> 0 | X85: =VLOOKUP(W85,送料!$J$3:$K$42,2,FALSE) -> #N/A | Y85: =VLOOKUP(X85,送料!$A$1:$B$40,2,FALSE) -> #N/A | Z85: =(N85*S85)*0.16 -> 0 | AA85: =(N85*0.15)+4.5 -> 4.5 | AB85: =S85*AA85 -> 0 | AC85: =Y85+Z85+AB85+D85 -> #N/A | AD85: =N85*S85 -> 0 | AE85: =AD85-AC85 -> #N/A
A86: 5-5 | B86: =【２】結果!I7 -> 0 | T86: =O86 -> 0 | U86: =(P86*Q86*R86)/5000 -> 0 | V86: =MAX(T86,U86) -> 0 | W86: =CEILING(ROUNDDOWN(V86,2),0.5) -> 0 | X86: =VLOOKUP(W86,送料!$J$3:$K$42,2,FALSE) -> #N/A | Y86: =VLOOKUP(X86,送料!$A$1:$B$40,2,FALSE) -> #N/A | Z86: =(N86*S86)*0.16 -> 0 | AA86: =(N86*0.15)+4.5 -> 4.5 | AB86: =S86*AA86 -> 0 | AC86: =Y86+Z86+AB86+D86 -> #N/A | AD86: =N86*S86 -> 0 | AE86: =AD86-AC86 -> #N/A
A87: 5-6 | B87: =【２】結果!J7 -> 0 | T87: =O87 -> 0 | U87: =(P87*Q87*R87)/5000 -> 0 | V87: =MAX(T87,U87) -> 0 | W87: =CEILING(ROUNDDOWN(V87,2),0.5) -> 0 | X87: =VLOOKUP(W87,送料!$J$3:$K$42,2,FALSE) -> #N/A | Y87: =VLOOKUP(X87,送料!$A$1:$B$40,2,FALSE) -> #N/A | Z87: =(N87*S87)*0.16 -> 0 | AA87: =(N87*0.15)+4.5 -> 4.5 | AB87: =S87*AA87 -> 0 | AC87: =Y87+Z87+AB87+D87 -> #N/A | AD87: =N87*S87 -> 0 | AE87: =AD87-AC87 -> #N/A
A88: 5-7 | B88: =【２】結果!K7 -> 0 | T88: =O88 -> 0 | U88: =(P88*Q88*R88)/5000 -> 0 | V88: =MAX(T88,U88) -> 0 | W88: =CEILING(ROUNDDOWN(V88,2),0.5) -> 0 | X88: =VLOOKUP(W88,送料!$J$3:$K$42,2,FALSE) -> #N/A | Y88: =VLOOKUP(X88,送料!$A$1:$B$40,2,FALSE) -> #N/A | Z88: =(N88*S88)*0.16 -> 0 | AA88: =(N88*0.15)+4.5 -> 4.5 | AB88: =S88*AA88 -> 0 | AC88: =Y88+Z88+AB88+D88 -> #N/A | AD88: =N88*S88 -> 0 | AE88: =AD88-AC88 -> #N/A
A89: 5-8 | B89: =【２】結果!L7 -> 0 | T89: =O89 -> 0 | U89: =(P89*Q89*R89)/5000 -> 0 | V89: =MAX(T89,U89) -> 0 | W89: =CEILING(ROUNDDOWN(V89,2),0.5) -> 0 | X89: =VLOOKUP(W89,送料!$J$3:$K$42,2,FALSE) -> #N/A | Y89: =VLOOKUP(X89,送料!$A$1:$B$40,2,FALSE) -> #N/A | Z89: =(N89*S89)*0.16 -> 0 | AA89: =(N89*0.15)+4.5 -> 4.5 | AB89: =S89*AA89 -> 0 | AC89: =Y89+Z89+AB89+D89 -> #N/A | AD89: =N89*S89 -> 0 | AE89: =AD89-AC89 -> #N/A
A90: 5-9 | B90: =【２】結果!M7 -> 0 | T90: =O90 -> 0 | U90: =(P90*Q90*R90)/5000 -> 0 | V90: =MAX(T90,U90) -> 0 | W90: =CEILING(ROUNDDOWN(V90,2),0.5) -> 0 | X90: =VLOOKUP(W90,送料!$J$3:$K$42,2,FALSE) -> #N/A | Y90: =VLOOKUP(X90,送料!$A$1:$B$40,2,FALSE) -> #N/A | Z90: =(N90*S90)*0.16 -> 0 | AA90: =(N90*0.15)+4.5 -> 4.5 | AB90: =S90*AA90 -> 0 | AC90: =Y90+Z90+AB90+D90 -> #N/A | AD90: =N90*S90 -> 0 | AE90: =AD90-AC90 -> #N/A
A91: 5-10 | B91: =【２】結果!N7 -> 0 | T91: =O91 -> 0 | U91: =(P91*Q91*R91)/5000 -> 0 | V91: =MAX(T91,U91) -> 0 | W91: =CEILING(ROUNDDOWN(V91,2),0.5) -> 0 | X91: =VLOOKUP(W91,送料!$J$3:$K$42,2,FALSE) -> #N/A | Y91: =VLOOKUP(X91,送料!$A$1:$B$40,2,FALSE) -> #N/A | Z91: =(N91*S91)*0.16 -> 0 | AA91: =(N91*0.15)+4.5 -> 4.5 | AB91: =S91*AA91 -> 0 | AC91: =Y91+Z91+AB91+D91 -> #N/A | AD91: =N91*S91 -> 0 | AE91: =AD91-AC91 -> #N/A
A92: 5-11 | B92: =【２】結果!O7 -> 0 | T92: =O92 -> 0 | U92: =(P92*Q92*R92)/5000 -> 0 | V92: =MAX(T92,U92) -> 0 | W92: =CEILING(ROUNDDOWN(V92,2),0.5) -> 0 | X92: =VLOOKUP(W92,送料!$J$3:$K$42,2,FALSE) -> #N/A | Y92: =VLOOKUP(X92,送料!$A$1:$B$40,2,FALSE) -> #N/A | Z92: =(N92*S92)*0.16 -> 0 | AA92: =(N92*0.15)+4.5 -> 4.5 | AB92: =S92*AA92 -> 0 | AC92: =Y92+Z92+AB92+D92 -> #N/A | AD92: =N92*S92 -> 0 | AE92: =AD92-AC92 -> #N/A
A93: 5-12 | B93: =【２】結果!P7 -> 0 | T93: =O93 -> 0 | U93: =(P93*Q93*R93)/5000 -> 0 | V93: =MAX(T93,U93) -> 0 | W93: =CEILING(ROUNDDOWN(V93,2),0.5) -> 0 | X93: =VLOOKUP(W93,送料!$J$3:$K$42,2,FALSE) -> #N/A | Y93: =VLOOKUP(X93,送料!$A$1:$B$40,2,FALSE) -> #N/A | Z93: =(N93*S93)*0.16 -> 0 | AA93: =(N93*0.15)+4.5 -> 4.5 | AB93: =S93*AA93 -> 0 | AC93: =Y93+Z93+AB93+D93 -> #N/A | AD93: =N93*S93 -> 0 | AE93: =AD93-AC93 -> #N/A
A94: 5-13 | B94: =【２】結果!Q7 -> 0 | T94: =O94 -> 0 | U94: =(P94*Q94*R94)/5000 -> 0 | V94: =MAX(T94,U94) -> 0 | W94: =CEILING(ROUNDDOWN(V94,2),0.5) -> 0 | X94: =VLOOKUP(W94,送料!$J$3:$K$42,2,FALSE) -> #N/A | Y94: =VLOOKUP(X94,送料!$A$1:$B$40,2,FALSE) -> #N/A | Z94: =(N94*S94)*0.16 -> 0 | AA94: =(N94*0.15)+4.5 -> 4.5 | AB94: =S94*AA94 -> 0 | AC94: =Y94+Z94+AB94+D94 -> #N/A | AD94: =N94*S94 -> 0 | AE94: =AD94-AC94 -> #N/A
A95: 5-14 | B95: =【２】結果!R7 -> 0 | T95: =O95 -> 0 | U95: =(P95*Q95*R95)/5000 -> 0 | V95: =MAX(T95,U95) -> 0 | W95: =CEILING(ROUNDDOWN(V95,2),0.5) -> 0 | X95: =VLOOKUP(W95,送料!$J$3:$K$42,2,FALSE) -> #N/A | Y95: =VLOOKUP(X95,送料!$A$1:$B$40,2,FALSE) -> #N/A | Z95: =(N95*S95)*0.16 -> 0 | AA95: =(N95*0.15)+4.5 -> 4.5 | AB95: =S95*AA95 -> 0 | AC95: =Y95+Z95+AB95+D95 -> #N/A | AD95: =N95*S95 -> 0 | AE95: =AD95-AC95 -> #N/A
A96: 5-15 | B96: =【２】結果!S7 -> 0 | T96: =O96 -> 0 | U96: =(P96*Q96*R96)/5000 -> 0 | V96: =MAX(T96,U96) -> 0 | W96: =CEILING(ROUNDDOWN(V96,2),0.5) -> 0 | X96: =VLOOKUP(W96,送料!$J$3:$K$42,2,FALSE) -> #N/A | Y96: =VLOOKUP(X96,送料!$A$1:$B$40,2,FALSE) -> #N/A | Z96: =(N96*S96)*0.16 -> 0 | AA96: =(N96*0.15)+4.5 -> 4.5 | AB96: =S96*AA96 -> 0 | AC96: =Y96+Z96+AB96+D96 -> #N/A | AD96: =N96*S96 -> 0 | AE96: =AD96-AC96 -> #N/A
A97: 5-16 | B97: =【２】結果!T7 -> 0 | T97: =O97 -> 0 | U97: =(P97*Q97*R97)/5000 -> 0 | V97: =MAX(T97,U97) -> 0 | W97: =CEILING(ROUNDDOWN(V97,2),0.5) -> 0 | X97: =VLOOKUP(W97,送料!$J$3:$K$42,2,FALSE) -> #N/A | Y97: =VLOOKUP(X97,送料!$A$1:$B$40,2,FALSE) -> #N/A | Z97: =(N97*S97)*0.16 -> 0 | AA97: =(N97*0.15)+4.5 -> 4.5 | AB97: =S97*AA97 -> 0 | AC97: =Y97+Z97+AB97+D97 -> #N/A | AD97: =N97*S97 -> 0 | AE97: =AD97-AC97 -> #N/A
A98: 5-17 | B98: =【２】結果!U7 -> 0 | T98: =O98 -> 0 | U98: =(P98*Q98*R98)/5000 -> 0 | V98: =MAX(T98,U98) -> 0 | W98: =CEILING(ROUNDDOWN(V98,2),0.5) -> 0 | X98: =VLOOKUP(W98,送料!$J$3:$K$42,2,FALSE) -> #N/A | Y98: =VLOOKUP(X98,送料!$A$1:$B$40,2,FALSE) -> #N/A | Z98: =(N98*S98)*0.16 -> 0 | AA98: =(N98*0.15)+4.5 -> 4.5 | AB98: =S98*AA98 -> 0 | AC98: =Y98+Z98+AB98+D98 -> #N/A | AD98: =N98*S98 -> 0 | AE98: =AD98-AC98 -> #N/A
A99: 5-18 | B99: =【２】結果!V7 -> 0 | T99: =O99 -> 0 | U99: =(P99*Q99*R99)/5000 -> 0 | V99: =MAX(T99,U99) -> 0 | W99: =CEILING(ROUNDDOWN(V99,2),0.5) -> 0 | X99: =VLOOKUP(W99,送料!$J$3:$K$42,2,FALSE) -> #N/A | Y99: =VLOOKUP(X99,送料!$A$1:$B$40,2,FALSE) -> #N/A | Z99: =(N99*S99)*0.16 -> 0 | AA99: =(N99*0.15)+4.5 -> 4.5 | AB99: =S99*AA99 -> 0 | AC99: =Y99+Z99+AB99+D99 -> #N/A | AD99: =N99*S99 -> 0 | AE99: =AD99-AC99 -> #N/A
A100: 5-19 | B100: =【２】結果!W7 -> 0 | T100: =O100 -> 0 | U100: =(P100*Q100*R100)/5000 -> 0 | V100: =MAX(T100,U100) -> 0 | W100: =CEILING(ROUNDDOWN(V100,2),0.5) -> 0 | X100: =VLOOKUP(W100,送料!$J$3:$K$42,2,FALSE) -> #N/A | Y100: =VLOOKUP(X100,送料!$A$1:$B$40,2,FALSE) -> #N/A | Z100: =(N100*S100)*0.16 -> 0 | AA100: =(N100*0.15)+4.5 -> 4.5 | AB100: =S100*AA100 -> 0 | AC100: =Y100+Z100+AB100+D100 -> #N/A | AD100: =N100*S100 -> 0 | AE100: =AD100-AC100 -> #N/A
...

Sheet 【４】精査
B1: 日本語タイトル | C1: 仕入れ先価格 | D1: 予想 最安値($) | E1: 結果（Fedex） | F1: 予想送料 | G1: 予想手数料 | H1: 予想関税2 | I1: 仕入れ先候補 | J1: 抽出URL | K1: 安仕入れ先１ | L1: 安仕入れ先２ | M1: 安仕入れ先３ | N1: 安仕入れ先４ | O1: 安仕入れ先５ | P1: メルカリ | Q1: ラクマ | R1: 楽天市場 | S1: ヤフオク | T1: ヤフーショッピング | U1: チェック | V1: 出品テンプレート | AB1: 出品テンプレート一覧
A2: 1 | AB2: Beauty Light Therapy
A3: 2 | AB3: Books
A4: 3 | AB4: CCG Individual Cards
A5: 4 | AB5: CDs
A6: 5 | AB6: Ceramic ornaments & Statue
A7: 6 | AB7: Dolls & Dolls playsets
A8: 7 | AB8: DVD & Blu-ray
A9: 8 | AB9: Eyeglass Frames
A10: 9 | AB10: Fish Binders
A11: 10 | AB11: Model Kits Hobby Toy
A12: 11 | AB12: Music Instrument
A13: 12 | AB13: Other Animation Merchandise
... A25: 24 | AB25: Wristwatches
A26: 25
A27: 26
A28: 27
A29: 28
A30: 29
A31: 30
A32: 31
A33: 32
A34: 33
A35: 34
A36: 35
A37: 36
... A201: 200

Sheet 【５】出品リスト
B1: Item title | C1: Custom label (SKU) | D1: Shipping Policy | E1: カテゴリ（出品テンプレート参照） | F1: 出品価格 | G1: 仕入れ先 | H1: 画像
A2: File1 | B2: Galaxy Express 999 The Movie 4K UHD Blu-ray Box Set Leiji Matsumoto Anime Japan | C2: 1658 | D2: Fedex 2.5kg | E2: DVD & Blu-ray | F2: 620 | G2: https://jp.mercari.com/item/m27984414731 | H2: 仕入れ先からダウンロードしてください
A3: File2 | B3: Kingdom Hearts 20th Anniversary Plate Collection Complete Set 16 Types Japan | C3: 1659 | D3: Fedex 2.5kg | E3: Other Animation Merchandise | F3: 274.99 | G3: https://jp.mercari.com/item/m80942673010 | H3: 仕入れ先からダウンロードしてください
A4: File3 | B4: Kingdom Hearts x Samantha Thavasa 20th Round Zip Leather Long Wallet Japan | C4: 1660 | D4: Fedex 1.0kg | E4: Other Animation Merchandise | F4: 755.99 | G4: https://auctions.yahoo.co.jp/jp/auction/r1175870416 | H4: 仕入れ先からダウンロードしてください
A5: File4 | B5: Volks Super Dollfie Seikan Gakuryo Eric SD17 Boy Doll Full Set Japan | C5: 1661 | D5: Fedex 5.5kg | E5: Dolls & Dolls playsets | F5: 1039.99 | G5: https://page.auctions.yahoo.co.jp/jp/auction/p1231976907 | H5: 仕入れ先からダウンロードしてください
A6: File5 | B6: Volks Dollfie Dream Sister DDS Macross F Ranka Lee Doll New Sealed Japan | C6: 1662 | D6: Fedex 5.5kg | E6: Dolls & Dolls playsets | F6: 1000.99 | G6: https://page.auctions.yahoo.co.jp/jp/auction/d516061039 | H6: 仕入れ先からダウンロードしてください
A7: File6 | B7: Toshi Yoshida Monument Valley Woodblock Print 1971 Framed Shin-hanga Japan | C7: 1663 | D7: Fedex 2.5kg | E7: Other Animation Merchandise | F7: 1250.99 | G7: https://page.auctions.yahoo.co.jp/jp/auction/p1231857857 | H7: 仕入れ先からダウンロードしてください
A8: File7 | B8: AUTOart 1/43 Mad Max 2 Interceptor & Enemy Car Weathering Diecast Set Limited | C8: 1664 | D8: Fedex 2.0kg | E8: Other Animation Merchandise | F8: 592 | G8: https://jp.mercari.com/item/m24175944612 | H8: 仕入れ先からダウンロードしてください
A9: File8 | B9: Aoshima 1/24 Mad Max 2 The Road Warrior Interceptor Model Kit Supercharger Japan | C9: 1665 | D9: Fedex 2.0kg | E9: Other Animation Merchandise | F9: 419 | G9: https://jp.mercari.com/item/m64753601502 | H9: 仕入れ先からダウンロードしてください
A10: File9 | B10: Mad Max Interceptor Mel Gibson 1/6 Figure Premium Toys Westland Rare Japan | C10: 1666 | D10: Fedex 2.0kg | E10: Other Animation Merchandise | F10: 809 | G10: https://paypayfleamarket.yahoo.co.jp/item/z623953652 | H10: 仕入れ先からダウンロードしてください
A11: File10 | B11: Bloodborne T-Shirt Father Gascoigne TORCH TORCH Size WM Heather Grey New Japan | C11: 1667 | D11: Fedex 1.5kg | E11: Other Animation Merchandise | F11: 294 | G11: https://jp.mercari.com/item/m50698842813 | H11: 仕入れ先からダウンロードしてください
A12: File11 | B12: Bloodborne T-Shirt Micolash Host of Nightmare TORCH TORCH Size WM Black Japan | C12: 1668 | D12: Fedex 1.5kg | E12: Other Animation Merchandise | F12: 294 | G12: https://jp.mercari.com/item/m27046971593 | H12: 仕入れ先からダウンロードしてください
A13: File12 | B13: Swatch MoMA Tadanori Yokoo SUOZ334 The City and Design Art Wrist Watch Japan | C13: 1669 | D13: Fedex 0.5kg | E13: Other Animation Merchandise | F13: 250 | G13: https://jp.mercari.com/item/m29601124354 | H13: 仕入れ先からダウンロードしてください
... A41: File40 | B41: Ghibli Acapella Style CD Studio Ghibli Songs Teichiku Japan Totoro Spirited Away | C41: 1697 | D41: Fedex 1.0kg | E41: Fish Binders | F41: 229 | G41: https://paypayfleamarket.yahoo.co.jp/item/z300604720 | H41: 仕入れ先からダウンロードしてください
A42: File41 | B42: Shimano Furuno Tankenmaru CV Color Fish Finder Sounder Marine Japan | C42: 1698 | D42: Fedex 3.0kg | F42: 399 | G42: https://jp.mercari.com/item/m61432143703 | H42: 仕入れ先からダウンロードしてください
A43: File42 | B43: Medicom RAH Metal Gear Solid 3 Snake Eater Naked Snake WF2005 500 Limited | C43: 1699 | D43: Fedex 3.0kg | E43: Other Animation Merchandise | F43: 520 | G43: https://jp.mercari.com/item/m43750621893 | H43: 仕入れ先からダウンロードしてください
A44: File43 | B44: Brahms Complete Edition 46 CD Box Deutsche Grammophon Karajan Pollini Abbado | C44: 1700 | D44: Fedex 1.5kg | E44: CDs | F44: 298 | G44: https://jp.mercari.com/item/m48839020184 | H44: 仕入れ先からダウンロードしてください
A45: File44 | B45: SIREN x Doko Demo Issyo Shibito-ro T-Shirt 2014 Original Cospa Size L Japan | C45: 1701 | D45: Fedex 2.0kg | E45: Other Animation Merchandise | F45: 270 | G45: https://jp.mercari.com/item/m73428428037 | H45: 仕入れ先からダウンロードしてください
A46: File45 | B46: Vertex Super Pochaco Cowgirl 1/6 Figure WonderFestival Limited Edition Japan | C46: 1702 | D46: Fedex 5.0kg | E46: Other Animation Merchandise | F46: 490 | G46: https://jp.mercari.com/item/m25397753764 | H46: 仕入れ先からダウンロードしてください
A47: File46 | B47: Medicos Chozokado Guido Mista and Sex Pistols JoJo Part 5 Figure Reissue | C47: 1703 | D47: Fedex 1.0kg | E47: Other Animation Merchandise | F47: 228 | G47: https://jp.mercari.com/shops/product/2JUYTDGc3URDspDQNQUZPn | H47: 仕入れ先からダウンロードしてください
A48: File47 | B48: Alpha Industries x Ace Combat 7 CWU-36/P Flight Jacket Black Size XL Japan | C48: 1704 | D48: Fedex 7.5kg | E48: Trading Card Singles | F48: 920 | G48: https://page.auctions.yahoo.co.jp/jp/auction/b1236905956 | H48: 仕入れ先からダウンロードしてください
A49: File48 | B49: Hazbin Hotel The Roach Secret Trading Card 64/60 Season 2 | C49: 1705 | D49: Fedex 0.5kg | F49: 560 | G49: https://jp.mercari.com/item/m81328910059 | H49: 仕入れ先からダウンロードしてください
A50: File49 | B50: Hazbin Hotel Charlie Acrylic Stand Standee Shark Robot Limited Japan | C50: 1706 | D50: Fedex 0.5kg | E50: Books | F50: 980 | G50: https://jp.mercari.com/item/m69186539344 | H50: 仕入れ先からダウンロードしてください
A51: File50 | B51: ARS MAGNA Yukito Kishiro First Art Book Battle Angel Alita 145 Illustrations | C51: 1707 | D51: Fedex 1.5kg | F51: 227 | G51: https://jp.mercari.com/item/m35148971723 | H51: 仕入れ先からダウンロードしてください
A52: File51 | B52: Neo Blythe Winterish Allure Doll Takara Tomy 2015 Sealed Japan | C52: 1708 | D52: Fedex 1.5kg | E52: Dolls & Dolls playsets | F52: 420 | G52: https://jp.mercari.com/item/m31653145904 | H52: 仕入れ先からダウンロードしてください
A53: File52 | B53: Soul of Chogokin GX-05 Daiku Maryu Gaiking Bandai Diecast Figure Japan | C53: 1709 | D53: Fedex 4.5kg | E53: Other Animation Merchandise | F53: 440 | G53: https://auctions.yahoo.co.jp/jp/auction/o1239092692 | H53: 仕入れ先からダウンロードしてください
A54: File53 | B54: KISS Retro 12 inch Figure Set with Mini Concert T-Shirts Vintage | C54: 1710 | D54: Fedex 1.0kg | E54: Other Animation Merchandise | F54: 640 | G54: https://auctions.yahoo.co.jp/jp/auction/c1058697225 | H54: 仕入れ先からダウンロードしてください
A55: File54 | B55: Bandai Chogokin GD-57B Mechagodzilla 2004 Black Version Tokyo SOS Japan | C55: 1711 | D55: Fedex 2.0kg | E55: Other Animation Merchandise | F55: 193 | G55: https://jp.mercari.com/shops/product/2JUGr6vHSnR9SpPJDpUFby | H55: 仕入れ先からダウンロードしてください
A56: File55 | B56: Popy Chogokin Mechagodzilla Vintage Diecast Figure Japan | C56: 1712 | D56: Fedex 1.5kg | E56: Other Animation Merchandise | F56: 880 | G56: https://jp.mercari.com/shops/product/2JMbWsRLdJeksEgW8dhoeZ | H56: 仕入れ先からダウンロードしてください
A57: File56 | B57: Max Factory I-No Extra Color Ver Guilty Gear XX 1/7 Figure WF2008 Limited | C57: 1713 | D57: Fedex 4.5kg | E57: Other Animation Merchandise | F57: 427 | G57: https://jp.mercari.com/item/m14829633369 | H57: 仕入れ先からダウンロードしてください
A58: File57 | B58: Harem in the Labyrinth Roxanne Hyoju Issei Comic Ver 1/7 Figure Japan | C58: 1714 | D58: Fedex 1.5kg | E58: Other Animation Merchandise | F58: 372 | G58: https://jp.mercari.com/item/m61827929822 | H58: 仕入れ先からダウンロードしてください
A59: File58 | B59: Realize Garage Kit Manami and Roxanne Resin Figure 2 Set K.PIERO Unbuilt | C59: 1715 | D59: Fedex 1.5kg | E59: Other Animation Merchandise | F59: 286 | G59: https://jp.mercari.com/item/m11658788348 | H59: 仕入れ先からダウンロードしてください
A60: File59 | B60: Shohei Ohtani Package Sleeve PS4 PS5 Powerpro 2024-2025 Bonus | C60: 1716 | D60: Fedex 0.5kg | E60: Other Animation Merchandise | F60: 1053 | G60: https://paypayfleamarket.yahoo.co.jp/item/z647477800 | H60: 仕入れ先からダウンロードしてください
A61: File60 | B61: Sentinel RIOBOT Getter 1 Devolution and Upgrade Parts Set Figure Japan | C61: 1717 | D61: Fedex 2.0kg | E61: Other Animation Merchandise | F61: 950 | G61: https://jp.mercari.com/item/m14135353857 | H61: 仕入れ先からダウンロードしてください
A62: File61 | B62: Bungo Stray Dogs Dazai Osamu F:NEX 1/7 Figure FuRyu Made to Order Tuxedo | C62: 1718 | D62: Fedex 1.5kg | E62: Other Animation Merchandise | F62: 922 | G62: https://jp.mercari.com/item/m84715579311 | H62: 仕入れ先からダウンロードしてください
A63: File62 | B63: Bungo Stray Dogs Nakahara Chuya 1/7 Figure Tuxedo F:NEX Event Ver Japan | C63: 1719 | D63: Fedex 1.5kg | E63: Other Animation Merchandise | F63: 922 | G63: https://jp.mercari.com/item/m14231022758 | H63: 仕入れ先からダウンロードしてください
... A235: File234 | B235: The Kinks At The BBC SHM-CD BOX 5CD 1DVD Limited Japan Discontinued Sealed New | C235: 1891 | D235: Fedex 1.0kg | E235: CDs | F235: 430 | G235: https://jp.mercari.com/item/m56334718647 | H235: 仕入れ先からダウンロードしてください

Sheet 【６】管理用
A1: Custom label (SKU) | B1: 商品名 | C1: 在庫数 | D1: 仕入価格 | E1: 販売価格 | F1: 見込送料 | G1: ebay相場 | H1: 最安値1 | I1: 最安値2 | J1: 最安値3 | K1: 最安値4 | L1: 最安値5 | N1: メルカリ | O1: ラクマ | P1: 楽天市場 | Q1: ヤフオク | R1: ヤフーショッピング
A2: 1658 | B2: 銀河鉄道999 THE MOVIE 4KリマスターBOX | C2: 1 | D2: 41200 | E2: 620 | F2: Fedex 2.5kg | G2: https://www.ebay.com/sch/i.html?_nkw=Galaxy+Express+999+The+Movie+4K+Remaster+Box+Blu-ray+First+Limited&_sacat=0&_from=R40&_sop=15&rt=nc&_udlo=20000 | H2: https://jp.mercari.com/item/m27984414731 | I2: https://jp.mercari.com/item/m58252217206 | N2: https://jp.mercari.com/search?keyword=%E9%8A%80%E6%B2%B3%E9%89%84%E9%81%93999%204K%E3%83%AA%E3%83%9E%E3%82%B9%E3%82%BF%E3%83%BCBOX&price_min=10000&sort=price&order=asc&status=on_sale | O2: https://fril.jp/s?query=%E9%8A%80%E6%B2%B3%E9%89%84%E9%81%93999%204K%E3%83%AA%E3%83%9E%E3%82%B9%E3%82%BF%E3%83%BCBOX&min=10000&transaction=selling | P2: https://search.rakuten.co.jp/search/mall/%E9%8A%80%E6%B2%B3%E9%89%84%E9%81%93999%204K%E3%83%AA%E3%83%9E%E3%82%B9%E3%82%BF%E3%83%BCBOX/?min=10000 | Q2: https://auctions.yahoo.co.jp/search/search?p=%E9%8A%80%E6%B2%B3%E9%89%84%E9%81%93999%204K%E3%83%AA%E3%83%9E%E3%82%B9%E3%82%BF%E3%83%BCBOX&aucminprice=10000 | R2: https://shopping.yahoo.co.jp/search/%E9%8A%80%E6%B2%B3%E9%89%84%E9%81%93999%204K%E3%83%AA%E3%83%9E%E3%82%B9%E3%82%BF%E3%83%BCBOX/0/?pf=10000
A3: 1659 | B3: キングダムハーツ プレートコレクション 全16種 フルコンプ | C3: 1 | D3: 13800 | E3: 274 | F3: Fedex 2.5kg | G3: https://www.ebay.com/sch/i.html?_nkw=Kingdom%20Hearts%20Plate%20Collection%20Complete%2016%20Set&_sacat=0&_from=R40&_sop=15&rt=nc&_udlo=20000 | H3: https://jp.mercari.com/item/m80942673010 | I3: https://jp.mercari.com/search?keyword=%E3%82%AD%E3%83%B3%E3%82%B0%E3%83%80%E3%83%A0%E3%83%8F%E3%83%BC%E3%83%84%20%E3%83%97%E3%83%AC%E3%83%BC%E3%83%88%E3%82%B3%E3%83%AC%E3%82%AF%E3%82%B7%E3%83%A7%E3%83%B3&price_min=10000&sort=price&order=asc&status=on_sale | J3: https://jp.mercari.com/search?keyword=%E3%82%AD%E3%83%B3%E3%82%B0%E3%83%80%E3%83%A0%E3%83%8F%E3%83%BC%E3%83%84%20%E3%83%97%E3%83%AC%E3%83%BC%E3%83%88%E3%82%B3%E3%83%AC%E3%82%AF%E3%82%B7%E3%83%A7%E3%83%B3&price_min=10000&sort=price&order=asc&status=on_sale | K3: https://jp.mercari.com/search?keyword=%E3%82%AD%E3%83%B3%E3%82%B0%E3%83%80%E3%83%A0%E3%83%8F%E3%83%BC%E3%83%84%20%E3%83%97%E3%83%AC%E3%83%BC%E3%83%88%E3%82%B3%E3%83%AC%E3%82%AF%E3%82%B7%E3%83%A7%E3%83%B3&price_min=10000&sort=price&order=asc&status=on_sale | L3: https://jp.mercari.com/search?keyword=%E3%82%AD%E3%83%B3%E3%82%B0%E3%83%80%E3%83%A0%E3%83%8F%E3%83%BC%E3%83%84%20%E3%83%97%E3%83%AC%E3%83%BC%E3%83%88%E3%82%B3%E3%83%AC%E3%82%AF%E3%82%B7%E3%83%A7%E3%83%B3&price_min=10000&sort=price&order=asc&status=on_sale | N3: https://jp.mercari.com/search?keyword=%E3%82%AD%E3%83%B3%E3%82%B0%E3%83%80%E3%83%A0%E3%83%8F%E3%83%BC%E3%83%84%20%E3%83%97%E3%83%AC%E3%83%BC%E3%83%88%E3%82%B3%E3%83%AC%E3%82%AF%E3%82%B7%E3%83%A7%E3%83%B3&price_min=10000&sort=price&order=asc&status=on_sale | O3: https://fril.jp/s?query=%E3%82%AD%E3%83%B3%E3%82%B0%E3%83%80%E3%83%A0%E3%83%8F%E3%83%BC%E3%83%84%20%E3%83%97%E3%83%AC%E3%83%BC%E3%83%88%E3%82%B3%E3%83%AC%E3%82%AF%E3%82%B7%E3%83%A7%E3%83%B3&min=10000&transaction=selling | P3: https://search.rakuten.co.jp/search/mall/%E3%82%AD%E3%83%B3%E3%82%B0%E3%83%80%E3%83%A0%E3%83%8F%E3%83%BC%E3%83%84%20%E3%83%97%E3%83%AC%E3%83%BC%E3%83%88%E3%82%B3%E3%83%AC%E3%82%AF%E3%82%B7%E3%83%A7%E3%83%B3/?min=10000 | Q3: https://auctions.yahoo.co.jp/search/search?p=%E3%82%AD%E3%83%B3%E3%82%B0%E3%83%80%E3%83%A0%E3%83%8F%E3%83%BC%E3%83%84%20%E3%83%97%E3%83%AC%E3%83%BC%E3%83%88%E3%82%B3%E3%83%AC%E3%82%AF%E3%82%B7%E3%83%A7%E3%83%B3&aucminprice=10000 | R3: https://shopping.yahoo.co.jp/search/%E3%82%AD%E3%83%B3%E3%82%B0%E3%83%80%E3%83%A0%E3%83%8F%E3%83%BC%E3%83%84%20%E3%83%97%E3%83%AC%E3%83%BC%E3%83%88%E3%82%B3%E3%83%AC%E3%82%AF%E3%82%B7%E3%83%A7%E3%83%B3/0/?pf=10000
A4: 1660 | B4: サマンサタバサ キングダムハーツ 20周年 ラウンドジップ財布 | C4: 1 | D4: 59999 | E4: 755 | F4: Fedex 1.0kg | G4: https://www.ebay.com/sch/i.html?_nkw=Samantha%20Thavasa%20Kingdom%20Hearts%2020th%20Round%20Zip%20Wallet&_sacat=0&_from=R40&_sop=15&rt=nc&_udlo=20000 | H4: https://auctions.yahoo.co.jp/jp/auction/r1175870416 | I4: https://jp.mercari.com/search?keyword=%E3%82%B5%E3%83%9E%E3%83%B3%E3%82%B5%E3%82%BF%E3%83%90%E3%82%B5%20%E3%82%AD%E3%83%B3%E3%82%B0%E3%83%80%E3%83%A0%E3%83%8F%E3%83%BC%E3%83%84%20%E8%B2%A1%E5%B8%83&price_min=10000&sort=price&order=asc&status=on_sale | J4: https://jp.mercari.com/search?keyword=%E3%82%B5%E3%83%9E%E3%83%B3%E3%82%B5%E3%82%BF%E3%83%90%E3%82%B5%20%E3%82%AD%E3%83%B3%E3%82%B0%E3%83%80%E3%83%A0%E3%83%8F%E3%83%BC%E3%83%84%20%E8%B2%A1%E5%B8%83&price_min=10000&sort=price&order=asc&status=on_sale | K4: https://jp.mercari.com/search?keyword=%E3%82%B5%E3%83%9E%E3%83%B3%E3%82%B5%E3%82%BF%E3%83%90%E3%82%B5%20%E3%82%AD%E3%83%B3%E3%82%B0%E3%83%80%E3%83%A0%E3%83%8F%E3%83%BC%E3%83%84%20%E8%B2%A1%E5%B8%83&price_min=10000&sort=price&order=asc&status=on_sale | L4: https://jp.mercari.com/search?keyword=%E3%82%B5%E3%83%9E%E3%83%B3%E3%82%B5%E3%82%BF%E3%83%90%E3%82%B5%20%E3%82%AD%E3%83%B3%E3%82%B0%E3%83%80%E3%83%A0%E3%83%8F%E3%83%BC%E3%83%84%20%E8%B2%A1%E5%B8%83&price_min=10000&sort=price&order=asc&status=on_sale | N4: https://jp.mercari.com/search?keyword=%E3%82%B5%E3%83%9E%E3%83%B3%E3%82%B5%E3%82%BF%E3%83%90%E3%82%B5%20%E3%82%AD%E3%83%B3%E3%82%B0%E3%83%80%E3%83%A0%E3%83%8F%E3%83%BC%E3%83%84%20%E8%B2%A1%E5%B8%83&price_min=10000&sort=price&order=asc&status=on_sale | O4: https://fril.jp/s?query=%E3%82%B5%E3%83%9E%E3%83%B3%E3%82%B5%E3%82%BF%E3%83%90%E3%82%B5%20%E3%82%AD%E3%83%B3%E3%82%B0%E3%83%80%E3%83%A0%E3%83%8F%E3%83%BC%E3%83%84%20%E8%B2%A1%E5%B8%83&min=10000&transaction=selling | P4: https://search.rakuten.co.jp/search/mall/%E3%82%B5%E3%83%9E%E3%83%B3%E3%82%B5%E3%82%BF%E3%83%90%E3%82%B5%20%E3%82%AD%E3%83%B3%E3%82%B0%E3%83%80%E3%83%A0%E3%83%8F%E3%83%BC%E3%83%84%20%E8%B2%A1%E5%B8%83/?min=10000 | Q4: https://auctions.yahoo.co.jp/search/search?p=%E3%82%B5%E3%83%9E%E3%83%B3%E3%82%B5%E3%82%BF%E3%83%90%E3%82%B5%20%E3%82%AD%E3%83%B3%E3%82%B0%E3%83%80%E3%83%A0%E3%83%8F%E3%83%BC%E3%83%84%20%E8%B2%A1%E5%B8%83&aucminprice=10000 | R4: https://shopping.yahoo.co.jp/search/%E3%82%B5%E3%83%9E%E3%83%B3%E3%82%B5%E3%82%BF%E3%83%90%E3%82%B5%20%E3%82%AD%E3%83%B3%E3%82%B0%E3%83%80%E3%83%A0%E3%83%8F%E3%83%BC%E3%83%84%20%E8%B2%A1%E5%B8%83/0/?pf=10000
A5: 1661 | B5: スーパードルフィー 星間学寮 エリック | C5: 1 | D5: 92000 | E5: 1039 | F5: Fedex 5.5kg | G5: https://www.ebay.com/sch/i.html?_nkw=Volks%20Super%20Dollfie%20Seikan%20Gakuryo%20Eric%20Doll&_sacat=0&_from=R40&_sop=15&rt=nc&_udlo=20000 | H5: https://page.auctions.yahoo.co.jp/jp/auction/p1231976907 | I5: https://jp.mercari.com/search?keyword=%E3%82%B9%E3%83%BC%E3%83%91%E3%83%BC%E3%83%89%E3%83%AB%E3%83%95%E3%82%A3%E3%83%BC%20%E3%82%A8%E3%83%AA%E3%83%83%E3%82%AF&price_min=10000&sort=price&order=asc&status=on_sale | J5: https://jp.mercari.com/search?keyword=%E3%82%B9%E3%83%BC%E3%83%91%E3%83%BC%E3%83%89%E3%83%AB%E3%83%95%E3%82%A3%E3%83%BC%20%E3%82%A8%E3%83%AA%E3%83%83%E3%82%AF&price_min=10000&sort=price&order=asc&status=on_sale | K5: https://jp.mercari.com/search?keyword=%E3%82%B9%E3%83%BC%E3%83%91%E3%83%BC%E3%83%89%E3%83%AB%E3%83%95%E3%82%A3%E3%83%BC%20%E3%82%A8%E3%83%AA%E3%83%83%E3%82%AF&price_min=10000&sort=price&order=asc&status=on_sale | L5: https://jp.mercari.com/search?keyword=%E3%82%B9%E3%83%BC%E3%83%91%E3%83%BC%E3%83%89%E3%83%AB%E3%83%95%E3%82%A3%E3%83%BC%20%E3%82%A8%E3%83%AA%E3%83%83%E3%82%AF&price_min=10000&sort=price&order=asc&status=on_sale | N5: https://jp.mercari.com/search?keyword=%E3%82%B9%E3%83%BC%E3%83%91%E3%83%BC%E3%83%89%E3%83%AB%E3%83%95%E3%82%A3%E3%83%BC%20%E3%82%A8%E3%83%AA%E3%83%83%E3%82%AF&price_min=10000&sort=price&order=asc&status=on_sale | O5: https://fril.jp/s?query=%E3%82%B9%E3%83%BC%E3%83%91%E3%83%BC%E3%83%89%E3%83%AB%E3%83%95%E3%82%A3%E3%83%BC%20%E3%82%A8%E3%83%AA%E3%83%83%E3%82%AF&min=10000&transaction=selling | P5: https://search.rakuten.co.jp/search/mall/%E3%82%B9%E3%83%BC%E3%83%91%E3%83%BC%E3%83%89%E3%83%AB%E3%83%95%E3%82%A3%E3%83%BC%20%E3%82%A8%E3%83%AA%E3%83%83%E3%82%AF/?min=10000 | Q5: https://auctions.yahoo.co.jp/search/search?p=%E3%82%B9%E3%83%BC%E3%83%91%E3%83%BC%E3%83%89%E3%83%AB%E3%83%95%E3%82%A3%E3%83%BC%20%E3%82%A8%E3%83%AA%E3%83%83%E3%82%AF&aucminprice=10000 | R5: https://shopping.yahoo.co.jp/search/%E3%82%B9%E3%83%BC%E3%83%91%E3%83%BC%E3%83%89%E3%83%AB%E3%83%95%E3%82%A3%E3%83%BC%20%E3%82%A8%E3%83%AA%E3%83%83%E3%82%AF/0/?pf=10000
A6: 1662 | B6: ボークス ドルフィードリーム DDS マクロスF ランカ・リー | C6: 1 | D6: 88000 | E6: 1000 | F6: Fedex 5.5kg | G6: https://www.ebay.com/sch/i.html?_nkw=Volks%20Dollfie%20Dream%20DDS%20Macross%20F%20Ranka%20Lee&_sacat=0&_from=R40&_sop=15&rt=nc&_udlo=20000 | H6: https://page.auctions.yahoo.co.jp/jp/auction/d516061039 | I6: https://auctions.yahoo.co.jp/jp/auction/l1236140065 | J6: https://jp.mercari.com/search?keyword=%E3%83%89%E3%83%AB%E3%83%95%E3%82%A3%E3%83%BC%E3%83%89%E3%83%AA%E3%83%BC%E3%83%A0%20%E3%83%A9%E3%83%B3%E3%82%AB&price_min=10000&sort=price&order=asc&status=on_sale | K6: https://jp.mercari.com/search?keyword=%E3%83%89%E3%83%AB%E3%83%95%E3%82%A3%E3%83%BC%E3%83%89%E3%83%AA%E3%83%BC%E3%83%A0%20%E3%83%A9%E3%83%B3%E3%82%AB&price_min=10000&sort=price&order=asc&status=on_sale | L6: https://jp.mercari.com/search?keyword=%E3%83%89%E3%83%AB%E3%83%95%E3%82%A3%E3%83%BC%E3%83%89%E3%83%AA%E3%83%BC%E3%83%A0%20%E3%83%A9%E3%83%B3%E3%82%AB&price_min=10000&sort=price&order=asc&status=on_sale | N6: https://jp.mercari.com/search?keyword=%E3%83%89%E3%83%AB%E3%83%95%E3%82%A3%E3%83%BC%E3%83%89%E3%83%AA%E3%83%BC%E3%83%A0%20%E3%83%A9%E3%83%B3%E3%82%AB&price_min=10000&sort=price&order=asc&status=on_sale | O6: https://fril.jp/s?query=%E3%83%89%E3%83%AB%E3%83%95%E3%82%A3%E3%83%BC%E3%83%89%E3%83%AA%E3%83%BC%E3%83%A0%20%E3%83%A9%E3%83%B3%E3%82%AB&min=10000&transaction=selling | P6: https://search.rakuten.co.jp/search/mall/%E3%83%89%E3%83%AB%E3%83%95%E3%82%A3%E3%83%BC%E3%83%89%E3%83%AA%E3%83%BC%E3%83%A0%20%E3%83%A9%E3%83%B3%E3%82%AB/?min=10000 | Q6: https://auctions.yahoo.co.jp/search/search?p=%E3%83%89%E3%83%AB%E3%83%95%E3%82%A3%E3%83%BC%E3%83%89%E3%83%AA%E3%83%BC%E3%83%A0%20%E3%83%A9%E3%83%B3%E3%82%AB&aucminprice=10000 | R6: https://shopping.yahoo.co.jp/search/%E3%83%89%E3%83%AB%E3%83%95%E3%82%A3%E3%83%BC%E3%83%89%E3%83%AA%E3%83%BC%E3%83%A0%20%E3%83%A9%E3%83%B3%E3%82%AB/0/?pf=10000
A7: 1663 | B7: 吉田遠志 モニュメント・バレー 木版画 | C7: 1 | D7: 91500 | E7: 1250 | F7: Fedex 2.5kg | G7: https://www.ebay.com/sch/i.html?_nkw=Toshi%20Yoshida%20Monument%20Valley%20Woodblock%20Print&_sacat=0&_from=R40&_sop=15&rt=nc&_udlo=20000 | H7: https://page.auctions.yahoo.co.jp/jp/auction/p1231857857 | I7: https://jp.mercari.com/search?keyword=%E5%90%89%E7%94%B0%E9%81%A0%E5%BF%97%20%E3%83%A2%E3%83%8B%E3%83%A5%E3%83%A1%E3%83%B3%E3%83%88%E3%83%BB%E3%83%90%E3%83%AC%E3%83%BC%20%E6%9C%A8%E7%89%88%E7%94%BB&price_min=10000&sort=price&order=asc&status=on_sale | J7: https://jp.mercari.com/search?keyword=%E5%90%89%E7%94%B0%E9%81%A0%E5%BF%97%20%E3%83%A2%E3%83%8B%E3%83%A5%E3%83%A1%E3%83%B3%E3%83%88%E3%83%BB%E3%83%90%E3%83%AC%E3%83%BC%20%E6%9C%A8%E7%89%88%E7%94%BB&price_min=10000&sort=price&order=asc&status=on_sale | K7: https://jp.mercari.com/search?keyword=%E5%90%89%E7%94%B0%E9%81%A0%E5%BF%97%20%E3%83%A2%E3%83%8B%E3%83%A5%E3%83%A1%E3%83%B3%E3%83%88%E3%83%BB%E3%83%90%E3%83%AC%E3%83%BC%20%E6%9C%A8%E7%89%88%E7%94%BB&price_min=10000&sort=price&order=asc&status=on_sale | L7: https://jp.mercari.com/search?keyword=%E5%90%89%E7%94%B0%E9%81%A0%E5%BF%97%20%E3%83%A2%E3%83%8B%E3%83%A5%E3%83%A1%E3%83%B3%E3%83%88%E3%83%BB%E3%83%90%E3%83%AC%E3%83%BC%20%E6%9C%A8%E7%89%88%E7%94%BB&price_min=10000&sort=price&order=asc&status=on_sale | N7: https://jp.mercari.com/search?keyword=%E5%90%89%E7%94%B0%E9%81%A0%E5%BF%97%20%E3%83%A2%E3%83%8B%E3%83%A5%E3%83%A1%E3%83%B3%E3%83%88%E3%83%BB%E3%83%90%E3%83%AC%E3%83%BC%20%E6%9C%A8%E7%89%88%E7%94%BB&price_min=10000&sort=price&order=asc&status=on_sale | O7: https://fril.jp/s?query=%E5%90%89%E7%94%B0%E9%81%A0%E5%BF%97%20%E3%83%A2%E3%83%8B%E3%83%A5%E3%83%A1%E3%83%B3%E3%83%88%E3%83%BB%E3%83%90%E3%83%AC%E3%83%BC%20%E6%9C%A8%E7%89%88%E7%94%BB&min=10000&transaction=selling | P7: https://search.rakuten.co.jp/search/mall/%E5%90%89%E7%94%B0%E9%81%A0%E5%BF%97%20%E3%83%A2%E3%83%8B%E3%83%A5%E3%83%A1%E3%83%B3%E3%83%88%E3%83%BB%E3%83%90%E3%83%AC%E3%83%BC%20%E6%9C%A8%E7%89%88%E7%94%BB/?min=10000 | Q7: https://auctions.yahoo.co.jp/search/search?p=%E5%90%89%E7%94%B0%E9%81%A0%E5%BF%97%20%E3%83%A2%E3%83%8B%E3%83%A5%E3%83%A1%E3%83%B3%E3%83%88%E3%83%BB%E3%83%90%E3%83%AC%E3%83%BC%20%E6%9C%A8%E7%89%88%E7%94%BB&aucminprice=10000 | R7: https://shopping.yahoo.co.jp/search/%E5%90%89%E7%94%B0%E9%81%A0%E5%BF%97%20%E3%83%A2%E3%83%8B%E3%83%A5%E3%83%A1%E3%83%B3%E3%83%88%E3%83%BB%E3%83%90%E3%83%AC%E3%83%BC%20%E6%9C%A8%E7%89%88%E7%94%BB/0/?pf=10000
A8: 1664 | B8: AUTOart マッドマックス インターセプター 2台セット ウェザリング | C8: 1 | D8: 50500 | E8: 592 | F8: Fedex 2.0kg | G8: https://www.ebay.com/sch/i.html?_nkw=AUTOart%20Mad%20Max%20Interceptor&_sacat=0&_from=R40&_sop=15&rt=nc&_udlo=20000 | H8: https://jp.mercari.com/item/m24175944612 | N8: https://jp.mercari.com/search?keyword=AUTOart%20%E3%83%9E%E3%83%83%E3%83%89%E3%83%9E%E3%83%83%E3%82%AF%E3%82%B9%20%E3%82%A4%E3%83%B3%E3%82%BF%E3%83%BC%E3%82%BB%E3%83%97%E3%82%BF%E3%83%BC%202%E5%8F%B0&price_min=10000&sort=price&order=asc&status=on_sale | O8: https://fril.jp/s?query=AUTOart%20%E3%83%9E%E3%83%83%E3%83%89%E3%83%9E%E3%83%83%E3%82%AF%E3%82%B9%20%E3%82%A4%E3%83%B3%E3%82%BF%E3%83%BC%E3%82%BB%E3%83%97%E3%82%BF%E3%83%BC%202%E5%8F%B0&min=10000&transaction=selling | P8: https://search.rakuten.co.jp/search/mall/AUTOart%20%E3%83%9E%E3%83%83%E3%83%89%E3%83%9E%E3%83%83%E3%82%AF%E3%82%B9%20%E3%82%A4%E3%83%B3%E3%82%BF%E3%83%BC%E3%82%BB%E3%83%97%E3%82%BF%E3%83%BC%202%E5%8F%B0/?min=10000 | Q8: https://auctions.yahoo.co.jp/search/search?p=AUTOart%20%E3%83%9E%E3%83%83%E3%83%89%E3%83%9E%E3%83%83%E3%82%AF%E3%82%B9%20%E3%82%A4%E3%83%B3%E3%82%BF%E3%83%BC%E3%82%BB%E3%83%97%E3%82%BF%E3%83%BC%202%E5%8F%B0&aucminprice=10000 | R8: https://shopping.yahoo.co.jp/search/AUTOart%20%E3%83%9E%E3%83%83%E3%83%89%E3%83%9E%E3%83%83%E3%82%AF%E3%82%B9%20%E3%82%A4%E3%83%B3%E3%82%BF%E3%83%BC%E3%82%BB%E3%83%97%E3%82%BF%E3%83%BC%202%E5%8F%B0/0/?pf=10000
A9: 1665 | B9: アオシマ 1/24 マッドマックス2 インターセプター フィギュア | C9: 1 | D9: 31000 | E9: 419 | F9: Fedex 2.0kg | G9: https://www.ebay.com/sch/i.html?_nkw=Aoshima%20Mad%20Max%20Interceptor&_sacat=0&_from=R40&_sop=15&rt=nc&_udlo=20000 | H9: https://jp.mercari.com/item/m64753601502 | N9: https://jp.mercari.com/search?keyword=%E3%83%9E%E3%83%83%E3%83%89%E3%83%9E%E3%83%83%E3%82%AF%E3%82%B9%20%E3%82%A4%E3%83%B3%E3%82%BF%E3%83%BC%E3%82%BB%E3%83%97%E3%82%BF%E3%83%BC%20%E3%83%95%E3%82%A3%E3%82%AE%E3%83%A5%E3%82%A2&price_min=10000&sort=price&order=asc&status=on_sale | O9: https://fril.jp/s?query=%E3%83%9E%E3%83%83%E3%83%89%E3%83%9E%E3%83%83%E3%82%AF%E3%82%B9%20%E3%82%A4%E3%83%B3%E3%82%BF%E3%83%BC%E3%82%BB%E3%83%97%E3%82%BF%E3%83%BC%20%E3%83%95%E3%82%A3%E3%82%AE%E3%83%A5%E3%82%A2&min=10000&transaction=selling | P9: https://search.rakuten.co.jp/search/mall/%E3%83%9E%E3%83%83%E3%83%89%E3%83%9E%E3%83%83%E3%82%AF%E3%82%B9%20%E3%82%A4%E3%83%B3%E3%82%BF%E3%83%BC%E3%82%BB%E3%83%97%E3%82%BF%E3%83%BC%20%E3%83%95%E3%82%A3%E3%82%AE%E3%83%A5%E3%82%A2/?min=10000 | Q9: https://auctions.yahoo.co.jp/search/search?p=%E3%83%9E%E3%83%83%E3%83%89%E3%83%9E%E3%83%83%E3%82%AF%E3%82%B9%20%E3%82%A4%E3%83%B3%E3%82%BF%E3%83%BC%E3%82%BB%E3%83%97%E3%82%BF%E3%83%BC%20%E3%83%95%E3%82%A3%E3%82%AE%E3%83%A5%E3%82%A2&aucminprice=10000 | R9: https://shopping.yahoo.co.jp/search/%E3%83%9E%E3%83%83%E3%83%89%E3%83%9E%E3%83%83%E3%82%AF%E3%82%B9%20%E3%82%A4%E3%83%B3%E3%82%BF%E3%83%BC%E3%82%BB%E3%83%97%E3%82%BF%E3%83%BC%20%E3%83%95%E3%82%A3%E3%82%AE%E3%83%A5%E3%82%A2/0/?pf=10000
A10: 1666 | B10: マッドマックス メルギブソン 1/6 フィギュア プレミアトイズ | C10: 1 | D10: 75000 | E10: 809 | F10: Fedex 2.0kg | G10: https://www.ebay.com/sch/i.html?_nkw=Mad%20Max%20Mel%20Gibson%20Figure&_sacat=0&_from=R40&_sop=15&rt=nc&_udlo=20000 | H10: https://paypayfleamarket.yahoo.co.jp/item/z623953652 | I10: https://jp.mercari.com/item/m35594640581 | N10: https://jp.mercari.com/search?keyword=%E3%83%9E%E3%83%83%E3%83%89%E3%83%9E%E3%83%83%E3%82%AF%E3%82%B9%20%E3%83%95%E3%82%A3%E3%82%AE%E3%83%A5%E3%82%A2%20%E3%83%97%E3%83%AC%E3%83%9F%E3%82%A2%E3%83%88%E3%82%A4%E3%82%BA%201%2F6&price_min=10000&sort=price&order=asc&status=on_sale | O10: https://fril.jp/s?query=%E3%83%9E%E3%83%83%E3%83%89%E3%83%9E%E3%83%83%E3%82%AF%E3%82%B9%20%E3%83%95%E3%82%A3%E3%82%AE%E3%83%A5%E3%82%A2%20%E3%83%97%E3%83%AC%E3%83%9F%E3%82%A2%E3%83%88%E3%82%A4%E3%82%BA%201%2F6&min=10000&transaction=selling | P10: https://search.rakuten.co.jp/search/mall/%E3%83%9E%E3%83%83%E3%83%89%E3%83%9E%E3%83%83%E3%82%AF%E3%82%B9%20%E3%83%95%E3%82%A3%E3%82%AE%E3%83%A5%E3%82%A2%20%E3%83%97%E3%83%AC%E3%83%9F%E3%82%A2%E3%83%88%E3%82%A4%E3%82%BA%201%2F6/?min=10000 | Q10: https://auctions.yahoo.co.jp/search/search?p=%E3%83%9E%E3%83%83%E3%83%89%E3%83%9E%E3%83%83%E3%82%AF%E3%82%B9%20%E3%83%95%E3%82%A3%E3%82%AE%E3%83%A5%E3%82%A2%20%E3%83%97%E3%83%AC%E3%83%9F%E3%82%A2%E3%83%88%E3%82%A4%E3%82%BA%201%2F6&aucminprice=10000 | R10: https://shopping.yahoo.co.jp/search/%E3%83%9E%E3%83%83%E3%83%89%E3%83%9E%E3%83%83%E3%82%AF%E3%82%B9%20%E3%83%95%E3%82%A3%E3%82%AE%E3%83%A5%E3%82%A2%20%E3%83%97%E3%83%AC%E3%83%9F%E3%82%A2%E3%83%88%E3%82%A4%E3%82%BA%201%2F6/0/?pf=10000
A11: 1667 | B11: Bloodborne Tシャツ ガスコイン神父 TORCH TORCH | C11: 1 | D11: 22222 | E11: 294 | F11: Fedex 1.5kg | G11: https://www.ebay.com/sch/i.html?_nkw=Bloodborne%20T-Shirt%20Gascoigne&_sacat=0&_from=R40&_sop=15&rt=nc&_udlo=20000 | H11: https://jp.mercari.com/item/m50698842813 | N11: https://jp.mercari.com/search?keyword=Bloodborne%20T%E3%82%B7%E3%83%A3%E3%83%84%20%E3%82%AC%E3%82%B9%E3%82%B3%E3%82%A4%E3%83%B3%20TORCH%20TORCH&price_min=10000&sort=price&order=asc&status=on_sale | O11: https://fril.jp/s?query=Bloodborne%20T%E3%82%B7%E3%83%A3%E3%83%84%20%E3%82%AC%E3%82%B9%E3%82%B3%E3%82%A4%E3%83%B3%20TORCH%20TORCH&min=10000&transaction=selling | P11: https://search.rakuten.co.jp/search/mall/Bloodborne%20T%E3%82%B7%E3%83%A3%E3%83%84%20%E3%82%AC%E3%82%B9%E3%82%B3%E3%82%A4%E3%83%B3%20TORCH%20TORCH/?min=10000 | Q11: https://auctions.yahoo.co.jp/search/search?p=Bloodborne%20T%E3%82%B7%E3%83%A3%E3%83%84%20%E3%82%AC%E3%82%B9%E3%82%B3%E3%82%A4%E3%83%B3%20TORCH%20TORCH&aucminprice=10000 | R11: https://shopping.yahoo.co.jp/search/Bloodborne%20T%E3%82%B7%E3%83%A3%E3%83%84%20%E3%82%AC%E3%82%B9%E3%82%B3%E3%82%A4%E3%83%B3%20TORCH%20TORCH/0/?pf=10000
A12: 1668 | B12: Bloodborne Tシャツ ミコラーシュ TORCH TORCH | C12: 1 | D12: 17555 | E12: 294 | F12: Fedex 1.5kg | G12: https://www.ebay.com/sch/i.html?_nkw=Bloodborne%20T-Shirt%20Micolash&_sacat=0&_from=R40&_sop=15&rt=nc&_udlo=20000 | H12: https://jp.mercari.com/item/m27046971593 | N12: https://jp.mercari.com/search?keyword=Bloodborne%20T%E3%82%B7%E3%83%A3%E3%83%84%20%E3%83%9F%E3%82%B3%E3%83%A9%E3%83%BC%E3%82%B7%E3%83%A5%20TORCH%20TORCH&price_min=10000&sort=price&order=asc&status=on_sale | O12: https://fril.jp/s?query=Bloodborne%20T%E3%82%B7%E3%83%A3%E3%83%84%20%E3%83%9F%E3%82%B3%E3%83%A9%E3%83%BC%E3%82%B7%E3%83%A5%20TORCH%20TORCH&min=10000&transaction=selling | P12: https://search.rakuten.co.jp/search/mall/Bloodborne%20T%E3%82%B7%E3%83%A3%E3%83%84%20%E3%83%9F%E3%82%B3%E3%83%A9%E3%83%BC%E3%82%B7%E3%83%A5%20TORCH%20TORCH/?min=10000 | Q12: https://auctions.yahoo.co.jp/search/search?p=Bloodborne%20T%E3%82%B7%E3%83%A3%E3%83%84%20%E3%83%9F%E3%82%B3%E3%83%A9%E3%83%BC%E3%82%B7%E3%83%A5%20TORCH%20TORCH&aucminprice=10000 | R12: https://shopping.yahoo.co.jp/search/Bloodborne%20T%E3%82%B7%E3%83%A3%E3%83%84%20%E3%83%9F%E3%82%B3%E3%83%A9%E3%83%BC%E3%82%B7%E3%83%A5%20TORCH%20TORCH/0/?pf=10000
A13: 1669 | B13: swatch MoMA 横尾忠則 SUOZ334 腕時計 | C13: 1 | D13: 13333 | E13: 250 | F13: Fedex 0.5kg | G13: https://www.ebay.com/sch/i.html?_nkw=Swatch%20MoMA%20Yokoo%20SUOZ334&_sacat=0&_from=R40&_sop=15&rt=nc&_udlo=20000 | H13: https://jp.mercari.com/item/m29601124354 | I13: https://jp.mercari.com/item/m29601124354 | N13: https://jp.mercari.com/search?keyword=swatch%20MoMA%20%E6%A8%AA%E5%B0%BE%E5%BF%A0%E5%89%87%20SUOZ334&price_min=10000&sort=price&order=asc&status=on_sale | O13: https://fril.jp/s?query=swatch%20MoMA%20%E6%A8%AA%E5%B0%BE%E5%BF%A0%E5%89%87%20SUOZ334&min=10000&transaction=selling | P13: https://search.rakuten.co.jp/search/mall/swatch%20MoMA%20%E6%A8%AA%E5%B0%BE%E5%BF%A0%E5%89%87%20SUOZ334/?min=10000 | Q13: https://auctions.yahoo.co.jp/search/search?p=swatch%20MoMA%20%E6%A8%AA%E5%B0%BE%E5%BF%A0%E5%89%87%20SUOZ334&aucminprice=10000 | R13: https://shopping.yahoo.co.jp/search/swatch%20MoMA%20%E6%A8%AA%E5%B0%BE%E5%BF%A0%E5%89%87%20SUOZ334/0/?pf=10000
A14: 1670 | B14: Swatch ロイヤルポップ ピンク ヴィンテージ腕時計 | C14: 1 | D14: 75000 | E14: 800 | F14: Fedex 0.5kg | G14: https://www.ebay.com/sch/i.html?_nkw=Swatch%20Royal%20Pop&_sacat=0&_from=R40&_sop=15&rt=nc&_udlo=20000 | H14: https://paypayfleamarket.yahoo.co.jp/item/z628302812 | I14: https://jp.mercari.com/item/m92887806542 | N14: https://jp.mercari.com/search?keyword=Swatch%20Royal%20Pop%20%E3%82%AA%E3%83%BC%E3%83%87%E3%83%9E%E3%83%94%E3%82%B2&price_min=10000&sort=price&order=asc&status=on_sale | O14: https://fril.jp/s?query=Swatch%20Royal%20Pop%20%E3%82%AA%E3%83%BC%E3%83%87%E3%83%9E%E3%83%94%E3%82%B2&min=10000&transaction=selling | P14: https://search.rakuten.co.jp/search/mall/Swatch%20Royal%20Pop%20%E3%82%AA%E3%83%BC%E3%83%87%E3%83%9E%E3%83%94%E3%82%B2/?min=10000 | Q14: https://auctions.yahoo.co.jp/search/search?p=Swatch%20Royal%20Pop%20%E3%82%AA%E3%83%BC%E3%83%87%E3%83%9E%E3%83%94%E3%82%B2&aucminprice=10000 | R14: https://shopping.yahoo.co.jp/search/Swatch%20Royal%20Pop%20%E3%82%AA%E3%83%BC%E3%83%87%E3%83%9E%E3%83%94%E3%82%B2/0/?pf=10000
A15: 1671 | B15: ナルニア国物語 ミニチュアボックス 武器 ウォールアート | C15: 1 | D15: 15000 | E15: 299 | F15: Fedex 3.0kg | G15: https://www.ebay.com/sch/i.html?_nkw=Narnia%20Miniature%20Weapons&_sacat=0&_from=R40&_sop=15&rt=nc&_udlo=20000 | H15: https://jp.mercari.com/item/m39552034255 | N15: https://jp.mercari.com/search?keyword=%E3%83%8A%E3%83%AB%E3%83%8B%E3%82%A2%E5%9B%BD%E7%89%A9%E8%AA%9E%20%E3%83%9F%E3%83%8B%E3%83%81%E3%83%A5%E3%82%A2%E3%83%9C%E3%83%83%E3%82%AF%E3%82%B9%20%E6%AD%A6%E5%99%A8&price_min=10000&sort=price&order=asc&status=on_sale | O15: https://fril.jp/s?query=%E3%83%8A%E3%83%AB%E3%83%8B%E3%82%A2%E5%9B%BD%E7%89%A9%E8%AA%9E%20%E3%83%9F%E3%83%8B%E3%83%81%E3%83%A5%E3%82%A2%E3%83%9C%E3%83%83%E3%82%AF%E3%82%B9%20%E6%AD%A6%E5%99%A8&min=10000&transaction=selling | P15: https://search.rakuten.co.jp/search/mall/%E3%83%8A%E3%83%AB%E3%83%8B%E3%82%A2%E5%9B%BD%E7%89%A9%E8%AA%9E%20%E3%83%9F%E3%83%8B%E3%83%81%E3%83%A5%E3%82%A2%E3%83%9C%E3%83%83%E3%82%AF%E3%82%B9%20%E6%AD%A6%E5%99%A8/?min=10000 | Q15: https://auctions.yahoo.co.jp/search/search?p=%E3%83%8A%E3%83%AB%E3%83%8B%E3%82%A2%E5%9B%BD%E7%89%A9%E8%AA%9E%20%E3%83%9F%E3%83%8B%E3%83%81%E3%83%A5%E3%82%A2%E3%83%9C%E3%83%83%E3%82%AF%E3%82%B9%20%E6%AD%A6%E5%99%A8&aucminprice=10000 | R15: https://shopping.yahoo.co.jp/search/%E3%83%8A%E3%83%AB%E3%83%8B%E3%82%A2%E5%9B%BD%E7%89%A9%E8%AA%9E%20%E3%83%9F%E3%83%8B%E3%83%81%E3%83%A5%E3%82%A2%E3%83%9C%E3%83%83%E3%82%AF%E3%82%B9%20%E6%AD%A6%E5%99%A8/0/?pf=10000
A16: 1672 | B16: ナルニア国物語 ジオラマ ブックエンド 街灯&ビーバー 2点 | C16: 1 | D16: 14800 | E16: 302 | F16: Fedex 3.0kg | G16: https://www.ebay.com/sch/i.html?_nkw=Narnia%20Diorama%20Bookend&_sacat=0&_from=R40&_sop=15&rt=nc&_udlo=20000 | H16: https://jp.mercari.com/item/m39133500111 | N16: https://jp.mercari.com/search?keyword=%E3%83%8A%E3%83%AB%E3%83%8B%E3%82%A2%E5%9B%BD%E7%89%A9%E8%AA%9E%20%E3%82%B8%E3%82%AA%E3%83%A9%E3%83%9E%20%E3%83%96%E3%83%83%E3%82%AF%E3%82%A8%E3%83%B3%E3%83%89%20%E8%A1%97%E7%81%AF&price_min=10000&sort=price&order=asc&status=on_sale | O16: https://fril.jp/s?query=%E3%83%8A%E3%83%AB%E3%83%8B%E3%82%A2%E5%9B%BD%E7%89%A9%E8%AA%9E%20%E3%82%B8%E3%82%AA%E3%83%A9%E3%83%9E%20%E3%83%96%E3%83%83%E3%82%AF%E3%82%A8%E3%83%B3%E3%83%89%20%E8%A1%97%E7%81%AF&min=10000&transaction=selling | P16: https://search.rakuten.co.jp/search/mall/%E3%83%8A%E3%83%AB%E3%83%8B%E3%82%A2%E5%9B%BD%E7%89%A9%E8%AA%9E%20%E3%82%B8%E3%82%AA%E3%83%A9%E3%83%9E%20%E3%83%96%E3%83%83%E3%82%AF%E3%82%A8%E3%83%B3%E3%83%89%20%E8%A1%97%E7%81%AF/?min=10000 | Q16: https://auctions.yahoo.co.jp/search/search?p=%E3%83%8A%E3%83%AB%E3%83%8B%E3%82%A2%E5%9B%BD%E7%89%A9%E8%AA%9E%20%E3%82%B8%E3%82%AA%E3%83%A9%E3%83%9E%20%E3%83%96%E3%83%83%E3%82%AF%E3%82%A8%E3%83%B3%E3%83%89%20%E8%A1%97%E7%81%AF&aucminprice=10000 | R16: https://shopping.yahoo.co.jp/search/%E3%83%8A%E3%83%AB%E3%83%8B%E3%82%A2%E5%9B%BD%E7%89%A9%E8%AA%9E%20%E3%82%B8%E3%82%AA%E3%83%A9%E3%83%9E%20%E3%83%96%E3%83%83%E3%82%AF%E3%82%A8%E3%83%B3%E3%83%89%20%E8%A1%97%E7%81%AF/0/?pf=10000
A17: 1673 | B17: 仮面ライダーギーツ DXメモリアルヴィジョンドライバー&ベルト帯セット | C17: 1 | D17: 24444 | E17: 370 | F17: Fedex 3.0kg | G17: https://www.ebay.com/sch/i.html?_nkw=Kamen%20Rider%20Geats%20Vision%20Driver&_sacat=0&_from=R40&_sop=15&rt=nc&_udlo=20000 | H17: https://page.auctions.yahoo.co.jp/jp/auction/u1237001539 | I17: https://jp.mercari.com/item/m89165612254 | J17: https://auctions.yahoo.co.jp/jp/auction/r1236372915 | N17: https://jp.mercari.com/search?keyword=%E3%83%90%E3%83%B3%E3%83%80%E3%82%A4%20PREMIUM%20DX%20%E3%83%A1%E3%83%A2%E3%83%AA%E3%82%A2%E3%83%AB%E3%82%B8%E3%83%AA%E3%82%AA%E3%83%B3%E3%83%89%E3%83%A9%E3%82%A4%E3%83%90%E3%83%BC&price_min=10000&sort=price&order=asc&status=on_sale | O17: https://fril.jp/s?query=%E3%83%90%E3%83%B3%E3%83%80%E3%82%A4%20PREMIUM%20DX%20%E3%83%A1%E3%83%A2%E3%83%AA%E3%82%A2%E3%83%AB%E3%82%B8%E3%83%AA%E3%82%AA%E3%83%B3%E3%83%89%E3%83%A9%E3%82%A4%E3%83%90%E3%83%BC&min=10000&transaction=selling | P17: https://search.rakuten.co.jp/search/mall/%E3%83%90%E3%83%B3%E3%83%80%E3%82%A4%20PREMIUM%20DX%20%E3%83%A1%E3%83%A2%E3%83%AA%E3%82%A2%E3%83%AB%E3%82%B8%E3%83%AA%E3%82%AA%E3%83%B3%E3%83%89%E3%83%A9%E3%82%A4%E3%83%90%E3%83%BC/?min=10000 | Q17: https://auctions.yahoo.co.jp/search/search?p=%E3%83%90%E3%83%B3%E3%83%80%E3%82%A4%20PREMIUM%20DX%20%E3%83%A1%E3%83%A2%E3%83%AA%E3%82%A2%E3%83%AB%E3%82%B8%E3%83%AA%E3%82%AA%E3%83%B3%E3%83%89%E3%83%A9%E3%82%A4%E3%83%90%E3%83%BC&aucminprice=10000 | R17: https://shopping.yahoo.co.jp/search/%E3%83%90%E3%83%B3%E3%83%80%E3%82%A4%20PREMIUM%20DX%20%E3%83%A1%E3%83%A2%E3%83%AA%E3%82%A2%E3%83%AB%E3%82%B8%E3%83%AA%E3%82%AA%E3%83%B3%E3%83%89%E3%83%A9%E3%82%A4%E3%83%90%E3%83%BC/0/?pf=10000
A18: 1674 | B18: Roland PG-800 プログラマー JX-8P/JX-10/MKS-70用 | C18: 1 | D18: 71000 | E18: 830 | F18: Fedex 5.5kg | G18: https://www.ebay.com/sch/i.html?_nkw=Roland%20PG-800&_sacat=0&_from=R40&_sop=15&rt=nc&_udlo=20000 | H18: https://jp.mercari.com/item/m67981041003 | N18: https://jp.mercari.com/search?keyword=Roland%20PG-800&price_min=10000&sort=price&order=asc&status=on_sale | O18: https://fril.jp/s?query=Roland%20PG-800&min=10000&transaction=selling | P18: https://search.rakuten.co.jp/search/mall/Roland%20PG-800/?min=10000 | Q18: https://auctions.yahoo.co.jp/search/search?p=Roland%20PG-800&aucminprice=10000 | R18: https://shopping.yahoo.co.jp/search/Roland%20PG-800/0/?pf=10000
A19: 1675 | B19: ポケモントランプ 金 Part2 (箱付・全揃) | C19: 1 | D19: 25000 | E19: 354 | F19: Fedex 0.5kg | G19: https://www.ebay.com/sch/i.html?_nkw=Pokemon%20Trump%20Part%202%20Gold&_sacat=0&_from=R40&_sop=15&rt=nc&_udlo=20000 | H19: https://jp.mercari.com/item/m90466462651 | N19: https://jp.mercari.com/search?keyword=%E3%83%9D%E3%82%B1%E3%83%A2%E3%83%B3%E3%83%88%E3%83%A9%E3%83%B3%E3%83%97%20%E9%87%91%20Part2&price_min=10000&sort=price&order=asc&status=on_sale | O19: https://fril.jp/s?query=%E3%83%9D%E3%82%B1%E3%83%A2%E3%83%B3%E3%83%88%E3%83%A9%E3%83%B3%E3%83%97%20%E9%87%91%20Part2&min=10000&transaction=selling | P19: https://search.rakuten.co.jp/search/mall/%E3%83%9D%E3%82%B1%E3%83%A2%E3%83%B3%E3%83%88%E3%83%A9%E3%83%B3%E3%83%97%20%E9%87%91%20Part2/?min=10000 | Q19: https://auctions.yahoo.co.jp/search/search?p=%E3%83%9D%E3%82%B1%E3%83%A2%E3%83%B3%E3%83%88%E3%83%A9%E3%83%B3%E3%83%97%20%E9%87%91%20Part2&aucminprice=10000 | R19: https://shopping.yahoo.co.jp/search/%E3%83%9D%E3%82%B1%E3%83%A2%E3%83%B3%E3%83%88%E3%83%A9%E3%83%B3%E3%83%97%20%E9%87%91%20Part2/0/?pf=10000
A20: 1676 | B20: ワンピース カードダス ルフィ C565 鑑定10 | C20: 1 | D20: 100000 | E20: 1080 | F20: Fedex 0.5kg | G20: https://www.ebay.com/sch/i.html?_nkw=One%20Piece%20Carddass%20Luffy%20C565&_sacat=0&_from=R40&_sop=15&rt=nc&_udlo=20000 | H20: https://page.auctions.yahoo.co.jp/jp/auction/h1227562797 | N20: https://jp.mercari.com/search?keyword=%E3%83%AF%E3%83%B3%E3%83%94%E3%83%BC%E3%82%B9%20%E3%82%AB%E3%83%BC%E3%83%89%E3%83%80%E3%82%B9%20%E3%83%AB%E3%83%95%E3%82%A3%20C565&price_min=10000&sort=price&order=asc&status=on_sale | O20: https://fril.jp/s?query=%E3%83%AF%E3%83%B3%E3%83%94%E3%83%BC%E3%82%B9%20%E3%82%AB%E3%83%BC%E3%83%89%E3%83%80%E3%82%B9%20%E3%83%AB%E3%83%95%E3%82%A3%20C565&min=10000&transaction=selling | P20: https://search.rakuten.co.jp/search/mall/%E3%83%AF%E3%83%B3%E3%83%94%E3%83%BC%E3%82%B9%20%E3%82%AB%E3%83%BC%E3%83%89%E3%83%80%E3%82%B9%20%E3%83%AB%E3%83%95%E3%82%A3%20C565/?min=10000 | Q20: https://auctions.yahoo.co.jp/search/search?p=%E3%83%AF%E3%83%B3%E3%83%94%E3%83%BC%E3%82%B9%20%E3%82%AB%E3%83%BC%E3%83%89%E3%83%80%E3%82%B9%20%E3%83%AB%E3%83%95%E3%82%A3%20C565&aucminprice=10000 | R20: https://shopping.yahoo.co.jp/search/%E3%83%AF%E3%83%B3%E3%83%94%E3%83%BC%E3%82%B9%20%E3%82%AB%E3%83%BC%E3%83%89%E3%83%80%E3%82%B9%20%E3%83%AB%E3%83%95%E3%82%A3%20C565/0/?pf=10000
A21: 1677 | B21: ワンピース カードダス 怪盗ルフィ 98 麦わら航海記 | C21: 1 | D21: 100000 | E21: 1080 | F21: Fedex 0.5kg | G21: https://www.ebay.com/sch/i.html?_nkw=One%20Piece%20Carddass%20Luffy%2098&_sacat=0&_from=R40&_sop=15&rt=nc&_udlo=20000 | H21: https://page.auctions.yahoo.co.jp/jp/auction/m1236970434 | N21: https://jp.mercari.com/search?keyword=%E3%83%AF%E3%83%B3%E3%83%94%E3%83%BC%E3%82%B9%20%E3%82%AB%E3%83%BC%E3%83%89%E3%83%80%E3%82%B9%20%E9%BA%A6%E3%82%8F%E3%82%89&price_min=10000&sort=price&order=asc&status=on_sale | O21: https://fril.jp/s?query=%E3%83%AF%E3%83%B3%E3%83%94%E3%83%BC%E3%82%B9%20%E3%82%AB%E3%83%BC%E3%83%89%E3%83%80%E3%82%B9%20%E9%BA%A6%E3%82%8F%E3%82%89&min=10000&transaction=selling | P21: https://search.rakuten.co.jp/search/mall/%E3%83%AF%E3%83%B3%E3%83%94%E3%83%BC%E3%82%B9%20%E3%82%AB%E3%83%BC%E3%83%89%E3%83%80%E3%82%B9%20%E9%BA%A6%E3%82%8F%E3%82%89/?min=10000 | Q21: https://auctions.yahoo.co.jp/search/search?p=%E3%83%AF%E3%83%B3%E3%83%94%E3%83%BC%E3%82%B9%20%E3%82%AB%E3%83%BC%E3%83%89%E3%83%80%E3%82%B9%20%E9%BA%A6%E3%82%8F%E3%82%89&aucminprice=10000 | R21: https://shopping.yahoo.co.jp/search/%E3%83%AF%E3%83%B3%E3%83%94%E3%83%BC%E3%82%B9%20%E3%82%AB%E3%83%BC%E3%83%89%E3%83%80%E3%82%B9%20%E9%BA%A6%E3%82%8F%E3%82%89/0/?pf=10000
A22: 1678 | B22: 魔女の宅急便 サントラ音楽集 LP レコード (オリジナル盤1989) | C22: 1 | D22: 49999 | E22: 720 | F22: Fedex 1.5kg | G22: https://www.ebay.com/sch/i.html?_nkw=Kiki%20Delivery%20Service%20Soundtrack%20LP&_sacat=0&_from=R40&_sop=15&rt=nc&_udlo=20000 | H22: https://jp.mercari.com/item/m58362558513 | N22: https://jp.mercari.com/search?keyword=%E9%AD%94%E5%A5%B3%E3%81%AE%E5%AE%85%E6%80%A5%E4%BE%BF%20%E3%82%B5%E3%83%B3%E3%83%88%E3%83%A9&price_min=10000&sort=price&order=asc&status=on_sale | O22: https://fril.jp/s?query=%E9%AD%94%E5%A5%B3%E3%81%AE%E5%AE%85%E6%80%A5%E4%BE%BF%20%E3%82%B5%E3%83%B3%E3%83%88%E3%83%A9&min=10000&transaction=selling | P22: https://search.rakuten.co.jp/search/mall/%E9%AD%94%E5%A5%B3%E3%81%AE%E5%AE%85%E6%80%A5%E4%BE%BF%20%E3%82%B5%E3%83%B3%E3%83%88%E3%83%A9/?min=10000 | Q22: https://auctions.yahoo.co.jp/search/search?p=%E9%AD%94%E5%A5%B3%E3%81%AE%E5%AE%85%E6%80%A5%E4%BE%BF%20%E3%82%B5%E3%83%B3%E3%83%88%E3%83%A9&aucminprice=10000 | R22: https://shopping.yahoo.co.jp/search/%E9%AD%94%E5%A5%B3%E3%81%AE%E5%AE%85%E6%80%A5%E4%BE%BF%20%E3%82%B5%E3%83%B3%E3%83%88%E3%83%A9/0/?pf=10000
A23: 1679 | B23: ジブリパーク限定 食べ物マグネット 6種セット (リニューアル版) | C23: 1 | D23: 17122 | E23: 269 | F23: Fedex 0.5kg | G23: https://www.ebay.com/sch/i.html?_nkw=Ghibli%20Park%20Food%20Magnet%20Set&_sacat=0&_from=R40&_sop=15&rt=nc&_udlo=20000 | H23: https://jp.mercari.com/item/m30295800802 | N23: https://jp.mercari.com/search?keyword=%E3%82%B8%E3%83%96%E3%83%AA%E3%83%91%E3%83%BC%E3%82%AF%20%E9%A3%9F%E3%81%B9%E7%89%A9%20%E3%83%9E%E3%82%B0%E3%83%8D%E3%83%83%E3%83%88%206%E7%A8%AE%20%E3%82%BB%E3%83%83%E3%83%88&price_min=10000&sort=price&order=asc&status=on_sale | O23: https://fril.jp/s?query=%E3%82%B8%E3%83%96%E3%83%AA%E3%83%91%E3%83%BC%E3%82%AF%20%E9%A3%9F%E3%81%B9%E7%89%A9%20%E3%83%9E%E3%82%B0%E3%83%8D%E3%83%83%E3%83%88%206%E7%A8%AE%20%E3%82%BB%E3%83%83%E3%83%88&min=10000&transaction=selling | P23: https://search.rakuten.co.jp/search/mall/%E3%82%B8%E3%83%96%E3%83%AA%E3%83%91%E3%83%BC%E3%82%AF%20%E9%A3%9F%E3%81%B9%E7%89%A9%20%E3%83%9E%E3%82%B0%E3%83%8D%E3%83%83%E3%83%88%206%E7%A8%AE%20%E3%82%BB%E3%83%83%E3%83%88/?min=10000 | Q23: https://auctions.yahoo.co.jp/search/search?p=%E3%82%B8%E3%83%96%E3%83%AA%E3%83%91%E3%83%BC%E3%82%AF%20%E9%A3%9F%E3%81%B9%E7%89%A9%20%E3%83%9E%E3%82%B0%E3%83%8D%E3%83%83%E3%83%88%206%E7%A8%AE%20%E3%82%BB%E3%83%83%E3%83%88&aucminprice=10000 | R23: https://shopping.yahoo.co.jp/search/%E3%82%B8%E3%83%96%E3%83%AA%E3%83%91%E3%83%BC%E3%82%AF%20%E9%A3%9F%E3%81%B9%E7%89%A9%20%E3%83%9E%E3%82%B0%E3%83%8D%E3%83%83%E3%83%88%206%E7%A8%AE%20%E3%82%BB%E3%83%83%E3%83%88/0/?pf=10000
A24: 1680 | B24: ジブリの大倉庫限定 陶器ブローチ 全4種 | C24: 1 | D24: 51000 | E24: 560 | F24: Fedex 0.5kg | G24: https://www.ebay.com/sch/i.html?_nkw=Ghibli%20Warehouse%20Brooch%20Set&_sacat=0&_from=R40&_sop=15&rt=nc&_udlo=20000 | H24: https://page.auctions.yahoo.co.jp/jp/auction/s1091867531 | N24: https://jp.mercari.com/search?keyword=%E3%82%B8%E3%83%96%E3%83%AA%E3%83%91%E3%83%BC%E3%82%AF%20%E3%83%96%E3%83%AD%E3%83%BC%E3%83%81%20%E3%82%BB%E3%83%83%E3%83%88&price_min=10000&sort=price&order=asc&status=on_sale | O24: https://fril.jp/s?query=%E3%82%B8%E3%83%96%E3%83%AA%E3%83%91%E3%83%BC%E3%82%AF%20%E3%83%96%E3%83%AD%E3%83%BC%E3%83%81%20%E3%82%BB%E3%83%83%E3%83%88&min=10000&transaction=selling | P24: https://search.rakuten.co.jp/search/mall/%E3%82%B8%E3%83%96%E3%83%AA%E3%83%91%E3%83%BC%E3%82%AF%20%E3%83%96%E3%83%AD%E3%83%BC%E3%83%81%20%E3%82%BB%E3%83%83%E3%83%88/?min=10000 | Q24: https://auctions.yahoo.co.jp/search/search?p=%E3%82%B8%E3%83%96%E3%83%AA%E3%83%91%E3%83%BC%E3%82%AF%20%E3%83%96%E3%83%AD%E3%83%BC%E3%83%81%20%E3%82%BB%E3%83%83%E3%83%88&aucminprice=10000 | R24: https://shopping.yahoo.co.jp/search/%E3%82%B8%E3%83%96%E3%83%AA%E3%83%91%E3%83%BC%E3%82%AF%20%E3%83%96%E3%83%AD%E3%83%BC%E3%83%81%20%E3%82%BB%E3%83%83%E3%83%88/0/?pf=10000
A25: 1681 | B25: スタートレックTNG エンタープライズ NCC-1701D バトルダメージ (ツクダ/電子音) | C25: 1 | D25: 15500 | E25: 288 | F25: Fedex 2.5kg | G25: https://www.ebay.com/sch/i.html?_nkw=Star%20Trek%20Enterprise%20NCC-1701-D%20Tsukuda&_sacat=0&_from=R40&_sop=15&rt=nc&_udlo=20000 | H25: https://jp.mercari.com/item/m41727262239 | N25: https://jp.mercari.com/search?keyword=%E3%82%B9%E3%82%BF%E3%83%BC%E3%83%88%E3%83%AC%E3%83%83%E3%82%AF%20%E3%82%A8%E3%83%B3%E3%82%BF%E3%83%BC%E3%83%97%E3%83%A9%E3%82%A4%E3%82%BA%20NCC-1701D%20%E3%83%84%E3%82%AF%E3%83%80&price_min=10000&sort=price&order=asc&status=on_sale | O25: https://fril.jp/s?query=%E3%82%B9%E3%82%BF%E3%83%BC%E3%83%88%E3%83%AC%E3%83%83%E3%82%AF%20%E3%82%A8%E3%83%B3%E3%82%BF%E3%83%BC%E3%83%97%E3%83%A9%E3%82%A4%E3%82%BA%20NCC-1701D%20%E3%83%84%E3%82%AF%E3%83%80&min=10000&transaction=selling | P25: https://search.rakuten.co.jp/search/mall/%E3%82%B9%E3%82%BF%E3%83%BC%E3%83%88%E3%83%AC%E3%83%83%E3%82%AF%20%E3%82%A8%E3%83%B3%E3%82%BF%E3%83%BC%E3%83%97%E3%83%A9%E3%82%A4%E3%82%BA%20NCC-1701D%20%E3%83%84%E3%82%AF%E3%83%80/?min=10000 | Q25: https://auctions.yahoo.co.jp/search/search?p=%E3%82%B9%E3%82%BF%E3%83%BC%E3%83%88%E3%83%AC%E3%83%83%E3%82%AF%20%E3%82%A8%E3%83%B3%E3%82%BF%E3%83%BC%E3%83%97%E3%83%A9%E3%82%A4%E3%82%BA%20NCC-1701D%20%E3%83%84%E3%82%AF%E3%83%80&aucminprice=10000 | R25: https://shopping.yahoo.co.jp/search/%E3%82%B9%E3%82%BF%E3%83%BC%E3%83%88%E3%83%AC%E3%83%83%E3%82%AF%20%E3%82%A8%E3%83%B3%E3%82%BF%E3%83%BC%E3%83%97%E3%83%A9%E3%82%A4%E3%82%BA%20NCC-1701D%20%E3%83%84%E3%82%AF%E3%83%80/0/?pf=10000
A26: 1682 | B26: デスノート 弥海砂 モエアート 1/6 フィギュア ホワイトVer | C26: 1 | D26: 53900 | E26: 650 | F26: Fedex 3.0kg | G26: https://www.ebay.com/sch/i.html?_nkw=Death%20Note%20Misa%20Amane%20Figure&_sacat=0&_from=R40&_sop=15&rt=nc&_udlo=20000 | H26: https://jp.mercari.com/item/m46259035317 | N26: https://jp.mercari.com/search?keyword=%E3%83%87%E3%82%B9%E3%83%8E%E3%83%BC%E3%83%88%20%E5%BC%A5%E6%B5%B7%E7%A0%82%20%E3%83%9B%E3%83%AF%E3%82%A4%E3%83%88%20%E3%83%95%E3%82%A3%E3%82%AE%E3%83%A5%E3%82%A2&price_min=10000&sort=price&order=asc&status=on_sale | O26: https://fril.jp/s?query=%E3%83%87%E3%82%B9%E3%83%8E%E3%83%BC%E3%83%88%20%E5%BC%A5%E6%B5%B7%E7%A0%82%20%E3%83%9B%E3%83%AF%E3%82%A4%E3%83%88%20%E3%83%95%E3%82%A3%E3%82%AE%E3%83%A5%E3%82%A2&min=10000&transaction=selling | P26: https://search.rakuten.co.jp/search/mall/%E3%83%87%E3%82%B9%E3%83%8E%E3%83%BC%E3%83%88%20%E5%BC%A5%E6%B5%B7%E7%A0%82%20%E3%83%9B%E3%83%AF%E3%82%A4%E3%83%88%20%E3%83%95%E3%82%A3%E3%82%AE%E3%83%A5%E3%82%A2/?min=10000 | Q26: https://auctions.yahoo.co.jp/search/search?p=%E3%83%87%E3%82%B9%E3%83%8E%E3%83%BC%E3%83%88%20%E5%BC%A5%E6%B5%B7%E7%A0%82%20%E3%83%9B%E3%83%AF%E3%82%A4%E3%83%88%20%E3%83%95%E3%82%A3%E3%82%AE%E3%83%A5%E3%82%A2&aucminprice=10000 | R26: https://shopping.yahoo.co.jp/search/%E3%83%87%E3%82%B9%E3%83%8E%E3%83%BC%E3%83%88%20%E5%BC%A5%E6%B5%B7%E7%A0%82%20%E3%83%9B%E3%83%AF%E3%82%A4%E3%83%88%20%E3%83%95%E3%82%A3%E3%82%AE%E3%83%A5%E3%82%A2/0/?pf=10000
A27: 1683 | B27: ファイナルファンタジーXIV 輪島塗デザインプレート バハムート | C27: 1 | D27: 89098 | E27: 1109 | F27: Fedex 6.0kg | G27: https://www.ebay.com/sch/i.html?_nkw=Final%20Fantasy%20XIV%20Wajima%20Plate&_sacat=0&_from=R40&_sop=15&rt=nc&_udlo=20000 | H27: https://jp.mercari.com/item/m81521630117 | I27: https://paypayfleamarket.yahoo.co.jp/item/z346118678 | N27: https://jp.mercari.com/search?keyword=FF14%20%E8%BC%AA%E5%B3%B6%E5%A1%97%20%E3%83%97%E3%83%AC%E3%83%BC%E3%83%88%20%E3%83%90%E3%83%8F%E3%83%A0%E3%83%BC%E3%83%88&price_min=10000&sort=price&order=asc&status=on_sale | O27: https://fril.jp/s?query=FF14%20%E8%BC%AA%E5%B3%B6%E5%A1%97%20%E3%83%97%E3%83%AC%E3%83%BC%E3%83%88%20%E3%83%90%E3%83%8F%E3%83%A0%E3%83%BC%E3%83%88&min=10000&transaction=selling | P27: https://search.rakuten.co.jp/search/mall/FF14%20%E8%BC%AA%E5%B3%B6%E5%A1%97%20%E3%83%97%E3%83%AC%E3%83%BC%E3%83%88%20%E3%83%90%E3%83%8F%E3%83%A0%E3%83%BC%E3%83%88/?min=10000 | Q27: https://auctions.yahoo.co.jp/search/search?p=FF14%20%E8%BC%AA%E5%B3%B6%E5%A1%97%20%E3%83%97%E3%83%AC%E3%83%BC%E3%83%88%20%E3%83%90%E3%83%8F%E3%83%A0%E3%83%BC%E3%83%88&aucminprice=10000 | R27: https://shopping.yahoo.co.jp/search/FF14%20%E8%BC%AA%E5%B3%B6%E5%A1%97%20%E3%83%97%E3%83%AC%E3%83%BC%E3%83%88%20%E3%83%90%E3%83%8F%E3%83%A0%E3%83%BC%E3%83%88/0/?pf=10000
A28: 1684 | B28: アビランド リモージュ ヴューパリヴェール デミタス カップ＆ソーサー6客セット | C28: 1 | D28: 17000 | E28: 358 | F28: Fedex 4.5kg | G28: https://www.ebay.com/sch/i.html?_nkw=Haviland%20Limoges%20Demitasse%20Cup&_sacat=0&_from=R40&_sop=15&rt=nc&_udlo=20000 | H28: https://jp.mercari.com/item/m70961417599 | N28: https://jp.mercari.com/search?keyword=%E3%82%A2%E3%83%93%E3%83%A9%E3%83%B3%E3%83%89%20%E3%83%AA%E3%83%A2%E3%83%BC%E3%82%B8%E3%83%A5%20%E3%83%B4%E3%83%A5%E3%83%BC%E3%83%91%E3%83%AA%E3%83%B4%E3%82%A7%E3%83%BC%E3%83%AB%20%E3%83%87%E3%83%9F%E3%82%BF%E3%82%B9&price_min=10000&sort=price&order=asc&status=on_sale | O28: https://fril.jp/s?query=%E3%82%A2%E3%83%93%E3%83%A9%E3%83%B3%E3%83%89%20%E3%83%AA%E3%83%A2%E3%83%BC%E3%82%B8%E3%83%A5%20%E3%83%B4%E3%83%A5%E3%83%BC%E3%83%91%E3%83%AA%E3%83%B4%E3%82%A7%E3%83%BC%E3%83%AB%20%E3%83%87%E3%83%9F%E3%82%BF%E3%82%B9&min=10000&transaction=selling | P28: https://search.rakuten.co.jp/search/mall/%E3%82%A2%E3%83%93%E3%83%A9%E3%83%B3%E3%83%89%20%E3%83%AA%E3%83%A2%E3%83%BC%E3%82%B8%E3%83%A5%20%E3%83%B4%E3%83%A5%E3%83%BC%E3%83%91%E3%83%AA%E3%83%B4%E3%82%A7%E3%83%BC%E3%83%AB%20%E3%83%87%E3%83%9F%E3%82%BF%E3%82%B9/?min=10000 | Q28: https://auctions.yahoo.co.jp/search/search?p=%E3%82%A2%E3%83%93%E3%83%A9%E3%83%B3%E3%83%89%20%E3%83%AA%E3%83%A2%E3%83%BC%E3%82%B8%E3%83%A5%20%E3%83%B4%E3%83%A5%E3%83%BC%E3%83%91%E3%83%AA%E3%83%B4%E3%82%A7%E3%83%BC%E3%83%AB%20%E3%83%87%E3%83%9F%E3%82%BF%E3%82%B9&aucminprice=10000 | R28: https://shopping.yahoo.co.jp/search/%E3%82%A2%E3%83%93%E3%83%A9%E3%83%B3%E3%83%89%20%E3%83%AA%E3%83%A2%E3%83%BC%E3%82%B8%E3%83%A5%20%E3%83%B4%E3%83%A5%E3%83%BC%E3%83%91%E3%83%AA%E3%83%B4%E3%82%A7%E3%83%BC%E3%83%AB%20%E3%83%87%E3%83%9F%E3%82%BF%E3%82%B9/0/?pf=10000
A29: 1685 | B29: アビランドリモージュ ヴューパリヴェールカップソーサー三客セット | C29: 1 | D29: 16000 | E29: 349 | F29: Fedex 4.5kg | G29: https://www.ebay.com/sch/i.html?_nkw=Haviland%20Limoges%20Cup%20Saucer&_sacat=0&_from=R40&_sop=15&rt=nc&_udlo=20000 | H29: https://jp.mercari.com/item/m28885121634 | N29: https://jp.mercari.com/search?keyword=%E3%82%A2%E3%83%93%E3%83%A9%E3%83%B3%E3%83%89%20%E3%83%AA%E3%83%A2%E3%83%BC%E3%82%B8%E3%83%A5%20%E3%83%B4%E3%83%A5%E3%83%BC%E3%83%91%E3%83%AA%E3%83%B4%E3%82%A7%E3%83%BC%E3%83%AB%20%E3%82%AB%E3%83%83%E3%83%97&price_min=10000&sort=price&order=asc&status=on_sale | O29: https://fril.jp/s?query=%E3%82%A2%E3%83%93%E3%83%A9%E3%83%B3%E3%83%89%20%E3%83%AA%E3%83%A2%E3%83%BC%E3%82%B8%E3%83%A5%20%E3%83%B4%E3%83%A5%E3%83%BC%E3%83%91%E3%83%AA%E3%83%B4%E3%82%A7%E3%83%BC%E3%83%AB%20%E3%82%AB%E3%83%83%E3%83%97&min=10000&transaction=selling | P29: https://search.rakuten.co.jp/search/mall/%E3%82%A2%E3%83%93%E3%83%A9%E3%83%B3%E3%83%89%20%E3%83%AA%E3%83%A2%E3%83%BC%E3%82%B8%E3%83%A5%20%E3%83%B4%E3%83%A5%E3%83%BC%E3%83%91%E3%83%AA%E3%83%B4%E3%82%A7%E3%83%BC%E3%83%AB%20%E3%82%AB%E3%83%83%E3%83%97/?min=10000 | Q29: https://auctions.yahoo.co.jp/search/search?p=%E3%82%A2%E3%83%93%E3%83%A9%E3%83%B3%E3%83%89%20%E3%83%AA%E3%83%A2%E3%83%BC%E3%82%B8%E3%83%A5%20%E3%83%B4%E3%83%A5%E3%83%BC%E3%83%91%E3%83%AA%E3%83%B4%E3%82%A7%E3%83%BC%E3%83%AB%20%E3%82%AB%E3%83%83%E3%83%97&aucminprice=10000 | R29: https://shopping.yahoo.co.jp/search/%E3%82%A2%E3%83%93%E3%83%A9%E3%83%B3%E3%83%89%20%E3%83%AA%E3%83%A2%E3%83%BC%E3%82%B8%E3%83%A5%20%E3%83%B4%E3%83%A5%E3%83%BC%E3%83%91%E3%83%AA%E3%83%B4%E3%82%A7%E3%83%BC%E3%83%AB%20%E3%82%AB%E3%83%83%E3%83%97/0/?pf=10000
A30: 1686 | B30: ハリーポッター レプリカ Alarm Eighteen 吟遊詩人ビードルの物語 | C30: 1 | D30: 66000 | E30: 723 | F30: Fedex 1.5kg | G30: https://www.ebay.com/sch/i.html?_nkw=Harry%20Potter%20Beedle%20Bard%20Book&_sacat=0&_from=R40&_sop=15&rt=nc&_udlo=20000 | H30: https://jp.mercari.com/item/m49065182959 | N30: https://jp.mercari.com/search?keyword=%E3%83%8F%E3%83%AA%E3%83%BC%E3%83%9D%E3%83%83%E3%82%BF%E3%83%BC%20%E3%83%93%E3%83%BC%E3%83%89%E3%83%AB%E3%81%AE%E7%89%A9%E8%AA%9E%20%E3%83%AC%E3%83%97%E3%83%AA%E3%82%AB&price_min=10000&sort=price&order=asc&status=on_sale | O30: https://fril.jp/s?query=%E3%83%8F%E3%83%AA%E3%83%BC%E3%83%9D%E3%83%83%E3%82%BF%E3%83%BC%20%E3%83%93%E3%83%BC%E3%83%89%E3%83%AB%E3%81%AE%E7%89%A9%E8%AA%9E%20%E3%83%AC%E3%83%97%E3%83%AA%E3%82%AB&min=10000&transaction=selling | P30: https://search.rakuten.co.jp/search/mall/%E3%83%8F%E3%83%AA%E3%83%BC%E3%83%9D%E3%83%83%E3%82%BF%E3%83%BC%20%E3%83%93%E3%83%BC%E3%83%89%E3%83%AB%E3%81%AE%E7%89%A9%E8%AA%9E%20%E3%83%AC%E3%83%97%E3%83%AA%E3%82%AB/?min=10000 | Q30: https://auctions.yahoo.co.jp/search/search?p=%E3%83%8F%E3%83%AA%E3%83%BC%E3%83%9D%E3%83%83%E3%82%BF%E3%83%BC%20%E3%83%93%E3%83%BC%E3%83%89%E3%83%AB%E3%81%AE%E7%89%A9%E8%AA%9E%20%E3%83%AC%E3%83%97%E3%83%AA%E3%82%AB&aucminprice=10000 | R30: https://shopping.yahoo.co.jp/search/%E3%83%8F%E3%83%AA%E3%83%BC%E3%83%9D%E3%83%83%E3%82%BF%E3%83%BC%20%E3%83%93%E3%83%BC%E3%83%89%E3%83%AB%E3%81%AE%E7%89%A9%E8%AA%9E%20%E3%83%AC%E3%83%97%E3%83%AA%E3%82%AB/0/?pf=10000
A31: 1687 | B31: ハリーポッター 杖 フェンリール・グレイバック レア ノーブルコレクション | C31: 1 | D31: 89990 | E31: 1050 | F31: Fedex 1.5kg | G31: https://www.ebay.com/sch/i.html?_nkw=Harry%20Potter%20Fenrir%20Greyback%20Wand&_sacat=0&_from=R40&_sop=15&rt=nc&_udlo=20000 | H31: https://jp.mercari.com/item/m12954924232 | N31: https://jp.mercari.com/search?keyword=%E3%83%8F%E3%83%AA%E3%83%BC%E3%83%9D%E3%83%83%E3%82%BF%E3%83%BC%20%E3%83%95%E3%82%A7%E3%83%B3%E3%83%AA%E3%83%BC%E3%83%AB%E3%82%B0%E3%83%AC%E3%82%A4%E3%83%90%E3%83%83%E3%82%AF%20%E6%9D%96%20%E3%83%8E%E3%83%BC%E3%83%96%E3%83%AB&price_min=10000&sort=price&order=asc&status=on_sale | O31: https://fril.jp/s?query=%E3%83%8F%E3%83%AA%E3%83%BC%E3%83%9D%E3%83%83%E3%82%BF%E3%83%BC%20%E3%83%95%E3%82%A7%E3%83%B3%E3%83%AA%E3%83%BC%E3%83%AB%E3%82%B0%E3%83%AC%E3%82%A4%E3%83%90%E3%83%83%E3%82%AF%20%E6%9D%96%20%E3%83%8E%E3%83%BC%E3%83%96%E3%83%AB&min=10000&transaction=selling | P31: https://search.rakuten.co.jp/search/mall/%E3%83%8F%E3%83%AA%E3%83%BC%E3%83%9D%E3%83%83%E3%82%BF%E3%83%BC%20%E3%83%95%E3%82%A7%E3%83%B3%E3%83%AA%E3%83%BC%E3%83%AB%E3%82%B0%E3%83%AC%E3%82%A4%E3%83%90%E3%83%83%E3%82%AF%20%E6%9D%96%20%E3%83%8E%E3%83%BC%E3%83%96%E3%83%AB/?min=10000 | Q31: https://auctions.yahoo.co.jp/search/search?p=%E3%83%8F%E3%83%AA%E3%83%BC%E3%83%9D%E3%83%83%E3%82%BF%E3%83%BC%20%E3%83%95%E3%82%A7%E3%83%B3%E3%83%AA%E3%83%BC%E3%83%AB%E3%82%B0%E3%83%AC%E3%82%A4%E3%83%90%E3%83%83%E3%82%AF%20%E6%9D%96%20%E3%83%8E%E3%83%BC%E3%83%96%E3%83%AB&aucminprice=10000 | R31: https://shopping.yahoo.co.jp/search/%E3%83%8F%E3%83%AA%E3%83%BC%E3%83%9D%E3%83%83%E3%82%BF%E3%83%BC%20%E3%83%95%E3%82%A7%E3%83%B3%E3%83%AA%E3%83%BC%E3%83%AB%E3%82%B0%E3%83%AC%E3%82%A4%E3%83%90%E3%83%83%E3%82%AF%20%E6%9D%96%20%E3%83%8E%E3%83%BC%E3%83%96%E3%83%AB/0/?pf=10000
A32: 1688 | B32: ハリーポッター ネビル ロングボトム 杖 ノーブルコレクション レア | C32: 1 | D32: 89900 | E32: 980 | F32: Fedex 1.5kg | G32: https://www.ebay.com/sch/i.html?_nkw=Harry%20Potter%20Neville%20Longbottom%20Wand&_sacat=0&_from=R40&_sop=15&rt=nc&_udlo=20000 | H32: https://jp.mercari.com/item/m16731501061 | N32: https://jp.mercari.com/search?keyword=%E3%83%8F%E3%83%AA%E3%83%BC%E3%83%9D%E3%83%83%E3%82%BF%E3%83%BC%20%E3%83%8D%E3%83%93%E3%83%AB%20%E6%9D%96%20%E3%83%8E%E3%83%BC%E3%83%96%E3%83%AB%E3%82%B3%E3%83%AC%E3%82%AF%E3%82%B7%E3%83%A7%E3%83%B3&price_min=10000&sort=price&order=asc&status=on_sale | O32: https://fril.jp/s?query=%E3%83%8F%E3%83%AA%E3%83%BC%E3%83%9D%E3%83%83%E3%82%BF%E3%83%BC%20%E3%83%8D%E3%83%93%E3%83%AB%20%E6%9D%96%20%E3%83%8E%E3%83%BC%E3%83%96%E3%83%AB%E3%82%B3%E3%83%AC%E3%82%AF%E3%82%B7%E3%83%A7%E3%83%B3&min=10000&transaction=selling | P32: https://search.rakuten.co.jp/search/mall/%E3%83%8F%E3%83%AA%E3%83%BC%E3%83%9D%E3%83%83%E3%82%BF%E3%83%BC%20%E3%83%8D%E3%83%93%E3%83%AB%20%E6%9D%96%20%E3%83%8E%E3%83%BC%E3%83%96%E3%83%AB%E3%82%B3%E3%83%AC%E3%82%AF%E3%82%B7%E3%83%A7%E3%83%B3/?min=10000 | Q32: https://auctions.yahoo.co.jp/search/search?p=%E3%83%8F%E3%83%AA%E3%83%BC%E3%83%9D%E3%83%83%E3%82%BF%E3%83%BC%20%E3%83%8D%E3%83%93%E3%83%AB%20%E6%9D%96%20%E3%83%8E%E3%83%BC%E3%83%96%E3%83%AB%E3%82%B3%E3%83%AC%E3%82%AF%E3%82%B7%E3%83%A7%E3%83%B3&aucminprice=10000 | R32: https://shopping.yahoo.co.jp/search/%E3%83%8F%E3%83%AA%E3%83%BC%E3%83%9D%E3%83%83%E3%82%BF%E3%83%BC%20%E3%83%8D%E3%83%93%E3%83%AB%20%E6%9D%96%20%E3%83%8E%E3%83%BC%E3%83%96%E3%83%AB%E3%82%B3%E3%83%AC%E3%82%AF%E3%82%B7%E3%83%A7%E3%83%B3/0/?pf=10000
A33: 1689 | B33: ハリーポッター 杖 チョウチャン レア ノーブルコレクション 1st | C33: 1 | D33: 84990 | E33: 930 | F33: Fedex 1.5kg | G33: https://www.ebay.com/sch/i.html?_nkw=Harry%20Potter%20Cho%20Chang%20Wand&_sacat=0&_from=R40&_sop=15&rt=nc&_udlo=20000 | H33: https://jp.mercari.com/item/m57859073121 | N33: https://jp.mercari.com/search?keyword=%E3%83%8F%E3%83%AA%E3%83%BC%E3%83%9D%E3%83%83%E3%82%BF%E3%83%BC%20%E3%83%81%E3%83%A7%E3%82%A6%E3%83%81%E3%83%A3%E3%83%B3%20%E6%9D%96%20%E3%83%8E%E3%83%BC%E3%83%96%E3%83%AB&price_min=10000&sort=price&order=asc&status=on_sale | O33: https://fril.jp/s?query=%E3%83%8F%E3%83%AA%E3%83%BC%E3%83%9D%E3%83%83%E3%82%BF%E3%83%BC%20%E3%83%81%E3%83%A7%E3%82%A6%E3%83%81%E3%83%A3%E3%83%B3%20%E6%9D%96%20%E3%83%8E%E3%83%BC%E3%83%96%E3%83%AB&min=10000&transaction=selling | P33: https://search.rakuten.co.jp/search/mall/%E3%83%8F%E3%83%AA%E3%83%BC%E3%83%9D%E3%83%83%E3%82%BF%E3%83%BC%20%E3%83%81%E3%83%A7%E3%82%A6%E3%83%81%E3%83%A3%E3%83%B3%20%E6%9D%96%20%E3%83%8E%E3%83%BC%E3%83%96%E3%83%AB/?min=10000 | Q33: https://auctions.yahoo.co.jp/search/search?p=%E3%83%8F%E3%83%AA%E3%83%BC%E3%83%9D%E3%83%83%E3%82%BF%E3%83%BC%20%E3%83%81%E3%83%A7%E3%82%A6%E3%83%81%E3%83%A3%E3%83%B3%20%E6%9D%96%20%E3%83%8E%E3%83%BC%E3%83%96%E3%83%AB&aucminprice=10000 | R33: https://shopping.yahoo.co.jp/search/%E3%83%8F%E3%83%AA%E3%83%BC%E3%83%9D%E3%83%83%E3%82%BF%E3%83%BC%20%E3%83%81%E3%83%A7%E3%82%A6%E3%83%81%E3%83%A3%E3%83%B3%20%E6%9D%96%20%E3%83%8E%E3%83%BC%E3%83%96%E3%83%AB/0/?pf=10000
A34: 1690 | B34: ゴーゴーファイブ SHODO SUPER 救急戦隊ゴーゴー... | C34: 1 | D34: 20460 | E34: 280 | F34: Fedex 1.0kg | G34: https://www.ebay.com/sch/i.html?_nkw=SHODO%20SUPER%20GoGo%20Five&_sacat=0&_from=R40&_sop=15&rt=nc&_udlo=20000 | H34: https://jp.mercari.com/shops/product/2JUTKRfw4o5HSbGTRtQXjz | N34: https://jp.mercari.com/search?keyword=SHODO%20SUPER%20%E3%82%B4%E3%83%BC%E3%82%B4%E3%83%BC%E3%83%95%E3%82%A1%E3%82%A4%E3%83%96&price_min=10000&sort=price&order=asc&status=on_sale | O34: https://fril.jp/s?query=SHODO%20SUPER%20%E3%82%B4%E3%83%BC%E3%82%B4%E3%83%BC%E3%83%95%E3%82%A1%E3%82%A4%E3%83%96&min=10000&transaction=selling | P34: https://search.rakuten.co.jp/search/mall/SHODO%20SUPER%20%E3%82%B4%E3%83%BC%E3%82%B4%E3%83%BC%E3%83%95%E3%82%A1%E3%82%A4%E3%83%96/?min=10000 | Q34: https://auctions.yahoo.co.jp/search/search?p=SHODO%20SUPER%20%E3%82%B4%E3%83%BC%E3%82%B4%E3%83%BC%E3%83%95%E3%82%A1%E3%82%A4%E3%83%96&aucminprice=10000 | R34: https://shopping.yahoo.co.jp/search/SHODO%20SUPER%20%E3%82%B4%E3%83%BC%E3%82%B4%E3%83%BC%E3%83%95%E3%82%A1%E3%82%A4%E3%83%96/0/?pf=10000
A35: 1691 | B35: 【稀少品】マンハッタンカフェ菊花賞ウマ娘ぬいぐるみ競馬アイドルホースAVANTI | C35: 1 | D35: 77777 | E35: 950 | F35: Fedex 1.5kg | G35: https://www.ebay.com/sch/i.html?_nkw=Manhattan%20Cafe%20idol%20horse%20plush&_sacat=0&_from=R40&_sop=15&rt=nc&_udlo=20000 | H35: https://jp.mercari.com/item/m16315707571 | I35: https://paypayfleamarket.yahoo.co.jp/item/z622042994 | N35: https://jp.mercari.com/search?keyword=%E3%83%9E%E3%83%B3%E3%83%8F%E3%83%83%E3%82%BF%E3%83%B3%E3%82%AB%E3%83%95%E3%82%A7%20%E3%81%AC%E3%81%84%E3%81%90%E3%82%8B%E3%81%BF%20%E3%82%A2%E3%82%A4%E3%83%89%E3%83%AB%E3%83%9B%E3%83%BC%E3%82%B9&price_min=10000&sort=price&order=asc&status=on_sale | O35: https://fril.jp/s?query=%E3%83%9E%E3%83%B3%E3%83%8F%E3%83%83%E3%82%BF%E3%83%B3%E3%82%AB%E3%83%95%E3%82%A7%20%E3%81%AC%E3%81%84%E3%81%90%E3%82%8B%E3%81%BF%20%E3%82%A2%E3%82%A4%E3%83%89%E3%83%AB%E3%83%9B%E3%83%BC%E3%82%B9&min=10000&transaction=selling | P35: https://search.rakuten.co.jp/search/mall/%E3%83%9E%E3%83%B3%E3%83%8F%E3%83%83%E3%82%BF%E3%83%B3%E3%82%AB%E3%83%95%E3%82%A7%20%E3%81%AC%E3%81%84%E3%81%90%E3%82%8B%E3%81%BF%20%E3%82%A2%E3%82%A4%E3%83%89%E3%83%AB%E3%83%9B%E3%83%BC%E3%82%B9/?min=10000 | Q35: https://auctions.yahoo.co.jp/search/search?p=%E3%83%9E%E3%83%B3%E3%83%8F%E3%83%83%E3%82%BF%E3%83%B3%E3%82%AB%E3%83%95%E3%82%A7%20%E3%81%AC%E3%81%84%E3%81%90%E3%82%8B%E3%81%BF%20%E3%82%A2%E3%82%A4%E3%83%89%E3%83%AB%E3%83%9B%E3%83%BC%E3%82%B9&aucminprice=10000 | R35: https://shopping.yahoo.co.jp/search/%E3%83%9E%E3%83%B3%E3%83%8F%E3%83%83%E3%82%BF%E3%83%B3%E3%82%AB%E3%83%95%E3%82%A7%20%E3%81%AC%E3%81%84%E3%81%90%E3%82%8B%E3%81%BF%20%E3%82%A2%E3%82%A4%E3%83%89%E3%83%AB%E3%83%9B%E3%83%BC%E3%82%B9/0/?pf=10000
A36: 1692 | B36: 【限定】マイネルラヴぬいぐるみウマ娘競馬アイドルホース馬AVANTIシルクロード | C36: 1 | D36: 59999 | E36: 670 | F36: Fedex 1.5kg | G36: https://www.ebay.com/sch/i.html?_nkw=Meiner%20Love%20idol%20horse%20plush&_sacat=0&_from=R40&_sop=15&rt=nc&_udlo=20000 | H36: https://paypayfleamarket.yahoo.co.jp/item/z573178766 | N36: https://jp.mercari.com/search?keyword=%E3%83%9E%E3%82%A4%E3%83%8D%E3%83%AB%E3%83%A9%E3%83%B4%20%E3%81%AC%E3%81%84%E3%81%90%E3%82%8B%E3%81%BF%20%E3%82%A2%E3%82%A4%E3%83%89%E3%83%AB%E3%83%9B%E3%83%BC%E3%82%B9&price_min=10000&sort=price&order=asc&status=on_sale | O36: https://fril.jp/s?query=%E3%83%9E%E3%82%A4%E3%83%8D%E3%83%AB%E3%83%A9%E3%83%B4%20%E3%81%AC%E3%81%84%E3%81%90%E3%82%8B%E3%81%BF%20%E3%82%A2%E3%82%A4%E3%83%89%E3%83%AB%E3%83%9B%E3%83%BC%E3%82%B9&min=10000&transaction=selling | P36: https://search.rakuten.co.jp/search/mall/%E3%83%9E%E3%82%A4%E3%83%8D%E3%83%AB%E3%83%A9%E3%83%B4%20%E3%81%AC%E3%81%84%E3%81%90%E3%82%8B%E3%81%BF%20%E3%82%A2%E3%82%A4%E3%83%89%E3%83%AB%E3%83%9B%E3%83%BC%E3%82%B9/?min=10000 | Q36: https://auctions.yahoo.co.jp/search/search?p=%E3%83%9E%E3%82%A4%E3%83%8D%E3%83%AB%E3%83%A9%E3%83%B4%20%E3%81%AC%E3%81%84%E3%81%90%E3%82%8B%E3%81%BF%20%E3%82%A2%E3%82%A4%E3%83%89%E3%83%AB%E3%83%9B%E3%83%BC%E3%82%B9&aucminprice=10000 | R36: https://shopping.yahoo.co.jp/search/%E3%83%9E%E3%82%A4%E3%83%8D%E3%83%AB%E3%83%A9%E3%83%B4%20%E3%81%AC%E3%81%84%E3%81%90%E3%82%8B%E3%81%BF%20%E3%82%A2%E3%82%A4%E3%83%89%E3%83%AB%E3%83%9B%E3%83%BC%E3%82%B9/0/?pf=10000
A37: 1693 | B37: 【稀少】マチカネフクキタルぬいぐるみウマ娘 アイドルホース競馬 馬 AVANTI | C37: 1 | D37: 53399 | E37: 630 | F37: Fedex 1.5kg | G37: https://www.ebay.com/sch/i.html?_nkw=Matikanefukukitaru%20idol%20horse%20plush&_sacat=0&_from=R40&_sop=15&rt=nc&_udlo=20000 | H37: https://paypayfleamarket.yahoo.co.jp/item/z246161498 | I37: https://jp.mercari.com/item/m37335929590 | J37: https://jp.mercari.com/item/m58211103185 | N37: https://jp.mercari.com/search?keyword=%E3%83%9E%E3%83%81%E3%82%AB%E3%83%8D%E3%83%95%E3%82%AF%E3%82%AD%E3%82%BF%E3%83%AB%20%E3%81%AC%E3%81%84%E3%81%90%E3%82%8B%E3%81%BF%20%E3%82%A2%E3%82%A4%E3%83%89%E3%83%AB%E3%83%9B%E3%83%BC%E3%82%B9&price_min=10000&sort=price&order=asc&status=on_sale | O37: https://fril.jp/s?query=%E3%83%9E%E3%83%81%E3%82%AB%E3%83%8D%E3%83%95%E3%82%AF%E3%82%AD%E3%82%BF%E3%83%AB%20%E3%81%AC%E3%81%84%E3%81%90%E3%82%8B%E3%81%BF%20%E3%82%A2%E3%82%A4%E3%83%89%E3%83%AB%E3%83%9B%E3%83%BC%E3%82%B9&min=10000&transaction=selling | P37: https://search.rakuten.co.jp/search/mall/%E3%83%9E%E3%83%81%E3%82%AB%E3%83%8D%E3%83%95%E3%82%AF%E3%82%AD%E3%82%BF%E3%83%AB%20%E3%81%AC%E3%81%84%E3%81%90%E3%82%8B%E3%81%BF%20%E3%82%A2%E3%82%A4%E3%83%89%E3%83%AB%E3%83%9B%E3%83%BC%E3%82%B9/?min=10000 | Q37: https://auctions.yahoo.co.jp/search/search?p=%E3%83%9E%E3%83%81%E3%82%AB%E3%83%8D%E3%83%95%E3%82%AF%E3%82%AD%E3%82%BF%E3%83%AB%20%E3%81%AC%E3%81%84%E3%81%90%E3%82%8B%E3%81%BF%20%E3%82%A2%E3%82%A4%E3%83%89%E3%83%AB%E3%83%9B%E3%83%BC%E3%82%B9&aucminprice=10000 | R37: https://shopping.yahoo.co.jp/search/%E3%83%9E%E3%83%81%E3%82%AB%E3%83%8D%E3%83%95%E3%82%AF%E3%82%AD%E3%82%BF%E3%83%AB%20%E3%81%AC%E3%81%84%E3%81%90%E3%82%8B%E3%81%BF%20%E3%82%A2%E3%82%A4%E3%83%89%E3%83%AB%E3%83%9B%E3%83%BC%E3%82%B9/0/?pf=10000
A38: 1694 | B38: 信楽焼 信じて楽しい 阪神タイガース 優勝お願い狸 必勝応援チアガール狸 ペア | C38: 1 | D38: 100000 | E38: 1130 | F38: Fedex 5.0kg | G38: https://www.ebay.com/sch/i.html?_nkw=Shigaraki%20Tanuki%20Hanshin%20Tigers&_sacat=0&_from=R40&_sop=15&rt=nc&_udlo=20000 | H38: https://jp.mercari.com/item/m60652632651 | N38: https://jp.mercari.com/search?keyword=%E4%BF%A1%E6%A5%BD%E7%84%BC%20%E9%98%AA%E7%A5%9E%E3%82%BF%E3%82%A4%E3%82%AC%E3%83%BC%E3%82%B9%20%E7%8B%B8&price_min=10000&sort=price&order=asc&status=on_sale | O38: https://fril.jp/s?query=%E4%BF%A1%E6%A5%BD%E7%84%BC%20%E9%98%AA%E7%A5%9E%E3%82%BF%E3%82%A4%E3%82%AC%E3%83%BC%E3%82%B9%20%E7%8B%B8&min=10000&transaction=selling | P38: https://search.rakuten.co.jp/search/mall/%E4%BF%A1%E6%A5%BD%E7%84%BC%20%E9%98%AA%E7%A5%9E%E3%82%BF%E3%82%A4%E3%82%AC%E3%83%BC%E3%82%B9%20%E7%8B%B8/?min=10000 | Q38: https://auctions.yahoo.co.jp/search/search?p=%E4%BF%A1%E6%A5%BD%E7%84%BC%20%E9%98%AA%E7%A5%9E%E3%82%BF%E3%82%A4%E3%82%AC%E3%83%BC%E3%82%B9%20%E7%8B%B8&aucminprice=10000 | R38: https://shopping.yahoo.co.jp/search/%E4%BF%A1%E6%A5%BD%E7%84%BC%20%E9%98%AA%E7%A5%9E%E3%82%BF%E3%82%A4%E3%82%AC%E3%83%BC%E3%82%B9%20%E7%8B%B8/0/?pf=10000
A39: 1695 | B39: 【未開封品】デイヴィッド・リンチ Blu-ray BOX | C39: 1 | D39: 46500 | E39: 550 | F39: Fedex 2.0kg | G39: https://www.ebay.com/sch/i.html?_nkw=David%20Lynch%20Blu-ray%20Box&_sacat=0&_from=R40&_sop=15&rt=nc&_udlo=20000 | H39: https://jp.mercari.com/item/m93402927208 | N39: https://jp.mercari.com/search?keyword=%E3%83%87%E3%82%A4%E3%83%B4%E3%82%A3%E3%83%83%E3%83%89%E3%83%AA%E3%83%B3%E3%83%81%20Blu-ray%20BOX&price_min=10000&sort=price&order=asc&status=on_sale | O39: https://fril.jp/s?query=%E3%83%87%E3%82%A4%E3%83%B4%E3%82%A3%E3%83%83%E3%83%89%E3%83%AA%E3%83%B3%E3%83%81%20Blu-ray%20BOX&min=10000&transaction=selling | P39: https://search.rakuten.co.jp/search/mall/%E3%83%87%E3%82%A4%E3%83%B4%E3%82%A3%E3%83%83%E3%83%89%E3%83%AA%E3%83%B3%E3%83%81%20Blu-ray%20BOX/?min=10000 | Q39: https://auctions.yahoo.co.jp/search/search?p=%E3%83%87%E3%82%A4%E3%83%B4%E3%82%A3%E3%83%83%E3%83%89%E3%83%AA%E3%83%B3%E3%83%81%20Blu-ray%20BOX&aucminprice=10000 | R39: https://shopping.yahoo.co.jp/search/%E3%83%87%E3%82%A4%E3%83%B4%E3%82%A3%E3%83%83%E3%83%89%E3%83%AA%E3%83%B3%E3%83%81%20Blu-ray%20BOX/0/?pf=10000
A40: 1696 | B40: ジブリパーク限定 ポーリッシュポタリー ハウル... | C40: 1 | D40: 49800 | E40: 690 | F40: Fedex 1.0kg | G40: https://www.ebay.com/sch/i.html?_nkw=Ghibli%20Park%20Polish%20Pottery%20Howl&_sacat=0&_from=R40&_sop=15&rt=nc&_udlo=20000 | H40: https://jp.mercari.com/item/m43318510705 | N40: https://jp.mercari.com/search?keyword=%E3%82%B8%E3%83%96%E3%83%AA%E3%83%91%E3%83%BC%E3%82%AF%20%E3%83%9D%E3%83%BC%E3%83%AA%E3%83%83%E3%82%B7%E3%83%A5%E3%83%9D%E3%82%BF%E3%83%AA%E3%83%BC%20%E3%83%8F%E3%82%A6%E3%83%AB&price_min=10000&sort=price&order=asc&status=on_sale | O40: https://fril.jp/s?query=%E3%82%B8%E3%83%96%E3%83%AA%E3%83%91%E3%83%BC%E3%82%AF%20%E3%83%9D%E3%83%BC%E3%83%AA%E3%83%83%E3%82%B7%E3%83%A5%E3%83%9D%E3%82%BF%E3%83%AA%E3%83%BC%20%E3%83%8F%E3%82%A6%E3%83%AB&min=10000&transaction=selling | P40: https://search.rakuten.co.jp/search/mall/%E3%82%B8%E3%83%96%E3%83%AA%E3%83%91%E3%83%BC%E3%82%AF%20%E3%83%9D%E3%83%BC%E3%83%AA%E3%83%83%E3%82%B7%E3%83%A5%E3%83%9D%E3%82%BF%E3%83%AA%E3%83%BC%20%E3%83%8F%E3%82%A6%E3%83%AB/?min=10000 | Q40: https://auctions.yahoo.co.jp/search/search?p=%E3%82%B8%E3%83%96%E3%83%AA%E3%83%91%E3%83%BC%E3%82%AF%20%E3%83%9D%E3%83%BC%E3%83%AA%E3%83%83%E3%82%B7%E3%83%A5%E3%83%9D%E3%82%BF%E3%83%AA%E3%83%BC%20%E3%83%8F%E3%82%A6%E3%83%AB&aucminprice=10000 | R40: https://shopping.yahoo.co.jp/search/%E3%82%B8%E3%83%96%E3%83%AA%E3%83%91%E3%83%BC%E3%82%AF%20%E3%83%9D%E3%83%BC%E3%83%AA%E3%83%83%E3%82%B7%E3%83%A5%E3%83%9D%E3%82%BF%E3%83%AA%E3%83%BC%20%E3%83%8F%E3%82%A6%E3%83%AB/0/?pf=10000
A41: 1697 | B41: ジブリ・アカペラスタイル CD 宮崎駿 スタジオジブリ | C41: 1 | D41: 10850 | E41: 229 | F41: Fedex 1.0kg | G41: https://www.ebay.com/sch/i.html?_nkw=Ghibli%20Acapella%20CD&_sacat=0&_from=R40&_sop=15&rt=nc&_udlo=20000 | H41: https://paypayfleamarket.yahoo.co.jp/item/z300604720 | N41: https://jp.mercari.com/search?keyword=%E3%82%B8%E3%83%96%E3%83%AA%20%E3%82%A2%E3%82%AB%E3%83%9A%E3%83%A9%20CD&price_min=4000&sort=price&order=asc&status=on_sale | O41: https://fril.jp/s?query=%E3%82%B8%E3%83%96%E3%83%AA%20%E3%82%A2%E3%82%AB%E3%83%9A%E3%83%A9%20CD&min=10000&transaction=selling | P41: https://search.rakuten.co.jp/search/mall/%E3%82%B8%E3%83%96%E3%83%AA%20%E3%82%A2%E3%82%AB%E3%83%9A%E3%83%A9%20CD/?min=10000 | Q41: https://auctions.yahoo.co.jp/search/search?p=%E3%82%B8%E3%83%96%E3%83%AA%20%E3%82%A2%E3%82%AB%E3%83%9A%E3%83%A9%20CD&aucminprice=10000 | R41: https://shopping.yahoo.co.jp/search/%E3%82%B8%E3%83%96%E3%83%AA%20%E3%82%A2%E3%82%AB%E3%83%9A%E3%83%A9%20CD/0/?pf=10000
A42: 1698 | B42: SHIMANO FURUNO 探見丸 CV 本体 魚群探知機 | C42: 1 | D42: 10000 | E42: 399 | F42: Fedex 3.0kg | G42: https://www.ebay.com/sch/i.html?_nkw=Shimano%20Furuno%20Tankenmaru%20CV&_sacat=0&_from=R40&_sop=15&rt=nc&_udlo=20000 | H42: https://jp.mercari.com/item/m61432143703 | I42: https://jp.mercari.com/item/m84803463019 | N42: https://jp.mercari.com/search?keyword=%E3%82%B7%E3%83%9E%E3%83%8E%20%E3%83%95%E3%83%AB%E3%83%8E%20%E6%8E%A2%E8%A6%8B%E4%B8%B8%20CV%20%E9%AD%9A%E6%8E%A2&price_min=10000&sort=price&order=asc&status=on_sale | O42: https://fril.jp/s?query=%E3%82%B7%E3%83%9E%E3%83%8E%20%E3%83%95%E3%83%AB%E3%83%8E%20%E6%8E%A2%E8%A6%8B%E4%B8%B8%20CV%20%E9%AD%9A%E6%8E%A2&min=10000&transaction=selling | P42: https://search.rakuten.co.jp/search/mall/%E3%82%B7%E3%83%9E%E3%83%8E%20%E3%83%95%E3%83%AB%E3%83%8E%20%E6%8E%A2%E8%A6%8B%E4%B8%B8%20CV%20%E9%AD%9A%E6%8E%A2/?min=10000 | Q42: https://auctions.yahoo.co.jp/search/search?p=%E3%82%B7%E3%83%9E%E3%83%8E%20%E3%83%95%E3%83%AB%E3%83%8E%20%E6%8E%A2%E8%A6%8B%E4%B8%B8%20CV%20%E9%AD%9A%E6%8E%A2&aucminprice=10000 | R42: https://shopping.yahoo.co.jp/search/%E3%82%B7%E3%83%9E%E3%83%8E%20%E3%83%95%E3%83%AB%E3%83%8E%20%E6%8E%A2%E8%A6%8B%E4%B8%B8%20CV%20%E9%AD%9A%E6%8E%A2/0/?pf=10000
A43: 1699 | B43: 新品未開封 MGS3 SNAKE EATER 2005冬 WF スネーク rah | C43: 1 | D43: 39480 | E43: 520 | F43: Fedex 3.0kg | G43: https://www.ebay.com/sch/i.html?_nkw=RAH%20MGS3%20Snake%20Eater%20Figure&_sacat=0&_from=R40&_sop=15&rt=nc&_udlo=20000 | H43: https://jp.mercari.com/item/m43750621893 | N43: https://jp.mercari.com/search?keyword=RAH%20%E3%83%A1%E3%82%BF%E3%83%AB%E3%82%AE%E3%82%A2%E3%82%BD%E3%83%AA%E3%83%83%E3%83%893%20%E3%82%B9%E3%83%8D%E3%83%BC%E3%82%AF%E3%82%A4%E3%83%BC%E3%82%BF%E3%83%BC&price_min=10000&sort=price&order=asc&status=on_sale | O43: https://fril.jp/s?query=RAH%20%E3%83%A1%E3%82%BF%E3%83%AB%E3%82%AE%E3%82%A2%E3%82%BD%E3%83%AA%E3%83%83%E3%83%893%20%E3%82%B9%E3%83%8D%E3%83%BC%E3%82%AF%E3%82%A4%E3%83%BC%E3%82%BF%E3%83%BC&min=10000&transaction=selling | P43: https://search.rakuten.co.jp/search/mall/RAH%20%E3%83%A1%E3%82%BF%E3%83%AB%E3%82%AE%E3%82%A2%E3%82%BD%E3%83%AA%E3%83%83%E3%83%893%20%E3%82%B9%E3%83%8D%E3%83%BC%E3%82%AF%E3%82%A4%E3%83%BC%E3%82%BF%E3%83%BC/?min=10000 | Q43: https://auctions.yahoo.co.jp/search/search?p=RAH%20%E3%83%A1%E3%82%BF%E3%83%AB%E3%82%AE%E3%82%A2%E3%82%BD%E3%83%AA%E3%83%83%E3%83%893%20%E3%82%B9%E3%83%8D%E3%83%BC%E3%82%AF%E3%82%A4%E3%83%BC%E3%82%BF%E3%83%BC&aucminprice=10000 | R43: https://shopping.yahoo.co.jp/search/RAH%20%E3%83%A1%E3%82%BF%E3%83%AB%E3%82%AE%E3%82%A2%E3%82%BD%E3%83%AA%E3%83%83%E3%83%893%20%E3%82%B9%E3%83%8D%E3%83%BC%E3%82%AF%E3%82%A4%E3%83%BC%E3%82%BF%E3%83%BC/0/?pf=10000
A44: 1700 | B44: BRAHMS COMPLETE EDITION 46CDs クラシック CD ボックスセット | C44: 1 | D44: 18000 | E44: 298 | F44: Fedex 1.5kg | G44: https://www.ebay.com/sch/i.html?_nkw=Brahms%20Complete%20Edition%2046%20CD&_sacat=0&_from=R40&_sop=15&rt=nc&_udlo=20000 | H44: https://jp.mercari.com/item/m48839020184 | I44: https://paypayfleamarket.yahoo.co.jp/item/z599036334 | N44: https://jp.mercari.com/search?keyword=%E3%83%96%E3%83%A9%E3%83%BC%E3%83%A0%E3%82%B9%20%E5%85%A8%E9%9B%86%2046CD&price_min=10000&sort=price&order=asc&status=on_sale | O44: https://fril.jp/s?query=%E3%83%96%E3%83%A9%E3%83%BC%E3%83%A0%E3%82%B9%20%E5%85%A8%E9%9B%86%2046CD&min=10000&transaction=selling | P44: https://search.rakuten.co.jp/search/mall/%E3%83%96%E3%83%A9%E3%83%BC%E3%83%A0%E3%82%B9%20%E5%85%A8%E9%9B%86%2046CD/?min=10000 | Q44: https://auctions.yahoo.co.jp/search/search?p=%E3%83%96%E3%83%A9%E3%83%BC%E3%83%A0%E3%82%B9%20%E5%85%A8%E9%9B%86%2046CD&aucminprice=10000 | R44: https://shopping.yahoo.co.jp/search/%E3%83%96%E3%83%A9%E3%83%BC%E3%83%A0%E3%82%B9%20%E5%85%A8%E9%9B%86%2046CD/0/?pf=10000
A45: 1701 | B45: SIRENといっしょ（シビトロの海帰りver.）Tシャツ BLACK Mサイズ | C45: 1 | D45: 12000 | E45: 270 | F45: Fedex 2.0kg | G45: https://www.ebay.com/sch/i.html?_nkw=SIREN%20Shibitoro%20T-Shirt&_sacat=0&_from=R40&_sop=15&rt=nc&_udlo=20000 | H45: https://jp.mercari.com/item/m73428428037 | N45: https://jp.mercari.com/search?keyword=SIREN%20%E3%82%B7%E3%83%93%E3%83%88%E3%83%AD%20T%E3%82%B7%E3%83%A3%E3%83%84&price_min=10000&sort=price&order=asc&status=on_sale | O45: https://fril.jp/s?query=SIREN%20%E3%82%B7%E3%83%93%E3%83%88%E3%83%AD%20T%E3%82%B7%E3%83%A3%E3%83%84&min=10000&transaction=selling | P45: https://search.rakuten.co.jp/search/mall/SIREN%20%E3%82%B7%E3%83%93%E3%83%88%E3%83%AD%20T%E3%82%B7%E3%83%A3%E3%83%84/?min=10000 | Q45: https://auctions.yahoo.co.jp/search/search?p=SIREN%20%E3%82%B7%E3%83%93%E3%83%88%E3%83%AD%20T%E3%82%B7%E3%83%A3%E3%83%84&aucminprice=10000 | R45: https://shopping.yahoo.co.jp/search/SIREN%20%E3%82%B7%E3%83%93%E3%83%88%E3%83%AD%20T%E3%82%B7%E3%83%A3%E3%83%84/0/?pf=10000
A46: 1702 | B46: ヴェルテクス すーぱーぽちゃ子 カウガール WF限定版 | C46: 1 | D46: 31600 | E46: 490 | F46: Fedex 5.0kg | G46: https://www.ebay.com/sch/i.html?_nkw=Vertex%20Super%20Pochaco%20Cowgirl&_sacat=0&_from=R40&_sop=15&rt=nc&_udlo=20000 | H46: https://jp.mercari.com/item/m25397753764 | N46: https://jp.mercari.com/search?keyword=%E3%83%B4%E3%82%A7%E3%83%AB%E3%83%86%E3%82%AF%E3%82%B9%20%E3%81%99%E3%83%BC%E3%81%B1%E3%83%BC%E3%81%BD%E3%81%A1%E3%82%83%E5%AD%90%20%E3%82%AB%E3%82%A6%E3%82%AC%E3%83%BC%E3%83%AB&price_min=10000&sort=price&order=asc&status=on_sale | O46: https://fril.jp/s?query=%E3%83%B4%E3%82%A7%E3%83%AB%E3%83%86%E3%82%AF%E3%82%B9%20%E3%81%99%E3%83%BC%E3%81%B1%E3%83%BC%E3%81%BD%E3%81%A1%E3%82%83%E5%AD%90%20%E3%82%AB%E3%82%A6%E3%82%AC%E3%83%BC%E3%83%AB&min=10000&transaction=selling | P46: https://search.rakuten.co.jp/search/mall/%E3%83%B4%E3%82%A7%E3%83%AB%E3%83%86%E3%82%AF%E3%82%B9%20%E3%81%99%E3%83%BC%E3%81%B1%E3%83%BC%E3%81%BD%E3%81%A1%E3%82%83%E5%AD%90%20%E3%82%AB%E3%82%A6%E3%82%AC%E3%83%BC%E3%83%AB/?min=10000 | Q46: https://auctions.yahoo.co.jp/search/search?p=%E3%83%B4%E3%82%A7%E3%83%AB%E3%83%86%E3%82%AF%E3%82%B9%20%E3%81%99%E3%83%BC%E3%81%B1%E3%83%BC%E3%81%BD%E3%81%A1%E3%82%83%E5%AD%90%20%E3%82%AB%E3%82%A6%E3%82%AC%E3%83%BC%E3%83%AB&aucminprice=10000 | R46: https://shopping.yahoo.co.jp/search/%E3%83%B4%E3%82%A7%E3%83%AB%E3%83%86%E3%82%AF%E3%82%B9%20%E3%81%99%E3%83%BC%E3%81%B1%E3%83%BC%E3%81%BD%E3%81%A1%E3%82%83%E5%AD%90%20%E3%82%AB%E3%82%A6%E3%82%AC%E3%83%BC%E3%83%AB/0/?pf=10000
A47: 1703 | B47: (再販) 超像可動 34.グイード・ミスタ&セックス・ピストルズ (荒木飛呂彦指定カラー) ジョジョの奇妙な冒険 第五部 黄金の風 フィギュア メディコス・エンタテインメント | C47: 1 | D47: 10828 | E47: 228 | F47: Fedex 1.0kg | G47: https://www.ebay.com/sch/i.html?_nkw=Chozokado%20Mista%20Sex%20Pistols%20figure&_sacat=0&_from=R40&_sop=15&rt=nc&_udlo=20000 | H47: https://jp.mercari.com/shops/product/2JUYTDGc3URDspDQNQUZPn | I47: https://auctions.yahoo.co.jp/jp/auction/t1238637685 | N47: https://jp.mercari.com/search?keyword=%E8%B6%85%E5%83%8F%E5%8F%AF%E5%8B%95%20%E3%83%9F%E3%82%B9%E3%82%BF%20%E3%82%BB%E3%83%83%E3%82%AF%E3%82%B9%E3%83%94%E3%82%B9%E3%83%88%E3%83%AB%E3%82%BA&price_min=10000&sort=price&order=asc&status=on_sale | O47: https://fril.jp/s?query=%E8%B6%85%E5%83%8F%E5%8F%AF%E5%8B%95%20%E3%83%9F%E3%82%B9%E3%82%BF%20%E3%82%BB%E3%83%83%E3%82%AF%E3%82%B9%E3%83%94%E3%82%B9%E3%83%88%E3%83%AB%E3%82%BA&min=10000&transaction=selling | P47: https://search.rakuten.co.jp/search/mall/%E8%B6%85%E5%83%8F%E5%8F%AF%E5%8B%95%20%E3%83%9F%E3%82%B9%E3%82%BF%20%E3%82%BB%E3%83%83%E3%82%AF%E3%82%B9%E3%83%94%E3%82%B9%E3%83%88%E3%83%AB%E3%82%BA/?min=10000 | Q47: https://auctions.yahoo.co.jp/search/search?p=%E8%B6%85%E5%83%8F%E5%8F%AF%E5%8B%95%20%E3%83%9F%E3%82%B9%E3%82%BF%20%E3%82%BB%E3%83%83%E3%82%AF%E3%82%B9%E3%83%94%E3%82%B9%E3%83%88%E3%83%AB%E3%82%BA&aucminprice=10000 | R47: https://shopping.yahoo.co.jp/search/%E8%B6%85%E5%83%8F%E5%8F%AF%E5%8B%95%20%E3%83%9F%E3%82%B9%E3%82%BF%20%E3%82%BB%E3%83%83%E3%82%AF%E3%82%B9%E3%83%94%E3%82%B9%E3%83%88%E3%83%AB%E3%82%BA/0/?pf=10000
A48: 1704 | B48: ALPHA×ACE COMBAT エースコンバット7 コラボ CW... | C48: 1 | D48: 76000 | E48: 920 | F48: Fedex 7.5kg | G48: https://www.ebay.com/sch/i.html?_nkw=Alpha%20Ace%20Combat%207%20jacket&_sacat=0&_from=R40&_sop=15&rt=nc&_udlo=20000 | H48: https://page.auctions.yahoo.co.jp/jp/auction/b1236905956 | N48: https://jp.mercari.com/search?keyword=ALPHA%20%E3%82%A8%E3%83%BC%E3%82%B9%E3%82%B3%E3%83%B3%E3%83%90%E3%83%83%E3%83%88%20%E3%82%B3%E3%83%A9%E3%83%9C%20%E3%82%B8%E3%83%A3%E3%82%B1%E3%83%83%E3%83%88&price_min=10000&sort=price&order=asc&status=on_sale | O48: https://fril.jp/s?query=ALPHA%20%E3%82%A8%E3%83%BC%E3%82%B9%E3%82%B3%E3%83%B3%E3%83%90%E3%83%83%E3%83%88%20%E3%82%B3%E3%83%A9%E3%83%9C%20%E3%82%B8%E3%83%A3%E3%82%B1%E3%83%83%E3%83%88&min=10000&transaction=selling | P48: https://search.rakuten.co.jp/search/mall/ALPHA%20%E3%82%A8%E3%83%BC%E3%82%B9%E3%82%B3%E3%83%B3%E3%83%90%E3%83%83%E3%83%88%20%E3%82%B3%E3%83%A9%E3%83%9C%20%E3%82%B8%E3%83%A3%E3%82%B1%E3%83%83%E3%83%88/?min=10000 | Q48: https://auctions.yahoo.co.jp/search/search?p=ALPHA%20%E3%82%A8%E3%83%BC%E3%82%B9%E3%82%B3%E3%83%B3%E3%83%90%E3%83%83%E3%83%88%20%E3%82%B3%E3%83%A9%E3%83%9C%20%E3%82%B8%E3%83%A3%E3%82%B1%E3%83%83%E3%83%88&aucminprice=10000 | R48: https://shopping.yahoo.co.jp/search/ALPHA%20%E3%82%A8%E3%83%BC%E3%82%B9%E3%82%B3%E3%83%B3%E3%83%90%E3%83%83%E3%83%88%20%E3%82%B3%E3%83%A9%E3%83%9C%20%E3%82%B8%E3%83%A3%E3%82%B1%E3%83%83%E3%83%88/0/?pf=10000
A49: 1705 | B49: ハズビンホテル トレーディングカード THE ROACH シークレット | C49: 1 | D49: 49999 | E49: 560 | F49: Fedex 0.5kg | G49: https://www.ebay.com/sch/i.html?_nkw=Hazbin%20Hotel%20The%20Roach%20secret&_sacat=0&_from=R40&_sop=15&rt=nc&_udlo=20000 | H49: https://jp.mercari.com/item/m81328910059 | N49: https://jp.mercari.com/search?keyword=%E3%83%8F%E3%82%BA%E3%83%93%E3%83%B3%E3%83%9B%E3%83%86%E3%83%AB%20THE%20ROACH%20%E3%82%B7%E3%83%BC%E3%82%AF%E3%83%AC%E3%83%83%E3%83%88&price_min=10000&sort=price&order=asc&status=on_sale | O49: https://fril.jp/s?query=%E3%83%8F%E3%82%BA%E3%83%93%E3%83%B3%E3%83%9B%E3%83%86%E3%83%AB%20THE%20ROACH%20%E3%82%B7%E3%83%BC%E3%82%AF%E3%83%AC%E3%83%83%E3%83%88&min=10000&transaction=selling | P49: https://search.rakuten.co.jp/search/mall/%E3%83%8F%E3%82%BA%E3%83%93%E3%83%B3%E3%83%9B%E3%83%86%E3%83%AB%20THE%20ROACH%20%E3%82%B7%E3%83%BC%E3%82%AF%E3%83%AC%E3%83%83%E3%83%88/?min=10000 | Q49: https://auctions.yahoo.co.jp/search/search?p=%E3%83%8F%E3%82%BA%E3%83%93%E3%83%B3%E3%83%9B%E3%83%86%E3%83%AB%20THE%20ROACH%20%E3%82%B7%E3%83%BC%E3%82%AF%E3%83%AC%E3%83%83%E3%83%88&aucminprice=10000 | R49: https://shopping.yahoo.co.jp/search/%E3%83%8F%E3%82%BA%E3%83%93%E3%83%B3%E3%83%9B%E3%83%86%E3%83%AB%20THE%20ROACH%20%E3%82%B7%E3%83%BC%E3%82%AF%E3%83%AC%E3%83%83%E3%83%88/0/?pf=10000
A50: 1706 | B50: ハズビンホテル アクリルスタンド チャーリー HAZBIN HOTEL Charlie STANDEE | C50: 1 | D50: 88888 | E50: 980 | F50: Fedex 0.5kg | G50: https://www.ebay.com/sch/i.html?_nkw=Hazbin%20Hotel%20Charlie%20acrylic%20stand&_sacat=0&_from=R40&_sop=15&rt=nc&_udlo=20000 | H50: https://jp.mercari.com/item/m69186539344 | N50: https://jp.mercari.com/search?keyword=%E3%83%8F%E3%82%BA%E3%83%93%E3%83%B3%E3%83%9B%E3%83%86%E3%83%AB%20%E3%83%81%E3%83%A3%E3%83%BC%E3%83%AA%E3%83%BC%20%E3%82%A2%E3%82%AF%E3%83%AA%E3%83%AB%E3%82%B9%E3%82%BF%E3%83%B3%E3%83%89&price_min=10000&sort=price&order=asc&status=on_sale | O50: https://fril.jp/s?query=%E3%83%8F%E3%82%BA%E3%83%93%E3%83%B3%E3%83%9B%E3%83%86%E3%83%AB%20%E3%83%81%E3%83%A3%E3%83%BC%E3%83%AA%E3%83%BC%20%E3%82%A2%E3%82%AF%E3%83%AA%E3%83%AB%E3%82%B9%E3%82%BF%E3%83%B3%E3%83%89&min=10000&transaction=selling | P50: https://search.rakuten.co.jp/search/mall/%E3%83%8F%E3%82%BA%E3%83%93%E3%83%B3%E3%83%9B%E3%83%86%E3%83%AB%20%E3%83%81%E3%83%A3%E3%83%BC%E3%83%AA%E3%83%BC%20%E3%82%A2%E3%82%AF%E3%83%AA%E3%83%AB%E3%82%B9%E3%82%BF%E3%83%B3%E3%83%89/?min=10000 | Q50: https://auctions.yahoo.co.jp/search/search?p=%E3%83%8F%E3%82%BA%E3%83%93%E3%83%B3%E3%83%9B%E3%83%86%E3%83%AB%20%E3%83%81%E3%83%A3%E3%83%BC%E3%83%AA%E3%83%BC%20%E3%82%A2%E3%82%AF%E3%83%AA%E3%83%AB%E3%82%B9%E3%82%BF%E3%83%B3%E3%83%89&aucminprice=10000 | R50: https://shopping.yahoo.co.jp/search/%E3%83%8F%E3%82%BA%E3%83%93%E3%83%B3%E3%83%9B%E3%83%86%E3%83%AB%20%E3%83%81%E3%83%A3%E3%83%BC%E3%83%AA%E3%83%BC%20%E3%82%A2%E3%82%AF%E3%83%AA%E3%83%AB%E3%82%B9%E3%82%BF%E3%83%B3%E3%83%89/0/?pf=10000
A51: 1707 | B51: 木城ゆきと画集 ARS MAGNA 銃夢 水中騎士 蜃気楼帝国 | C51: 1 | D51: 18000 | E51: 227 | F51: Fedex 1.5kg | G51: https://www.ebay.com/sch/i.html?_nkw=Yukito%20Kishiro%20ARS%20MAGNA%20art%20book&_sacat=0&_from=R40&_sop=15&rt=nc&_udlo=20000 | H51: https://jp.mercari.com/item/m35148971723 | N51: https://jp.mercari.com/search?keyword=%E6%9C%A8%E5%9F%8E%E3%82%86%E3%81%8D%E3%81%A8%E7%94%BB%E9%9B%86%20ARS%20MAGNA%20%E9%8A%83%E5%A4%A2&price_min=10000&sort=price&order=asc&status=on_sale | O51: https://fril.jp/s?query=%E6%9C%A8%E5%9F%8E%E3%82%86%E3%81%8D%E3%81%A8%E7%94%BB%E9%9B%86%20ARS%20MAGNA%20%E9%8A%83%E5%A4%A2&min=10000&transaction=selling | P51: https://search.rakuten.co.jp/search/mall/%E6%9C%A8%E5%9F%8E%E3%82%86%E3%81%8D%E3%81%A8%E7%94%BB%E9%9B%86%20ARS%20MAGNA%20%E9%8A%83%E5%A4%A2/?min=10000 | Q51: https://auctions.yahoo.co.jp/search/search?p=%E6%9C%A8%E5%9F%8E%E3%82%86%E3%81%8D%E3%81%A8%E7%94%BB%E9%9B%86%20ARS%20MAGNA%20%E9%8A%83%E5%A4%A2&aucminprice=10000 | R51: https://shopping.yahoo.co.jp/search/%E6%9C%A8%E5%9F%8E%E3%82%86%E3%81%8D%E3%81%A8%E7%94%BB%E9%9B%86%20ARS%20MAGNA%20%E9%8A%83%E5%A4%A2/0/?pf=10000
A52: 1708 | B52: 新品・未使用 Blythe ネオブライス ウィンタリッ... | C52: 1 | D52: 32000 | E52: 420 | F52: Fedex 1.5kg | G52: https://www.ebay.com/sch/i.html?_nkw=Neo%20Blythe%20Winterish%20Allure&_sacat=0&_from=R40&_sop=15&rt=nc&_udlo=20000 | H52: https://jp.mercari.com/item/m31653145904 | I52: https://jp.mercari.com/item/m47449145920 | N52: https://jp.mercari.com/search?keyword=%E3%83%8D%E3%82%AA%E3%83%96%E3%83%A9%E3%82%A4%E3%82%B9%20%E3%82%A6%E3%82%A3%E3%83%B3%E3%82%BF%E3%83%AA%E3%83%83%E3%82%B7%E3%83%A5%E3%82%A2%E3%83%AB%E3%83%BC%E3%82%A2&price_min=10000&sort=price&order=asc&status=on_sale | O52: https://fril.jp/s?query=%E3%83%8D%E3%82%AA%E3%83%96%E3%83%A9%E3%82%A4%E3%82%B9%20%E3%82%A6%E3%82%A3%E3%83%B3%E3%82%BF%E3%83%AA%E3%83%83%E3%82%B7%E3%83%A5%E3%82%A2%E3%83%AB%E3%83%BC%E3%82%A2&min=10000&transaction=selling | P52: https://search.rakuten.co.jp/search/mall/%E3%83%8D%E3%82%AA%E3%83%96%E3%83%A9%E3%82%A4%E3%82%B9%20%E3%82%A6%E3%82%A3%E3%83%B3%E3%82%BF%E3%83%AA%E3%83%83%E3%82%B7%E3%83%A5%E3%82%A2%E3%83%AB%E3%83%BC%E3%82%A2/?min=10000 | Q52: https://auctions.yahoo.co.jp/search/search?p=%E3%83%8D%E3%82%AA%E3%83%96%E3%83%A9%E3%82%A4%E3%82%B9%20%E3%82%A6%E3%82%A3%E3%83%B3%E3%82%BF%E3%83%AA%E3%83%83%E3%82%B7%E3%83%A5%E3%82%A2%E3%83%AB%E3%83%BC%E3%82%A2&aucminprice=10000 | R52: https://shopping.yahoo.co.jp/search/%E3%83%8D%E3%82%AA%E3%83%96%E3%83%A9%E3%82%A4%E3%82%B9%20%E3%82%A6%E3%82%A3%E3%83%B3%E3%82%BF%E3%83%AA%E3%83%83%E3%82%B7%E3%83%A5%E3%82%A2%E3%83%AB%E3%83%BC%E3%82%A2/0/?pf=10000
A53: 1709 | B53: ガイキング超合金アルカディア号マジンガーZ | C53: 1 | D53: 28000 | E53: 440 | F53: Fedex 4.5kg | G53: https://www.ebay.com/sch/i.html?_nkw=Chogokin%20Arcadia%20lot&_sacat=0&_from=R40&_sop=15&rt=nc&_udlo=20000 | H53: https://auctions.yahoo.co.jp/jp/auction/o1239092692 | I53: https://jp.mercari.com/item/m95276875888 | N53: https://jp.mercari.com/search?keyword=%E8%B6%85%E5%90%88%E9%87%91%20%E3%82%A2%E3%83%AB%E3%82%AB%E3%83%87%E3%82%A3%E3%82%A2%20%E3%82%AC%E3%82%A4%E3%82%AD%E3%83%B3%E3%82%B0&price_min=10000&sort=price&order=asc&status=on_sale | O53: https://fril.jp/s?query=%E8%B6%85%E5%90%88%E9%87%91%20%E3%82%A2%E3%83%AB%E3%82%AB%E3%83%87%E3%82%A3%E3%82%A2%20%E3%82%AC%E3%82%A4%E3%82%AD%E3%83%B3%E3%82%B0&min=10000&transaction=selling | P53: https://search.rakuten.co.jp/search/mall/%E8%B6%85%E5%90%88%E9%87%91%20%E3%82%A2%E3%83%AB%E3%82%AB%E3%83%87%E3%82%A3%E3%82%A2%20%E3%82%AC%E3%82%A4%E3%82%AD%E3%83%B3%E3%82%B0/?min=10000 | Q53: https://auctions.yahoo.co.jp/search/search?p=%E8%B6%85%E5%90%88%E9%87%91%20%E3%82%A2%E3%83%AB%E3%82%AB%E3%83%87%E3%82%A3%E3%82%A2%20%E3%82%AC%E3%82%A4%E3%82%AD%E3%83%B3%E3%82%B0&aucminprice=10000 | R53: https://shopping.yahoo.co.jp/search/%E8%B6%85%E5%90%88%E9%87%91%20%E3%82%A2%E3%83%AB%E3%82%AB%E3%83%87%E3%82%A3%E3%82%A2%20%E3%82%AC%E3%82%A4%E3%82%AD%E3%83%B3%E3%82%B0/0/?pf=10000
A54: 1710 | B54: キッス ＫＩＳS レトロ12インチ フィギュアセッ... | C54: 1 | D54: 53900 | E54: 640 | F54: Fedex 1.0kg | G54: https://www.ebay.com/sch/i.html?_nkw=Kiss%2012%20inch%20figure%20set&_sacat=0&_from=R40&_sop=15&rt=nc&_udlo=20000 | H54: https://auctions.yahoo.co.jp/jp/auction/c1058697225 | I54: https://auctions.yahoo.co.jp/jp/auction/c1058697225 | N54: https://jp.mercari.com/search?keyword=KISS%2012%E3%82%A4%E3%83%B3%E3%83%81%20%E3%83%95%E3%82%A3%E3%82%AE%E3%83%A5%E3%82%A2&price_min=10000&sort=price&order=asc&status=on_sale | O54: https://fril.jp/s?query=KISS%2012%E3%82%A4%E3%83%B3%E3%83%81%20%E3%83%95%E3%82%A3%E3%82%AE%E3%83%A5%E3%82%A2&min=10000&transaction=selling | P54: https://search.rakuten.co.jp/search/mall/KISS%2012%E3%82%A4%E3%83%B3%E3%83%81%20%E3%83%95%E3%82%A3%E3%82%AE%E3%83%A5%E3%82%A2/?min=10000 | Q54: https://auctions.yahoo.co.jp/search/search?p=KISS%2012%E3%82%A4%E3%83%B3%E3%83%81%20%E3%83%95%E3%82%A3%E3%82%AE%E3%83%A5%E3%82%A2&aucminprice=10000 | R54: https://shopping.yahoo.co.jp/search/KISS%2012%E3%82%A4%E3%83%B3%E3%83%81%20%E3%83%95%E3%82%A3%E3%82%AE%E3%83%A5%E3%82%A2/0/?pf=10000
A55: 1711 | B55: (未使用･未開封品) 超合金メカゴジラ2004(ブラックバージョン) lok26k6 | C55: 1 | D55: 13000 | E55: 193 | F55: Fedex 2.0kg | G55: https://www.ebay.com/sch/i.html?_nkw=Chogokin%20Mechagodzilla%202004%20Black&_sacat=0&_from=R40&_sop=15&rt=nc&_udlo=20000 | H55: https://jp.mercari.com/shops/product/2JUGr6vHSnR9SpPJDpUFby | I55: https://jp.mercari.com/shops/product/2JRiRZAfKH8oFxxz9kHBkj | J55: https://jp.mercari.com/shops/product/2JU6Kopb7pHrYN39rX4pXB | K55: https://jp.mercari.com/shops/product/2JRQJUDjcvZT9jHYax7ZQK | L55: https://auctions.yahoo.co.jp/jp/auction/c1239865978 | N55: https://jp.mercari.com/search?keyword=%E8%B6%85%E5%90%88%E9%87%91%20%E3%83%A1%E3%82%AB%E3%82%B4%E3%82%B8%E3%83%A92004%20%E3%83%96%E3%83%A9%E3%83%83%E3%82%AF&price_min=10000&sort=price&order=asc&status=on_sale | O55: https://fril.jp/s?query=%E8%B6%85%E5%90%88%E9%87%91%20%E3%83%A1%E3%82%AB%E3%82%B4%E3%82%B8%E3%83%A92004%20%E3%83%96%E3%83%A9%E3%83%83%E3%82%AF&min=10000&transaction=selling | P55: https://search.rakuten.co.jp/search/mall/%E8%B6%85%E5%90%88%E9%87%91%20%E3%83%A1%E3%82%AB%E3%82%B4%E3%82%B8%E3%83%A92004%20%E3%83%96%E3%83%A9%E3%83%83%E3%82%AF/?min=10000 | Q55: https://auctions.yahoo.co.jp/search/search?p=%E8%B6%85%E5%90%88%E9%87%91%20%E3%83%A1%E3%82%AB%E3%82%B4%E3%82%B8%E3%83%A92004%20%E3%83%96%E3%83%A9%E3%83%83%E3%82%AF&aucminprice=10000 | R55: https://shopping.yahoo.co.jp/search/%E8%B6%85%E5%90%88%E9%87%91%20%E3%83%A1%E3%82%AB%E3%82%B4%E3%82%B8%E3%83%A92004%20%E3%83%96%E3%83%A9%E3%83%83%E3%82%AF/0/?pf=10000
A56: 1712 | B56: 新品同様 ポピー 超合金 メカゴジラ | C56: 1 | D56: 79800 | E56: 880 | F56: Fedex 1.5kg | G56: https://www.ebay.com/sch/i.html?_nkw=Popy%20Chogokin%20Mechagodzilla&_sacat=0&_from=R40&_sop=15&rt=nc&_udlo=20000 | H56: https://jp.mercari.com/shops/product/2JMbWsRLdJeksEgW8dhoeZ | I56: https://item.fril.jp/232af237ab6294b60bb334847b993135?_gl=1*1ujglmk*Rakuma_gcl_aw*R0NMLjE3ODI4MzU5MTQuQ2p3S0NBancxdExPQmhBTUVpd0FpUGtSSHM1VDlLb0tJYlRWSHl6YkFMRno5dnlJaFR3RXd5XzlQenJHQ3FwSXFSSTczYnB6ZzNlV2lSb0M1SmtRQXZEX0J3RQ..*Rakuma_gcl_au*MTAzMDgyNTc4Mi4xNzg1ODU5NTQ3*_gcl_aw*R0NMLjE3ODI4MzU5MTYuQ2p3S0NBancxdExPQmhBTUVpd0FpUGtSSHM1VDlLb0tJYlRWSHl6YkFMRno5dnlJaFR3RXd5XzlQenJHQ3FwSXFSSTczYnB6ZzNlV2lSb0M1SmtRQXZEX0J3RQ..*_gcl_au*MTE5OTAwMTc0LjE3ODU1MDU0ODI.*_ga*MTMzMjQzMDk0MS4xNzE1MzM3Njg2*_ga_7KV9PBS698*czE3ODYwMjU5ODUkbzExMSRnMSR0MTc4NjAyNjc1NyRqNTckbDAkaDA. | J56: https://auctions.yahoo.co.jp/jp/auction/j1220776963 | N56: https://jp.mercari.com/search?keyword=%E3%83%9D%E3%83%94%E3%83%BC%20%E8%B6%85%E5%90%88%E9%87%91%20%E3%83%A1%E3%82%AB%E3%82%B4%E3%82%B8%E3%83%A9&price_min=10000&sort=price&order=asc&status=on_sale | O56: https://fril.jp/s?query=%E3%83%9D%E3%83%94%E3%83%BC%20%E8%B6%85%E5%90%88%E9%87%91%20%E3%83%A1%E3%82%AB%E3%82%B4%E3%82%B8%E3%83%A9&min=10000&transaction=selling | P56: https://search.rakuten.co.jp/search/mall/%E3%83%9D%E3%83%94%E3%83%BC%20%E8%B6%85%E5%90%88%E9%87%91%20%E3%83%A1%E3%82%AB%E3%82%B4%E3%82%B8%E3%83%A9/?min=10000 | Q56: https://auctions.yahoo.co.jp/search/search?p=%E3%83%9D%E3%83%94%E3%83%BC%20%E8%B6%85%E5%90%88%E9%87%91%20%E3%83%A1%E3%82%AB%E3%82%B4%E3%82%B8%E3%83%A9&aucminprice=10000 | R56: https://shopping.yahoo.co.jp/search/%E3%83%9D%E3%83%94%E3%83%BC%20%E8%B6%85%E5%90%88%E9%87%91%20%E3%83%A1%E3%82%AB%E3%82%B4%E3%82%B8%E3%83%A9/0/?pf=10000
A57: 1713 | B57: GUILTY GEAR XX イノ フィギュア 限定 新品 | C57: 1 | D57: 38500 | E57: 427 | F57: Fedex 4.5kg | G57: https://www.ebay.com/sch/i.html?_nkw=Max%20Factory%20I-No%20Guilty%20Gear%20figure&_sacat=0&_from=R40&_sop=15&rt=nc&_udlo=20000 | H57: https://jp.mercari.com/item/m14829633369 | I57: 仕入れ先URLの10枚中3枚目の画像（赤い外箱の画像）をメイン画像にしてくださいシイサキマイチュウマイメガゾウアカソトバコガゾウガゾウ | N57: https://jp.mercari.com/search?keyword=GUILTY%20GEAR%20%E3%82%A4%E3%83%8E%20%E3%83%95%E3%82%A3%E3%82%AE%E3%83%A5%E3%82%A2&price_min=10000&sort=price&order=asc&status=on_sale | O57: https://fril.jp/s?query=GUILTY%20GEAR%20%E3%82%A4%E3%83%8E%20%E3%83%95%E3%82%A3%E3%82%AE%E3%83%A5%E3%82%A2&min=10000&transaction=selling | P57: https://search.rakuten.co.jp/search/mall/GUILTY%20GEAR%20%E3%82%A4%E3%83%8E%20%E3%83%95%E3%82%A3%E3%82%AE%E3%83%A5%E3%82%A2/?min=10000 | Q57: https://auctions.yahoo.co.jp/search/search?p=GUILTY%20GEAR%20%E3%82%A4%E3%83%8E%20%E3%83%95%E3%82%A3%E3%82%AE%E3%83%A5%E3%82%A2&aucminprice=10000 | R57: https://shopping.yahoo.co.jp/search/GUILTY%20GEAR%20%E3%82%A4%E3%83%8E%20%E3%83%95%E3%82%A3%E3%82%AE%E3%83%A5%E3%82%A2/0/?pf=10000
A58: 1714 | B58: 異世界迷宮でハーレムを ロクサーヌ 氷樹一世コミックver フィギュア | C58: 1 | D58: 24980 | E58: 372 | F58: Fedex 1.5kg | G58: https://www.ebay.com/sch/i.html?_nkw=Harem%20Labyrinth%20Roxanne%20comic%20figure&_sacat=0&_from=R40&_sop=15&rt=nc&_udlo=20000 | H58: https://jp.mercari.com/item/m61827929822 | N58: https://jp.mercari.com/search?keyword=%E7%95%B0%E4%B8%96%E7%95%8C%E8%BF%B7%E5%AE%AE%E3%81%A7%E3%83%8F%E3%83%BC%E3%83%AC%E3%83%A0%E3%82%92%20%E3%83%AD%E3%82%AF%E3%82%B5%E3%83%BC%E3%83%8C%20%E3%82%B3%E3%83%9F%E3%83%83%E3%82%AFver%201%2F7&price_min=10000&sort=price&order=asc&status=on_sale | O58: https://fril.jp/s?query=%E7%95%B0%E4%B8%96%E7%95%8C%E8%BF%B7%E5%AE%AE%E3%81%A7%E3%83%8F%E3%83%BC%E3%83%AC%E3%83%A0%E3%82%92%20%E3%83%AD%E3%82%AF%E3%82%B5%E3%83%BC%E3%83%8C%20%E3%82%B3%E3%83%9F%E3%83%83%E3%82%AFver%201%2F7&min=10000&transaction=selling | P58: https://search.rakuten.co.jp/search/mall/%E7%95%B0%E4%B8%96%E7%95%8C%E8%BF%B7%E5%AE%AE%E3%81%A7%E3%83%8F%E3%83%BC%E3%83%AC%E3%83%A0%E3%82%92%20%E3%83%AD%E3%82%AF%E3%82%B5%E3%83%BC%E3%83%8C%20%E3%82%B3%E3%83%9F%E3%83%83%E3%82%AFver%201%2F7/?min=10000 | Q58: https://auctions.yahoo.co.jp/search/search?p=%E7%95%B0%E4%B8%96%E7%95%8C%E8%BF%B7%E5%AE%AE%E3%81%A7%E3%83%8F%E3%83%BC%E3%83%AC%E3%83%A0%E3%82%92%20%E3%83%AD%E3%82%AF%E3%82%B5%E3%83%BC%E3%83%8C%20%E3%82%B3%E3%83%9F%E3%83%83%E3%82%AFver%201%2F7&aucminprice=10000 | R58: https://shopping.yahoo.co.jp/search/%E7%95%B0%E4%B8%96%E7%95%8C%E8%BF%B7%E5%AE%AE%E3%81%A7%E3%83%8F%E3%83%BC%E3%83%AC%E3%83%A0%E3%82%92%20%E3%83%AD%E3%82%AF%E3%82%B5%E3%83%BC%E3%83%8C%20%E3%82%B3%E3%83%9F%E3%83%83%E3%82%AFver%201%2F7/0/?pf=10000
A59: 1715 | B59: Realize ガレージキット 2体セット | C59: 1 | D59: 15555 | E59: 286 | F59: Fedex 1.5kg | G59: https://www.ebay.com/sch/i.html?_nkw=Realize%20garage%20kit%20set&_sacat=0&_from=R40&_sop=15&rt=nc&_udlo=20000 | H59: https://jp.mercari.com/item/m11658788348 | N59: https://jp.mercari.com/search?keyword=Realize%20%E3%82%AC%E3%83%AC%E3%83%BC%E3%82%B8%E3%82%AD%E3%83%83%E3%83%88%20%E3%82%BB%E3%83%83%E3%83%88&price_min=10000&sort=price&order=asc&status=on_sale | O59: https://fril.jp/s?query=Realize%20%E3%82%AC%E3%83%AC%E3%83%BC%E3%82%B8%E3%82%AD%E3%83%83%E3%83%88%20%E3%82%BB%E3%83%83%E3%83%88&min=10000&transaction=selling | P59: https://search.rakuten.co.jp/search/mall/Realize%20%E3%82%AC%E3%83%AC%E3%83%BC%E3%82%B8%E3%82%AD%E3%83%83%E3%83%88%20%E3%82%BB%E3%83%83%E3%83%88/?min=10000 | Q59: https://auctions.yahoo.co.jp/search/search?p=Realize%20%E3%82%AC%E3%83%AC%E3%83%BC%E3%82%B8%E3%82%AD%E3%83%83%E3%83%88%20%E3%82%BB%E3%83%83%E3%83%88&aucminprice=10000 | R59: https://shopping.yahoo.co.jp/search/Realize%20%E3%82%AC%E3%83%AC%E3%83%BC%E3%82%B8%E3%82%AD%E3%83%83%E3%83%88%20%E3%82%BB%E3%83%83%E3%83%88/0/?pf=10000
A60: 1716 | B60: 大谷翔平 パッケージスリーブ | C60: 1 | D60: 100000 | E60: 1053 | F60: Fedex 0.5kg | G60: https://www.ebay.com/sch/i.html?_nkw=Ohtani%20package%20sleeve&_sacat=0&_from=R40&_sop=15&rt=nc&_udlo=20000 | H60: https://paypayfleamarket.yahoo.co.jp/item/z647477800 | N60: https://jp.mercari.com/search?keyword=%E5%A4%A7%E8%B0%B7%E7%BF%94%E5%B9%B3%20%E3%83%91%E3%83%83%E3%82%B1%E3%83%BC%E3%82%B8%20%E3%82%B9%E3%83%AA%E3%83%BC%E3%83%96&price_min=10000&sort=price&order=asc&status=on_sale | O60: https://fril.jp/s?query=%E5%A4%A7%E8%B0%B7%E7%BF%94%E5%B9%B3%20%E3%83%91%E3%83%83%E3%82%B1%E3%83%BC%E3%82%B8%20%E3%82%B9%E3%83%AA%E3%83%BC%E3%83%96&min=10000&transaction=selling | P60: https://search.rakuten.co.jp/search/mall/%E5%A4%A7%E8%B0%B7%E7%BF%94%E5%B9%B3%20%E3%83%91%E3%83%83%E3%82%B1%E3%83%BC%E3%82%B8%20%E3%82%B9%E3%83%AA%E3%83%BC%E3%83%96/?min=10000 | Q60: https://auctions.yahoo.co.jp/search/search?p=%E5%A4%A7%E8%B0%B7%E7%BF%94%E5%B9%B3%20%E3%83%91%E3%83%83%E3%82%B1%E3%83%BC%E3%82%B8%20%E3%82%B9%E3%83%AA%E3%83%BC%E3%83%96&aucminprice=10000 | R60: https://shopping.yahoo.co.jp/search/%E5%A4%A7%E8%B0%B7%E7%BF%94%E5%B9%B3%20%E3%83%91%E3%83%83%E3%82%B1%E3%83%BC%E3%82%B8%20%E3%82%B9%E3%83%AA%E3%83%BC%E3%83%96/0/?pf=10000
A61: 1717 | B61: RIOBOT ゲッターロボ デヴォリューション ＋ アップグレードパーツセット | C61: 1 | D61: 83000 | E61: 950 | F61: Fedex 2.0kg | G61: https://www.ebay.com/sch/i.html?_nkw=RIOBOT%20Getter%20Robo%20Devolution&_sacat=0&_from=R40&_sop=15&rt=nc&_udlo=20000 | H61: https://jp.mercari.com/item/m14135353857 | N61: https://jp.mercari.com/search?keyword=RIOBOT%20%E3%82%B2%E3%83%83%E3%82%BF%E3%83%BC%E3%83%AD%E3%83%9C%20%E3%83%87%E3%83%B4%E3%82%A9%E3%83%AA%E3%83%A5%E3%83%BC%E3%82%B7%E3%83%A7%E3%83%B3&price_min=10000&sort=price&order=asc&status=on_sale | O61: https://fril.jp/s?query=RIOBOT%20%E3%82%B2%E3%83%83%E3%82%BF%E3%83%BC%E3%83%AD%E3%83%9C%20%E3%83%87%E3%83%B4%E3%82%A9%E3%83%AA%E3%83%A5%E3%83%BC%E3%82%B7%E3%83%A7%E3%83%B3&min=10000&transaction=selling | P61: https://search.rakuten.co.jp/search/mall/RIOBOT%20%E3%82%B2%E3%83%83%E3%82%BF%E3%83%BC%E3%83%AD%E3%83%9C%20%E3%83%87%E3%83%B4%E3%82%A9%E3%83%AA%E3%83%A5%E3%83%BC%E3%82%B7%E3%83%A7%E3%83%B3/?min=10000 | Q61: https://auctions.yahoo.co.jp/search/search?p=RIOBOT%20%E3%82%B2%E3%83%83%E3%82%BF%E3%83%BC%E3%83%AD%E3%83%9C%20%E3%83%87%E3%83%B4%E3%82%A9%E3%83%AA%E3%83%A5%E3%83%BC%E3%82%B7%E3%83%A7%E3%83%B3&aucminprice=10000 | R61: https://shopping.yahoo.co.jp/search/RIOBOT%20%E3%82%B2%E3%83%83%E3%82%BF%E3%83%BC%E3%83%AD%E3%83%9C%20%E3%83%87%E3%83%B4%E3%82%A9%E3%83%AA%E3%83%A5%E3%83%BC%E3%82%B7%E3%83%A7%E3%83%B3/0/?pf=10000
A62: 1718 | B62: 文豪ストレイドッグス太宰治F:NEX1/7スケールフィギュアFuRyu受注生産 | C62: 1 | D62: 85000 | E62: 922 | F62: Fedex 1.5kg | G62: https://www.ebay.com/sch/i.html?_nkw=Bungo%20Stray%20Dogs%20Dazai%20FNEX%20figure&_sacat=0&_from=R40&_sop=15&rt=nc&_udlo=20000 | H62: https://jp.mercari.com/item/m84715579311 | N62: https://jp.mercari.com/search?keyword=%E6%96%87%E8%B1%AA%E3%82%B9%E3%83%88%E3%83%AC%E3%82%A4%E3%83%89%E3%83%83%E3%82%B0%E3%82%B9%20%E5%A4%AA%E5%AE%B0%E6%B2%BB%20F%3ANEX%201%2F7&price_min=10000&sort=price&order=asc&status=on_sale | O62: https://fril.jp/s?query=%E6%96%87%E8%B1%AA%E3%82%B9%E3%83%88%E3%83%AC%E3%82%A4%E3%83%89%E3%83%83%E3%82%B0%E3%82%B9%20%E5%A4%AA%E5%AE%B0%E6%B2%BB%20F%3ANEX%201%2F7&min=10000&transaction=selling | P62: https://search.rakuten.co.jp/search/mall/%E6%96%87%E8%B1%AA%E3%82%B9%E3%83%88%E3%83%AC%E3%82%A4%E3%83%89%E3%83%83%E3%82%B0%E3%82%B9%20%E5%A4%AA%E5%AE%B0%E6%B2%BB%20F%3ANEX%201%2F7/?min=10000 | Q62: https://auctions.yahoo.co.jp/search/search?p=%E6%96%87%E8%B1%AA%E3%82%B9%E3%83%88%E3%83%AC%E3%82%A4%E3%83%89%E3%83%83%E3%82%B0%E3%82%B9%20%E5%A4%AA%E5%AE%B0%E6%B2%BB%20F%3ANEX%201%2F7&aucminprice=10000 | R62: https://shopping.yahoo.co.jp/search/%E6%96%87%E8%B1%AA%E3%82%B9%E3%83%88%E3%83%AC%E3%82%A4%E3%83%89%E3%83%83%E3%82%B0%E3%82%B9%20%E5%A4%AA%E5%AE%B0%E6%B2%BB%20F%3ANEX%201%2F7/0/?pf=10000
A63: 1719 | B63: 文豪ストレイドッグス 中原中也 1/7スケールフィギュア タキシード | C63: 1 | D63: 84999 | E63: 922 | F63: Fedex 1.5kg | G63: https://www.ebay.com/sch/i.html?_nkw=Bungo%20Stray%20Dogs%20Nakahara%201/7%20figure&_sacat=0&_from=R40&_sop=15&rt=nc&_udlo=20000 | H63: https://jp.mercari.com/item/m14231022758 | N63: https://jp.mercari.com/search?keyword=%E6%96%87%E8%B1%AA%E3%82%B9%E3%83%88%E3%83%AC%E3%82%A4%E3%83%89%E3%83%83%E3%82%B0%E3%82%B9%20%E4%B8%AD%E5%8E%9F%E4%B8%AD%E4%B9%9F%201%2F7%20%E3%82%BF%E3%82%AD%E3%82%B7%E3%83%BC%E3%83%89&price_min=10000&sort=price&order=asc&status=on_sale | O63: https://fril.jp/s?query=%E6%96%87%E8%B1%AA%E3%82%B9%E3%83%88%E3%83%AC%E3%82%A4%E3%83%89%E3%83%83%E3%82%B0%E3%82%B9%20%E4%B8%AD%E5%8E%9F%E4%B8%AD%E4%B9%9F%201%2F7%20%E3%82%BF%E3%82%AD%E3%82%B7%E3%83%BC%E3%83%89&min=10000&transaction=selling | P63: https://search.rakuten.co.jp/search/mall/%E6%96%87%E8%B1%AA%E3%82%B9%E3%83%88%E3%83%AC%E3%82%A4%E3%83%89%E3%83%83%E3%82%B0%E3%82%B9%20%E4%B8%AD%E5%8E%9F%E4%B8%AD%E4%B9%9F%201%2F7%20%E3%82%BF%E3%82%AD%E3%82%B7%E3%83%BC%E3%83%89/?min=10000 | Q63: https://auctions.yahoo.co.jp/search/search?p=%E6%96%87%E8%B1%AA%E3%82%B9%E3%83%88%E3%83%AC%E3%82%A4%E3%83%89%E3%83%83%E3%82%B0%E3%82%B9%20%E4%B8%AD%E5%8E%9F%E4%B8%AD%E4%B9%9F%201%2F7%20%E3%82%BF%E3%82%AD%E3%82%B7%E3%83%BC%E3%83%89&aucminprice=10000 | R63: https://shopping.yahoo.co.jp/search/%E6%96%87%E8%B1%AA%E3%82%B9%E3%83%88%E3%83%AC%E3%82%A4%E3%83%89%E3%83%83%E3%82%B0%E3%82%B9%20%E4%B8%AD%E5%8E%9F%E4%B8%AD%E4%B9%9F%201%2F7%20%E3%82%BF%E3%82%AD%E3%82%B7%E3%83%BC%E3%83%89/0/?pf=10000
A64: 1720 | B64: 1/6フィギュア 織田信長 戦国武将 侍 戦国無双 戦国BASARA 刀 甲冑 | C64: 1 | D64: 48700 | E64: 610 | F64: Fedex 2.0kg | G64: https://www.ebay.com/sch/i.html?_nkw=Oda%20Nobunaga%201/6%20samurai%20figure&_sacat=0&_from=R40&_sop=15&rt=nc&_udlo=20000 | H64: https://jp.mercari.com/item/m33597846033 | N64: https://jp.mercari.com/search?keyword=%E7%B9%94%E7%94%B0%E4%BF%A1%E9%95%B7%201%2F6%20%E3%83%95%E3%82%A3%E3%82%AE%E3%83%A5%E3%82%A2%20%E4%BE%8D%20%E7%94%B2%E5%86%91&price_min=10000&sort=price&order=asc&status=on_sale | O64: https://fril.jp/s?query=%E7%B9%94%E7%94%B0%E4%BF%A1%E9%95%B7%201%2F6%20%E3%83%95%E3%82%A3%E3%82%AE%E3%83%A5%E3%82%A2%20%E4%BE%8D%20%E7%94%B2%E5%86%91&min=10000&transaction=selling | P64: https://search.rakuten.co.jp/search/mall/%E7%B9%94%E7%94%B0%E4%BF%A1%E9%95%B7%201%2F6%20%E3%83%95%E3%82%A3%E3%82%AE%E3%83%A5%E3%82%A2%20%E4%BE%8D%20%E7%94%B2%E5%86%91/?min=10000 | Q64: https://auctions.yahoo.co.jp/search/search?p=%E7%B9%94%E7%94%B0%E4%BF%A1%E9%95%B7%201%2F6%20%E3%83%95%E3%82%A3%E3%82%AE%E3%83%A5%E3%82%A2%20%E4%BE%8D%20%E7%94%B2%E5%86%91&aucminprice=10000 | R64: https://shopping.yahoo.co.jp/search/%E7%B9%94%E7%94%B0%E4%BF%A1%E9%95%B7%201%2F6%20%E3%83%95%E3%82%A3%E3%82%AE%E3%83%A5%E3%82%A2%20%E4%BE%8D%20%E7%94%B2%E5%86%91/0/?pf=10000
A65: 1721 | B65: タミヤ 1/12 ポルシェ カレラGT ビッグスケールシリーズ プラモデル 新品 | C65: 1 | D65: 47000 | E65: 699 | F65: Fedex 4.5kg | G65: https://www.ebay.com/sch/i.html?_nkw=Tamiya%201/12%20Porsche%20Carrera%20GT%20kit&_sacat=0&_from=R40&_sop=15&rt=nc&_udlo=20000 | H65: https://jp.mercari.com/item/m97837265470 | I65: https://auctions.yahoo.co.jp/jp/auction/t1231044347 | N65: https://jp.mercari.com/search?keyword=%E3%82%BF%E3%83%9F%E3%83%A4%201%2F12%20%E3%83%9D%E3%83%AB%E3%82%B7%E3%82%A7%20%E3%82%AB%E3%83%AC%E3%83%A9GT%20%E3%83%97%E3%83%A9%E3%83%A2&price_min=10000&sort=price&order=asc&status=on_sale | O65: https://fril.jp/s?query=%E3%82%BF%E3%83%9F%E3%83%A4%201%2F12%20%E3%83%9D%E3%83%AB%E3%82%B7%E3%82%A7%20%E3%82%AB%E3%83%AC%E3%83%A9GT%20%E3%83%97%E3%83%A9%E3%83%A2&min=10000&transaction=selling | P65: https://search.rakuten.co.jp/search/mall/%E3%82%BF%E3%83%9F%E3%83%A4%201%2F12%20%E3%83%9D%E3%83%AB%E3%82%B7%E3%82%A7%20%E3%82%AB%E3%83%AC%E3%83%A9GT%20%E3%83%97%E3%83%A9%E3%83%A2/?min=10000 | Q65: https://auctions.yahoo.co.jp/search/search?p=%E3%82%BF%E3%83%9F%E3%83%A4%201%2F12%20%E3%83%9D%E3%83%AB%E3%82%B7%E3%82%A7%20%E3%82%AB%E3%83%AC%E3%83%A9GT%20%E3%83%97%E3%83%A9%E3%83%A2&aucminprice=10000 | R65: https://shopping.yahoo.co.jp/search/%E3%82%BF%E3%83%9F%E3%83%A4%201%2F12%20%E3%83%9D%E3%83%AB%E3%82%B7%E3%82%A7%20%E3%82%AB%E3%83%AC%E3%83%A9GT%20%E3%83%97%E3%83%A9%E3%83%A2/0/?pf=10000
A66: 1722 | B66: TRF102 シャーシ キット タミヤ TAMIYA 84432 限定 | C66: 1 | D66: 67980 | E66: 820 | F66: Fedex 4.5kg | G66: https://www.ebay.com/sch/i.html?_nkw=Tamiya%20TRF102%20chassis%2084432&_sacat=0&_from=R40&_sop=15&rt=nc&_udlo=20000 | H66: https://paypayfleamarket.yahoo.co.jp/item/z602727038 | I66: https://jp.mercari.com/item/m55790842800 | N66: https://jp.mercari.com/search?keyword=%E3%82%BF%E3%83%9F%E3%83%A4%20TRF102%20%E3%82%B7%E3%83%A3%E3%83%BC%E3%82%B7%20%E3%82%AD%E3%83%83%E3%83%88%2084432&price_min=10000&sort=price&order=asc&status=on_sale | O66: https://fril.jp/s?query=%E3%82%BF%E3%83%9F%E3%83%A4%20TRF102%20%E3%82%B7%E3%83%A3%E3%83%BC%E3%82%B7%20%E3%82%AD%E3%83%83%E3%83%88%2084432&min=10000&transaction=selling | P66: https://search.rakuten.co.jp/search/mall/%E3%82%BF%E3%83%9F%E3%83%A4%20TRF102%20%E3%82%B7%E3%83%A3%E3%83%BC%E3%82%B7%20%E3%82%AD%E3%83%83%E3%83%88%2084432/?min=10000 | Q66: https://auctions.yahoo.co.jp/search/search?p=%E3%82%BF%E3%83%9F%E3%83%A4%20TRF102%20%E3%82%B7%E3%83%A3%E3%83%BC%E3%82%B7%20%E3%82%AD%E3%83%83%E3%83%88%2084432&aucminprice=10000 | R66: https://shopping.yahoo.co.jp/search/%E3%82%BF%E3%83%9F%E3%83%A4%20TRF102%20%E3%82%B7%E3%83%A3%E3%83%BC%E3%82%B7%20%E3%82%AD%E3%83%83%E3%83%88%2084432/0/?pf=10000
A67: 1723 | B67: トラベラーズノート パスポートサイズ LOVE AND TRIP レッド | C67: 1 | D67: 28000 | E67: 340 | F67: Fedex 0.5kg | G67: https://www.ebay.com/sch/i.html?_nkw=Traveler%27s%20Notebook%20Love%20Trip%20passport&_sacat=0&_from=R40&_sop=15&rt=nc | H67: https://paypayfleamarket.yahoo.co.jp/item/z596900862 | N67: https://jp.mercari.com/search?keyword=%E3%83%88%E3%83%A9%E3%83%99%E3%83%A9%E3%83%BC%E3%82%BA%E3%83%8E%E3%83%BC%E3%83%88%20LOVE%20AND%20TRIP%20%E3%83%91%E3%82%B9%E3%83%9D%E3%83%BC%E3%83%88&price_min=10000&sort=price&order=asc&status=on_sale | O67: https://fril.jp/s?query=%E3%83%88%E3%83%A9%E3%83%99%E3%83%A9%E3%83%BC%E3%82%BA%E3%83%8E%E3%83%BC%E3%83%88%20LOVE%20AND%20TRIP%20%E3%83%91%E3%82%B9%E3%83%9D%E3%83%BC%E3%83%88&min=10000&transaction=selling | P67: https://search.rakuten.co.jp/search/mall/%E3%83%88%E3%83%A9%E3%83%99%E3%83%A9%E3%83%BC%E3%82%BA%E3%83%8E%E3%83%BC%E3%83%88%20LOVE%20AND%20TRIP%20%E3%83%91%E3%82%B9%E3%83%9D%E3%83%BC%E3%83%88/?min=10000 | Q67: https://auctions.yahoo.co.jp/search/search?p=%E3%83%88%E3%83%A9%E3%83%99%E3%83%A9%E3%83%BC%E3%82%BA%E3%83%8E%E3%83%BC%E3%83%88%20LOVE%20AND%20TRIP%20%E3%83%91%E3%82%B9%E3%83%9D%E3%83%BC%E3%83%88&aucminprice=10000 | R67: https://shopping.yahoo.co.jp/search/%E3%83%88%E3%83%A9%E3%83%99%E3%83%A9%E3%83%BC%E3%82%BA%E3%83%8E%E3%83%BC%E3%83%88%20LOVE%20AND%20TRIP%20%E3%83%91%E3%82%B9%E3%83%9D%E3%83%BC%E3%83%88/0/?pf=10000
A68: 1724 | B68: トラベラーズノート 2022限定セット『レコード』... | C68: 1 | D68: 68000 | E68: 830 | F68: Fedex 0.5kg | G68: https://www.ebay.com/sch/i.html?_nkw=Traveler%27s%20Notebook%202022%20limited&_sacat=0&_from=R40&_sop=15&rt=nc | H68: https://jp.mercari.com/item/m16177170738 | N68: https://jp.mercari.com/search?keyword=%E3%83%88%E3%83%A9%E3%83%99%E3%83%A9%E3%83%BC%E3%82%BA%E3%83%8E%E3%83%BC%E3%83%88%202022%E9%99%90%E5%AE%9A%20%E3%83%AC%E3%82%B3%E3%83%BC%E3%83%89&price_min=10000&sort=price&order=asc&status=on_sale | O68: https://fril.jp/s?query=%E3%83%88%E3%83%A9%E3%83%99%E3%83%A9%E3%83%BC%E3%82%BA%E3%83%8E%E3%83%BC%E3%83%88%202022%E9%99%90%E5%AE%9A%20%E3%83%AC%E3%82%B3%E3%83%BC%E3%83%89&min=10000&transaction=selling | P68: https://search.rakuten.co.jp/search/mall/%E3%83%88%E3%83%A9%E3%83%99%E3%83%A9%E3%83%BC%E3%82%BA%E3%83%8E%E3%83%BC%E3%83%88%202022%E9%99%90%E5%AE%9A%20%E3%83%AC%E3%82%B3%E3%83%BC%E3%83%89/?min=10000 | Q68: https://auctions.yahoo.co.jp/search/search?p=%E3%83%88%E3%83%A9%E3%83%99%E3%83%A9%E3%83%BC%E3%82%BA%E3%83%8E%E3%83%BC%E3%83%88%202022%E9%99%90%E5%AE%9A%20%E3%83%AC%E3%82%B3%E3%83%BC%E3%83%89&aucminprice=10000 | R68: https://shopping.yahoo.co.jp/search/%E3%83%88%E3%83%A9%E3%83%99%E3%83%A9%E3%83%BC%E3%82%BA%E3%83%8E%E3%83%BC%E3%83%88%202022%E9%99%90%E5%AE%9A%20%E3%83%AC%E3%82%B3%E3%83%BC%E3%83%89/0/?pf=10000
A69: 1725 | B69: FF14 紅蓮の解放者（ぐれんのリベレーター ） コレクターズエディション未開封 | C69: 1 | D69: 28000 | E69: 450 | F69: Fedex 7.0kg | G69: https://www.ebay.com/sch/i.html?_nkw=FFXIV%20Stormblood%20Collector%27s%20Edition&_sacat=0&_from=R40&_sop=15&rt=nc | H69: https://jp.mercari.com/item/m12338195185 | N69: https://jp.mercari.com/search?keyword=FF14%20%E7%B4%85%E8%93%AE%E3%81%AE%E3%83%AA%E3%83%99%E3%83%AC%E3%83%BC%E3%82%BF%E3%83%BC%20%E3%82%B3%E3%83%AC%E3%82%AF%E3%82%BF%E3%83%BC%E3%82%BA&price_min=10000&sort=price&order=asc&status=on_sale | O69: https://fril.jp/s?query=FF14%20%E7%B4%85%E8%93%AE%E3%81%AE%E3%83%AA%E3%83%99%E3%83%AC%E3%83%BC%E3%82%BF%E3%83%BC%20%E3%82%B3%E3%83%AC%E3%82%AF%E3%82%BF%E3%83%BC%E3%82%BA&min=10000&transaction=selling | P69: https://search.rakuten.co.jp/search/mall/FF14%20%E7%B4%85%E8%93%AE%E3%81%AE%E3%83%AA%E3%83%99%E3%83%AC%E3%83%BC%E3%82%BF%E3%83%BC%20%E3%82%B3%E3%83%AC%E3%82%AF%E3%82%BF%E3%83%BC%E3%82%BA/?min=10000 | Q69: https://auctions.yahoo.co.jp/search/search?p=FF14%20%E7%B4%85%E8%93%AE%E3%81%AE%E3%83%AA%E3%83%99%E3%83%AC%E3%83%BC%E3%82%BF%E3%83%BC%20%E3%82%B3%E3%83%AC%E3%82%AF%E3%82%BF%E3%83%BC%E3%82%BA&aucminprice=10000 | R69: https://shopping.yahoo.co.jp/search/FF14%20%E7%B4%85%E8%93%AE%E3%81%AE%E3%83%AA%E3%83%99%E3%83%AC%E3%83%BC%E3%82%BF%E3%83%BC%20%E3%82%B3%E3%83%AC%E3%82%AF%E3%82%BF%E3%83%BC%E3%82%BA/0/?pf=10000
A70: 1726 | B70: 即決 紙ジャケット A 【デヴィッド・ボウイ / ア... | C70: 1 | D70: 25210 | E70: 399 | F70: Fedex 3.5kg | G70: https://www.ebay.com/sch/i.html?_nkw=David%20Bowie%20New%20Career%20New%20Town&_sacat=0&_from=R40&_sop=15&rt=nc | H70: https://page.auctions.yahoo.co.jp/jp/auction/n1152405819 | N70: https://jp.mercari.com/search?keyword=David%20Bowie%20A%20New%20Career%20in%20a%20New%20Town%20CD&price_min=10000&sort=price&order=asc&status=on_sale | O70: https://fril.jp/s?query=David%20Bowie%20A%20New%20Career%20in%20a%20New%20Town%20CD&min=10000&transaction=selling | P70: https://search.rakuten.co.jp/search/mall/David%20Bowie%20A%20New%20Career%20in%20a%20New%20Town%20CD/?min=10000 | Q70: https://auctions.yahoo.co.jp/search/search?p=David%20Bowie%20A%20New%20Career%20in%20a%20New%20Town%20CD&aucminprice=10000 | R70: https://shopping.yahoo.co.jp/search/David%20Bowie%20A%20New%20Career%20in%20a%20New%20Town%20CD/0/?pf=10000
A71: 1727 | B71: 逆転裁判 蘇る逆転〜4 逆転検事 公式ガイド 攻略本 設定資料集 6冊セット | C71: 1 | D71: 11780 | E71: 175 | F71: Fedex 0.5kg | G71: https://www.ebay.com/sch/i.html?_nkw=Ace%20Attorney%20guide%20book%20set&_sacat=0&_from=R40&_sop=15&rt=nc | H71: https://auctions.yahoo.co.jp/jp/auction/d1194831913 | I71: https://jp.mercari.com/item/m50011507121 | N71: https://jp.mercari.com/search?keyword=%E9%80%86%E8%BB%A2%E8%A3%81%E5%88%A4%20%E6%94%BB%E7%95%A5%E6%9C%AC%20%E8%A8%AD%E5%AE%9A%E8%B3%87%E6%96%99&price_min=10000&sort=price&order=asc&status=on_sale | O71: https://fril.jp/s?query=%E9%80%86%E8%BB%A2%E8%A3%81%E5%88%A4%20%E6%94%BB%E7%95%A5%E6%9C%AC%20%E8%A8%AD%E5%AE%9A%E8%B3%87%E6%96%99&min=10000&transaction=selling | P71: https://search.rakuten.co.jp/search/mall/%E9%80%86%E8%BB%A2%E8%A3%81%E5%88%A4%20%E6%94%BB%E7%95%A5%E6%9C%AC%20%E8%A8%AD%E5%AE%9A%E8%B3%87%E6%96%99/?min=10000 | Q71: https://auctions.yahoo.co.jp/search/search?p=%E9%80%86%E8%BB%A2%E8%A3%81%E5%88%A4%20%E6%94%BB%E7%95%A5%E6%9C%AC%20%E8%A8%AD%E5%AE%9A%E8%B3%87%E6%96%99&aucminprice=10000 | R71: https://shopping.yahoo.co.jp/search/%E9%80%86%E8%BB%A2%E8%A3%81%E5%88%A4%20%E6%94%BB%E7%95%A5%E6%9C%AC%20%E8%A8%AD%E5%AE%9A%E8%B3%87%E6%96%99/0/?pf=10000
A72: 1728 | B72: 【希少当時物】2011 逆転検事2 コレクターズ・パッケージ 御剣怜侍 イーカプコン限定 | C72: 1 | D72: 55000 | E72: 650 | F72: Fedex 2.5kg | G72: https://www.ebay.com/sch/i.html?_nkw=Ace%20Attorney%20Investigations%202%20Collector&_sacat=0&_from=R40&_sop=15&rt=nc | H72: https://paypayfleamarket.yahoo.co.jp/item/z632669994 | I72: https://jp.mercari.com/item/m72797263881 | J72: https://jp.mercari.com/item/m10343168508 | K72: https://jp.mercari.com/item/m50934775206 | L72: https://jp.mercari.com/item/m44827383906 | N72: https://jp.mercari.com/search?keyword=%E9%80%86%E8%BB%A2%E6%A4%9C%E4%BA%8B2%20%E3%82%B3%E3%83%AC%E3%82%AF%E3%82%BF%E3%83%BC%E3%82%BA%E3%83%91%E3%83%83%E3%82%B1%E3%83%BC%E3%82%B8&price_min=10000&sort=price&order=asc&status=on_sale | O72: https://fril.jp/s?query=%E9%80%86%E8%BB%A2%E6%A4%9C%E4%BA%8B2%20%E3%82%B3%E3%83%AC%E3%82%AF%E3%82%BF%E3%83%BC%E3%82%BA%E3%83%91%E3%83%83%E3%82%B1%E3%83%BC%E3%82%B8&min=10000&transaction=selling | P72: https://search.rakuten.co.jp/search/mall/%E9%80%86%E8%BB%A2%E6%A4%9C%E4%BA%8B2%20%E3%82%B3%E3%83%AC%E3%82%AF%E3%82%BF%E3%83%BC%E3%82%BA%E3%83%91%E3%83%83%E3%82%B1%E3%83%BC%E3%82%B8/?min=10000 | Q72: https://auctions.yahoo.co.jp/search/search?p=%E9%80%86%E8%BB%A2%E6%A4%9C%E4%BA%8B2%20%E3%82%B3%E3%83%AC%E3%82%AF%E3%82%BF%E3%83%BC%E3%82%BA%E3%83%91%E3%83%83%E3%82%B1%E3%83%BC%E3%82%B8&aucminprice=10000 | R72: https://shopping.yahoo.co.jp/search/%E9%80%86%E8%BB%A2%E6%A4%9C%E4%BA%8B2%20%E3%82%B3%E3%83%AC%E3%82%AF%E3%82%BF%E3%83%BC%E3%82%BA%E3%83%91%E3%83%83%E3%82%B1%E3%83%BC%E3%82%B8/0/?pf=10000
A73: 1729 | B73: ゴジラ(2016) 第4形態 覚醒Ver. パープルクリアエディション | C73: 1 | D73: 28000 | E73: 359 | F73: Fedex 1.5kg | G73: https://www.ebay.com/sch/i.html?_nkw=2016+Godzilla+Purple+Clear&_sacat=0&_from=R40&_trksid=m570.l1313&rt=nc&_odkw=Toho+30cm+Godzilla+Purple+Clear&_osacat=0&_sop=15 | H73: https://paypayfleamarket.yahoo.co.jp/item/z625675692 | I73: https://paypayfleamarket.yahoo.co.jp/item/z634072138 | N73: https://jp.mercari.com/search?keyword=%E6%9D%B1%E5%AE%9D30cm%20%E3%82%B4%E3%82%B8%E3%83%A9%202016%20%E8%A6%9A%E9%86%92%20%E3%83%91%E3%83%BC%E3%83%97%E3%83%AB%E3%82%AF%E3%83%AA%E3%82%A2&price_min=10000&sort=price&order=asc&status=on_sale | O73: https://fril.jp/s?query=%E6%9D%B1%E5%AE%9D30cm%20%E3%82%B4%E3%82%B8%E3%83%A9%202016%20%E8%A6%9A%E9%86%92%20%E3%83%91%E3%83%BC%E3%83%97%E3%83%AB%E3%82%AF%E3%83%AA%E3%82%A2&min=10000&transaction=selling | P73: https://search.rakuten.co.jp/search/mall/%E6%9D%B1%E5%AE%9D30cm%20%E3%82%B4%E3%82%B8%E3%83%A9%202016%20%E8%A6%9A%E9%86%92%20%E3%83%91%E3%83%BC%E3%83%97%E3%83%AB%E3%82%AF%E3%83%AA%E3%82%A2/?min=10000 | Q73: https://auctions.yahoo.co.jp/search/search?p=%E6%9D%B1%E5%AE%9D30cm%20%E3%82%B4%E3%82%B8%E3%83%A9%202016%20%E8%A6%9A%E9%86%92%20%E3%83%91%E3%83%BC%E3%83%97%E3%83%AB%E3%82%AF%E3%83%AA%E3%82%A2&aucminprice=10000 | R73: https://shopping.yahoo.co.jp/search/%E6%9D%B1%E5%AE%9D30cm%20%E3%82%B4%E3%82%B8%E3%83%A9%202016%20%E8%A6%9A%E9%86%92%20%E3%83%91%E3%83%BC%E3%83%97%E3%83%AB%E3%82%AF%E3%83%AA%E3%82%A2/0/?pf=10000
A74: 1730 | B74: ファイナルファンタジー ネックレス ペンダント Exarch's Cane | C74: 1 | D74: 34300 | E74: 480 | F74: Fedex 3.0kg | G74: https://www.ebay.com/sch/i.html?_nkw=FFXIV%20Exarch%20Cane%20necklace&_sacat=0&_from=R40&_sop=15&rt=nc | H74: https://jp.mercari.com/item/m41767889232 | N74: https://jp.mercari.com/search?keyword=FF14%20%E3%82%A8%E3%82%AE%20%E6%B0%B4%E6%99%B6%E5%85%AC%20%E3%83%8D%E3%83%83%E3%82%AF%E3%83%AC%E3%82%B9&price_min=10000&sort=price&order=asc&status=on_sale | O74: https://fril.jp/s?query=FF14%20%E3%82%A8%E3%82%AE%20%E6%B0%B4%E6%99%B6%E5%85%AC%20%E3%83%8D%E3%83%83%E3%82%AF%E3%83%AC%E3%82%B9&min=10000&transaction=selling | P74: https://search.rakuten.co.jp/search/mall/FF14%20%E3%82%A8%E3%82%AE%20%E6%B0%B4%E6%99%B6%E5%85%AC%20%E3%83%8D%E3%83%83%E3%82%AF%E3%83%AC%E3%82%B9/?min=10000 | Q74: https://auctions.yahoo.co.jp/search/search?p=FF14%20%E3%82%A8%E3%82%AE%20%E6%B0%B4%E6%99%B6%E5%85%AC%20%E3%83%8D%E3%83%83%E3%82%AF%E3%83%AC%E3%82%B9&aucminprice=10000 | R74: https://shopping.yahoo.co.jp/search/FF14%20%E3%82%A8%E3%82%AE%20%E6%B0%B4%E6%99%B6%E5%85%AC%20%E3%83%8D%E3%83%83%E3%82%AF%E3%83%AC%E3%82%B9/0/?pf=10000
A75: 1731 | B75: [未開封]ワンピース WCF ストロングワールド ver.3 & 4 全16品 | C75: 1 | D75: 99999 | E75: 1100 | F75: Fedex 3.5kg | G75: https://www.ebay.com/sch/i.html?_nkw=One%20Piece%20WCF%20Strong%20World&_sacat=0&_from=R40&_sop=15&rt=nc | H75: https://jp.mercari.com/item/m81646596389 | I75: https://paypayfleamarket.yahoo.co.jp/item/z623565928 | N75: https://jp.mercari.com/search?keyword=%E3%83%AF%E3%83%B3%E3%83%94%E3%83%BC%E3%82%B9%20WCF%20%E3%82%B9%E3%83%88%E3%83%AD%E3%83%B3%E3%82%B0%E3%83%AF%E3%83%BC%E3%83%AB%E3%83%89&price_min=10000&sort=price&order=asc&status=on_sale | O75: https://fril.jp/s?query=%E3%83%AF%E3%83%B3%E3%83%94%E3%83%BC%E3%82%B9%20WCF%20%E3%82%B9%E3%83%88%E3%83%AD%E3%83%B3%E3%82%B0%E3%83%AF%E3%83%BC%E3%83%AB%E3%83%89&min=10000&transaction=selling | P75: https://search.rakuten.co.jp/search/mall/%E3%83%AF%E3%83%B3%E3%83%94%E3%83%BC%E3%82%B9%20WCF%20%E3%82%B9%E3%83%88%E3%83%AD%E3%83%B3%E3%82%B0%E3%83%AF%E3%83%BC%E3%83%AB%E3%83%89/?min=10000 | Q75: https://auctions.yahoo.co.jp/search/search?p=%E3%83%AF%E3%83%B3%E3%83%94%E3%83%BC%E3%82%B9%20WCF%20%E3%82%B9%E3%83%88%E3%83%AD%E3%83%B3%E3%82%B0%E3%83%AF%E3%83%BC%E3%83%AB%E3%83%89&aucminprice=10000 | R75: https://shopping.yahoo.co.jp/search/%E3%83%AF%E3%83%B3%E3%83%94%E3%83%BC%E3%82%B9%20WCF%20%E3%82%B9%E3%83%88%E3%83%AD%E3%83%B3%E3%82%B0%E3%83%AF%E3%83%BC%E3%83%AB%E3%83%89/0/?pf=10000
A76: 1732 | B76: 東京ワンピースタワー 限定 ワールドコレクタブ... | C76: 1 | D76: 56000 | E76: 690 | F76: Fedex 3.5kg | G76: https://www.ebay.com/sch/i.html?_nkw=One%20Piece%20WCF%20Tower%20limited&_sacat=0&_from=R40&_sop=15&rt=nc | H76: https://page.auctions.yahoo.co.jp/jp/auction/x1239786128 | N76: https://jp.mercari.com/search?keyword=%E3%83%AF%E3%83%B3%E3%83%94%E3%83%BC%E3%82%B9%20%E3%83%AF%E3%83%BC%E3%82%B3%E3%83%AC%20%E3%83%AF%E3%83%B3%E3%83%94%E3%83%BC%E3%82%B9%E3%82%BF%E3%83%AF%E3%83%BC%20%E9%99%90%E5%AE%9A&price_min=10000&sort=price&order=asc&status=on_sale | O76: https://fril.jp/s?query=%E3%83%AF%E3%83%B3%E3%83%94%E3%83%BC%E3%82%B9%20%E3%83%AF%E3%83%BC%E3%82%B3%E3%83%AC%20%E3%83%AF%E3%83%B3%E3%83%94%E3%83%BC%E3%82%B9%E3%82%BF%E3%83%AF%E3%83%BC%20%E9%99%90%E5%AE%9A&min=10000&transaction=selling | P76: https://search.rakuten.co.jp/search/mall/%E3%83%AF%E3%83%B3%E3%83%94%E3%83%BC%E3%82%B9%20%E3%83%AF%E3%83%BC%E3%82%B3%E3%83%AC%20%E3%83%AF%E3%83%B3%E3%83%94%E3%83%BC%E3%82%B9%E3%82%BF%E3%83%AF%E3%83%BC%20%E9%99%90%E5%AE%9A/?min=10000 | Q76: https://auctions.yahoo.co.jp/search/search?p=%E3%83%AF%E3%83%B3%E3%83%94%E3%83%BC%E3%82%B9%20%E3%83%AF%E3%83%BC%E3%82%B3%E3%83%AC%20%E3%83%AF%E3%83%B3%E3%83%94%E3%83%BC%E3%82%B9%E3%82%BF%E3%83%AF%E3%83%BC%20%E9%99%90%E5%AE%9A&aucminprice=10000 | R76: https://shopping.yahoo.co.jp/search/%E3%83%AF%E3%83%B3%E3%83%94%E3%83%BC%E3%82%B9%20%E3%83%AF%E3%83%BC%E3%82%B3%E3%83%AC%20%E3%83%AF%E3%83%B3%E3%83%94%E3%83%BC%E3%82%B9%E3%82%BF%E3%83%AF%E3%83%BC%20%E9%99%90%E5%AE%9A/0/?pf=10000
A77: 1733 | B77: 【激レア】 カイロレン 修復版 ヘルメット シスの復讐 レプリカ スターウォーズ | C77: 1 | D77: 85000 | E77: 1020 | F77: Fedex 8.0kg | G77: https://www.ebay.com/sch/i.html?_nkw=Star%20Wars%20Kylo%20Ren%20helmet%20replica&_sacat=0&_from=R40&_sop=15&rt=nc | H77: https://paypayfleamarket.yahoo.co.jp/item/z658763990 | I77: https://jp.mercari.com/item/m41121962404 | N77: https://jp.mercari.com/search?keyword=%E3%82%B9%E3%82%BF%E3%83%BC%E3%82%A6%E3%82%A9%E3%83%BC%E3%82%BA%20%E3%82%AB%E3%82%A4%E3%83%AD%E3%83%AC%E3%83%B3%20%E3%83%98%E3%83%AB%E3%83%A1%E3%83%83%E3%83%88%20%E3%83%AC%E3%83%97%E3%83%AA%E3%82%AB&price_min=10000&sort=price&order=asc&status=on_sale | O77: https://fril.jp/s?query=%E3%82%B9%E3%82%BF%E3%83%BC%E3%82%A6%E3%82%A9%E3%83%BC%E3%82%BA%20%E3%82%AB%E3%82%A4%E3%83%AD%E3%83%AC%E3%83%B3%20%E3%83%98%E3%83%AB%E3%83%A1%E3%83%83%E3%83%88%20%E3%83%AC%E3%83%97%E3%83%AA%E3%82%AB&min=10000&transaction=selling | P77: https://search.rakuten.co.jp/search/mall/%E3%82%B9%E3%82%BF%E3%83%BC%E3%82%A6%E3%82%A9%E3%83%BC%E3%82%BA%20%E3%82%AB%E3%82%A4%E3%83%AD%E3%83%AC%E3%83%B3%20%E3%83%98%E3%83%AB%E3%83%A1%E3%83%83%E3%83%88%20%E3%83%AC%E3%83%97%E3%83%AA%E3%82%AB/?min=10000 | Q77: https://auctions.yahoo.co.jp/search/search?p=%E3%82%B9%E3%82%BF%E3%83%BC%E3%82%A6%E3%82%A9%E3%83%BC%E3%82%BA%20%E3%82%AB%E3%82%A4%E3%83%AD%E3%83%AC%E3%83%B3%20%E3%83%98%E3%83%AB%E3%83%A1%E3%83%83%E3%83%88%20%E3%83%AC%E3%83%97%E3%83%AA%E3%82%AB&aucminprice=10000 | R77: https://shopping.yahoo.co.jp/search/%E3%82%B9%E3%82%BF%E3%83%BC%E3%82%A6%E3%82%A9%E3%83%BC%E3%82%BA%20%E3%82%AB%E3%82%A4%E3%83%AD%E3%83%AC%E3%83%B3%20%E3%83%98%E3%83%AB%E3%83%A1%E3%83%83%E3%83%88%20%E3%83%AC%E3%83%97%E3%83%AA%E3%82%AB/0/?pf=10000
A78: 1734 | B78: 限定★未使用 SONIC ソニックアドベンチャー フィギュア 11inch | C78: 1 | D78: 46800 | E78: 640 | F78: Fedex 3.0kg | G78: https://www.ebay.com/sch/i.html?_nkw=Sonic%20Adventure%2011%20inch%20figure&_sacat=0&_from=R40&_sop=15&rt=nc | H78: https://jp.mercari.com/item/m32348398046 | I78: https://jp.mercari.com/item/m37761206323 | N78: https://jp.mercari.com/search?keyword=%E3%82%BD%E3%83%8B%E3%83%83%E3%82%AF%E3%82%A2%E3%83%89%E3%83%99%E3%83%B3%E3%83%81%E3%83%A3%E3%83%BC%20%E3%83%95%E3%82%A3%E3%82%AE%E3%83%A5%E3%82%A2%2011%E3%82%A4%E3%83%B3%E3%83%81&price_min=10000&sort=price&order=asc&status=on_sale | O78: https://fril.jp/s?query=%E3%82%BD%E3%83%8B%E3%83%83%E3%82%AF%E3%82%A2%E3%83%89%E3%83%99%E3%83%B3%E3%83%81%E3%83%A3%E3%83%BC%20%E3%83%95%E3%82%A3%E3%82%AE%E3%83%A5%E3%82%A2%2011%E3%82%A4%E3%83%B3%E3%83%81&min=10000&transaction=selling | P78: https://search.rakuten.co.jp/search/mall/%E3%82%BD%E3%83%8B%E3%83%83%E3%82%AF%E3%82%A2%E3%83%89%E3%83%99%E3%83%B3%E3%83%81%E3%83%A3%E3%83%BC%20%E3%83%95%E3%82%A3%E3%82%AE%E3%83%A5%E3%82%A2%2011%E3%82%A4%E3%83%B3%E3%83%81/?min=10000 | Q78: https://auctions.yahoo.co.jp/search/search?p=%E3%82%BD%E3%83%8B%E3%83%83%E3%82%AF%E3%82%A2%E3%83%89%E3%83%99%E3%83%B3%E3%83%81%E3%83%A3%E3%83%BC%20%E3%83%95%E3%82%A3%E3%82%AE%E3%83%A5%E3%82%A2%2011%E3%82%A4%E3%83%B3%E3%83%81&aucminprice=10000 | R78: https://shopping.yahoo.co.jp/search/%E3%82%BD%E3%83%8B%E3%83%83%E3%82%AF%E3%82%A2%E3%83%89%E3%83%99%E3%83%B3%E3%83%81%E3%83%A3%E3%83%BC%20%E3%83%95%E3%82%A3%E3%82%AE%E3%83%A5%E3%82%A2%2011%E3%82%A4%E3%83%B3%E3%83%81/0/?pf=10000
A79: 1735 | B79: LEGEND CONSUMER SERIES「サマーカーニバル'92 烈火」フ… | C79: 1 | D79: 16000 | E79: 319 | F79: Fedex 0.5kg | G79: https://www.ebay.com/sch/i.html?_nkw=Summer%20Carnival%2092%20Recca%20Famicom&_sacat=0&_from=R40&_sop=15&rt=nc | H79: https://auctions.yahoo.co.jp/jp/auction/t1222924100 | N79: https://jp.mercari.com/search?keyword=%E3%82%B5%E3%83%9E%E3%83%BC%E3%82%AB%E3%83%BC%E3%83%8B%E3%83%90%E3%83%AB%2092%20%E7%83%88%E7%81%AB%20%E3%83%95%E3%82%A1%E3%83%9F%E3%82%B3%E3%83%B3&price_min=10000&sort=price&order=asc&status=on_sale | O79: https://fril.jp/s?query=%E3%82%B5%E3%83%9E%E3%83%BC%E3%82%AB%E3%83%BC%E3%83%8B%E3%83%90%E3%83%AB%2092%20%E7%83%88%E7%81%AB%20%E3%83%95%E3%82%A1%E3%83%9F%E3%82%B3%E3%83%B3&min=10000&transaction=selling | P79: https://search.rakuten.co.jp/search/mall/%E3%82%B5%E3%83%9E%E3%83%BC%E3%82%AB%E3%83%BC%E3%83%8B%E3%83%90%E3%83%AB%2092%20%E7%83%88%E7%81%AB%20%E3%83%95%E3%82%A1%E3%83%9F%E3%82%B3%E3%83%B3/?min=10000 | Q79: https://auctions.yahoo.co.jp/search/search?p=%E3%82%B5%E3%83%9E%E3%83%BC%E3%82%AB%E3%83%BC%E3%83%8B%E3%83%90%E3%83%AB%2092%20%E7%83%88%E7%81%AB%20%E3%83%95%E3%82%A1%E3%83%9F%E3%82%B3%E3%83%B3&aucminprice=10000 | R79: https://shopping.yahoo.co.jp/search/%E3%82%B5%E3%83%9E%E3%83%BC%E3%82%AB%E3%83%BC%E3%83%8B%E3%83%90%E3%83%AB%2092%20%E7%83%88%E7%81%AB%20%E3%83%95%E3%82%A1%E3%83%9F%E3%82%B3%E3%83%B3/0/?pf=10000
A80: 1736 | B80: 現状品 Tシャツ 未開封 未使用品 ファミコン ナ... | C80: 1 | D80: 29800 | E80: 399 | F80: Fedex 0.5kg | G80: https://www.ebay.com/sch/i.html?_nkw=Summer%20Carnival%20Recca%20t-shirt&_sacat=0&_from=R40&_sop=15&rt=nc | H80: https://page.auctions.yahoo.co.jp/jp/auction/u1223180449 | N80: https://jp.mercari.com/search?keyword=%E3%82%B5%E3%83%9E%E3%83%BC%E3%82%AB%E3%83%BC%E3%83%8B%E3%83%90%E3%83%AB%20%E7%83%88%E7%81%AB%20T%E3%82%B7%E3%83%A3%E3%83%84&price_min=10000&sort=price&order=asc&status=on_sale | O80: https://fril.jp/s?query=%E3%82%B5%E3%83%9E%E3%83%BC%E3%82%AB%E3%83%BC%E3%83%8B%E3%83%90%E3%83%AB%20%E7%83%88%E7%81%AB%20T%E3%82%B7%E3%83%A3%E3%83%84&min=10000&transaction=selling | P80: https://search.rakuten.co.jp/search/mall/%E3%82%B5%E3%83%9E%E3%83%BC%E3%82%AB%E3%83%BC%E3%83%8B%E3%83%90%E3%83%AB%20%E7%83%88%E7%81%AB%20T%E3%82%B7%E3%83%A3%E3%83%84/?min=10000 | Q80: https://auctions.yahoo.co.jp/search/search?p=%E3%82%B5%E3%83%9E%E3%83%BC%E3%82%AB%E3%83%BC%E3%83%8B%E3%83%90%E3%83%AB%20%E7%83%88%E7%81%AB%20T%E3%82%B7%E3%83%A3%E3%83%84&aucminprice=10000 | R80: https://shopping.yahoo.co.jp/search/%E3%82%B5%E3%83%9E%E3%83%BC%E3%82%AB%E3%83%BC%E3%83%8B%E3%83%90%E3%83%AB%20%E7%83%88%E7%81%AB%20T%E3%82%B7%E3%83%A3%E3%83%84/0/?pf=10000
A81: 1737 | B81: 川久保玲とコムデギャルソン マガジンハウス 91... | C81: 1 | D81: 27600 | E81: 398 | F81: Fedex 3.5kg | G81: https://www.ebay.com/sch/i.html?_nkw=Rei%20Kawakubo%20Comme%20des%20Garcons%20book&_sacat=0&_from=R40&_sop=15&rt=nc | H81: https://jp.mercari.com/item/m32016336942 | I81: https://auctions.yahoo.co.jp/jp/auction/r1235106500 | N81: https://jp.mercari.com/search?keyword=%E5%B7%9D%E4%B9%85%E4%BF%9D%E7%8E%B2%20%E3%82%B3%E3%83%A0%E3%83%87%E3%82%AE%E3%83%A3%E3%83%AB%E3%82%BD%E3%83%B3%20%E3%83%9E%E3%82%AC%E3%82%B8%E3%83%B3%E3%83%8F%E3%82%A6%E3%82%B9&price_min=10000&sort=price&order=asc&status=on_sale | O81: https://fril.jp/s?query=%E5%B7%9D%E4%B9%85%E4%BF%9D%E7%8E%B2%20%E3%82%B3%E3%83%A0%E3%83%87%E3%82%AE%E3%83%A3%E3%83%AB%E3%82%BD%E3%83%B3%20%E3%83%9E%E3%82%AC%E3%82%B8%E3%83%B3%E3%83%8F%E3%82%A6%E3%82%B9&min=10000&transaction=selling | P81: https://search.rakuten.co.jp/search/mall/%E5%B7%9D%E4%B9%85%E4%BF%9D%E7%8E%B2%20%E3%82%B3%E3%83%A0%E3%83%87%E3%82%AE%E3%83%A3%E3%83%AB%E3%82%BD%E3%83%B3%20%E3%83%9E%E3%82%AC%E3%82%B8%E3%83%B3%E3%83%8F%E3%82%A6%E3%82%B9/?min=10000 | Q81: https://auctions.yahoo.co.jp/search/search?p=%E5%B7%9D%E4%B9%85%E4%BF%9D%E7%8E%B2%20%E3%82%B3%E3%83%A0%E3%83%87%E3%82%AE%E3%83%A3%E3%83%AB%E3%82%BD%E3%83%B3%20%E3%83%9E%E3%82%AC%E3%82%B8%E3%83%B3%E3%83%8F%E3%82%A6%E3%82%B9&aucminprice=10000 | R81: https://shopping.yahoo.co.jp/search/%E5%B7%9D%E4%B9%85%E4%BF%9D%E7%8E%B2%20%E3%82%B3%E3%83%A0%E3%83%87%E3%82%AE%E3%83%A3%E3%83%AB%E3%82%BD%E3%83%B3%20%E3%83%9E%E3%82%AC%E3%82%B8%E3%83%B3%E3%83%8F%E3%82%A6%E3%82%B9/0/?pf=10000
A82: 1738 | B82: 【中古】開封）SHODO SUPER 電子戦隊デンジマン[24] | C82: 1 | D82: 17710 | E82: 230 | F82: Fedex 0.5kg | G82: https://www.ebay.com/sch/i.html?_nkw=SHODO%20SUPER%20Denziman&_sacat=0&_from=R40&_sop=15&rt=nc | H82: https://jp.mercari.com/shops/product/2JV3gbY9pjyQjbj7gnBTku | N82: https://jp.mercari.com/search?keyword=SHODO%20SUPER%20%E9%9B%BB%E5%AD%90%E6%88%A6%E9%9A%8A%E3%83%87%E3%83%B3%E3%82%B8%E3%83%9E%E3%83%B3&price_min=10000&sort=price&order=asc&status=on_sale | O82: https://fril.jp/s?query=SHODO%20SUPER%20%E9%9B%BB%E5%AD%90%E6%88%A6%E9%9A%8A%E3%83%87%E3%83%B3%E3%82%B8%E3%83%9E%E3%83%B3&min=10000&transaction=selling | P82: https://search.rakuten.co.jp/search/mall/SHODO%20SUPER%20%E9%9B%BB%E5%AD%90%E6%88%A6%E9%9A%8A%E3%83%87%E3%83%B3%E3%82%B8%E3%83%9E%E3%83%B3/?min=10000 | Q82: https://auctions.yahoo.co.jp/search/search?p=SHODO%20SUPER%20%E9%9B%BB%E5%AD%90%E6%88%A6%E9%9A%8A%E3%83%87%E3%83%B3%E3%82%B8%E3%83%9E%E3%83%B3&aucminprice=10000 | R82: https://shopping.yahoo.co.jp/search/SHODO%20SUPER%20%E9%9B%BB%E5%AD%90%E6%88%A6%E9%9A%8A%E3%83%87%E3%83%B3%E3%82%B8%E3%83%9E%E3%83%B3/0/?pf=10000
A83: 1739 | B83: アートストーム / EX合金 / ゲッター2 ジャガー リーペイント Ver | C83: 1 | D83: 39600 | E83: 559 | F83: Fedex 6.0kg | G83: https://www.ebay.com/sch/i.html?_nkw=EX%20Gokin%20Getter%202%20repaint&_sacat=0&_from=R40&_sop=15&rt=nc | H83: https://jp.mercari.com/item/m84647861167 | I83: https://jp.mercari.com/shops/product/nybfxjjBpGH4mzirwBGbhb | N83: https://jp.mercari.com/search?keyword=EX%E5%90%88%E9%87%91%20%E3%82%B2%E3%83%83%E3%82%BF%E3%83%BC2%20%E3%82%B8%E3%83%A3%E3%82%AC%E3%83%BC%20%E3%83%AA%E3%83%9A%E3%82%A4%E3%83%B3%E3%83%88&price_min=10000&sort=price&order=asc&status=on_sale | O83: https://fril.jp/s?query=EX%E5%90%88%E9%87%91%20%E3%82%B2%E3%83%83%E3%82%BF%E3%83%BC2%20%E3%82%B8%E3%83%A3%E3%82%AC%E3%83%BC%20%E3%83%AA%E3%83%9A%E3%82%A4%E3%83%B3%E3%83%88&min=10000&transaction=selling | P83: https://search.rakuten.co.jp/search/mall/EX%E5%90%88%E9%87%91%20%E3%82%B2%E3%83%83%E3%82%BF%E3%83%BC2%20%E3%82%B8%E3%83%A3%E3%82%AC%E3%83%BC%20%E3%83%AA%E3%83%9A%E3%82%A4%E3%83%B3%E3%83%88/?min=10000 | Q83: https://auctions.yahoo.co.jp/search/search?p=EX%E5%90%88%E9%87%91%20%E3%82%B2%E3%83%83%E3%82%BF%E3%83%BC2%20%E3%82%B8%E3%83%A3%E3%82%AC%E3%83%BC%20%E3%83%AA%E3%83%9A%E3%82%A4%E3%83%B3%E3%83%88&aucminprice=10000 | R83: https://shopping.yahoo.co.jp/search/EX%E5%90%88%E9%87%91%20%E3%82%B2%E3%83%83%E3%82%BF%E3%83%BC2%20%E3%82%B8%E3%83%A3%E3%82%AC%E3%83%BC%20%E3%83%AA%E3%83%9A%E3%82%A4%E3%83%B3%E3%83%88/0/?pf=10000
A84: 1740 | B84: 新品未開封 激レアEX合金ウルトラホーク3号 ウルトラセブン フューチャーモデル | C84: 1 | D84: 38600 | E84: 500 | F84: Fedex 2.0kg | G84: https://www.ebay.com/sch/i.html?_nkw=EX%20Gokin%20Ultra%20Hawk%203&_sacat=0&_from=R40&_sop=15&rt=nc | H84: https://jp.mercari.com/shops/product/2JTbWJSoRRQkyycbpeVNiL | I84: https://jp.mercari.com/shops/product/2JU2pYCneApF75ZDNoV4qg | J84: https://jp.mercari.com/shops/product/2JTp8fmkK8jYEct5AcjHvm | N84: https://jp.mercari.com/search?keyword=EX%E5%90%88%E9%87%91%20%E3%82%A6%E3%83%AB%E3%83%88%E3%83%A9%E3%83%9B%E3%83%BC%E3%82%AF3%E5%8F%B7&price_min=10000&sort=price&order=asc&status=on_sale | O84: https://fril.jp/s?query=EX%E5%90%88%E9%87%91%20%E3%82%A6%E3%83%AB%E3%83%88%E3%83%A9%E3%83%9B%E3%83%BC%E3%82%AF3%E5%8F%B7&min=10000&transaction=selling | P84: https://search.rakuten.co.jp/search/mall/EX%E5%90%88%E9%87%91%20%E3%82%A6%E3%83%AB%E3%83%88%E3%83%A9%E3%83%9B%E3%83%BC%E3%82%AF3%E5%8F%B7/?min=10000 | Q84: https://auctions.yahoo.co.jp/search/search?p=EX%E5%90%88%E9%87%91%20%E3%82%A6%E3%83%AB%E3%83%88%E3%83%A9%E3%83%9B%E3%83%BC%E3%82%AF3%E5%8F%B7&aucminprice=10000 | R84: https://shopping.yahoo.co.jp/search/EX%E5%90%88%E9%87%91%20%E3%82%A6%E3%83%AB%E3%83%88%E3%83%A9%E3%83%9B%E3%83%BC%E3%82%AF3%E5%8F%B7/0/?pf=10000
A85: 1741 | B85: ウルトラセブン ウルトラセブン ウルトラホーク1号 EX合金 アートストーム | C85: 1 | D85: 34000 | E85: 480 | F85: Fedex 2.0kg | G85: https://www.ebay.com/sch/i.html?_nkw=EX%20Gokin%20Ultra%20Hawk%201&_sacat=0&_from=R40&_sop=15&rt=nc | H85: https://jp.mercari.com/shops/product/2JVJwKGGadBFBsEz3KXdwA | N85: https://jp.mercari.com/search?keyword=EX%E5%90%88%E9%87%91%20%E3%82%A6%E3%83%AB%E3%83%88%E3%83%A9%E3%83%9B%E3%83%BC%E3%82%AF1%E5%8F%B7&price_min=10000&sort=price&order=asc&status=on_sale | O85: https://fril.jp/s?query=EX%E5%90%88%E9%87%91%20%E3%82%A6%E3%83%AB%E3%83%88%E3%83%A9%E3%83%9B%E3%83%BC%E3%82%AF1%E5%8F%B7&min=10000&transaction=selling | P85: https://search.rakuten.co.jp/search/mall/EX%E5%90%88%E9%87%91%20%E3%82%A6%E3%83%AB%E3%83%88%E3%83%A9%E3%83%9B%E3%83%BC%E3%82%AF1%E5%8F%B7/?min=10000 | Q85: https://auctions.yahoo.co.jp/search/search?p=EX%E5%90%88%E9%87%91%20%E3%82%A6%E3%83%AB%E3%83%88%E3%83%A9%E3%83%9B%E3%83%BC%E3%82%AF1%E5%8F%B7&aucminprice=10000 | R85: https://shopping.yahoo.co.jp/search/EX%E5%90%88%E9%87%91%20%E3%82%A6%E3%83%AB%E3%83%88%E3%83%A9%E3%83%9B%E3%83%BC%E3%82%AF1%E5%8F%B7/0/?pf=10000
A86: 1742 | B86: FEWTURE MODELS EX合金 マジンガー1969 永井豪原作カラー | C86: 1 | D86: 23000 | E86: 490 | F86: Fedex 6.0kg | G86: https://www.ebay.com/sch/i.html?_nkw=EX%20Gokin%20Mazinger%201969&_sacat=0&_from=R40&_sop=15&rt=nc | H86: https://jp.mercari.com/item/m57644556706 | I86: https://jp.mercari.com/shops/product/2JNey5ontYvKmyQB9ruhSu | N86: https://jp.mercari.com/search?keyword=EX%E5%90%88%E9%87%91%20%E3%83%9E%E3%82%B8%E3%83%B3%E3%82%AC%E3%83%BC%201969%20%E5%8E%9F%E4%BD%9C%E3%82%AB%E3%83%A9%E3%83%BC&price_min=10000&sort=price&order=asc&status=on_sale | O86: https://fril.jp/s?query=EX%E5%90%88%E9%87%91%20%E3%83%9E%E3%82%B8%E3%83%B3%E3%82%AC%E3%83%BC%201969%20%E5%8E%9F%E4%BD%9C%E3%82%AB%E3%83%A9%E3%83%BC&min=10000&transaction=selling | P86: https://search.rakuten.co.jp/search/mall/EX%E5%90%88%E9%87%91%20%E3%83%9E%E3%82%B8%E3%83%B3%E3%82%AC%E3%83%BC%201969%20%E5%8E%9F%E4%BD%9C%E3%82%AB%E3%83%A9%E3%83%BC/?min=10000 | Q86: https://auctions.yahoo.co.jp/search/search?p=EX%E5%90%88%E9%87%91%20%E3%83%9E%E3%82%B8%E3%83%B3%E3%82%AC%E3%83%BC%201969%20%E5%8E%9F%E4%BD%9C%E3%82%AB%E3%83%A9%E3%83%BC&aucminprice=10000 | R86: https://shopping.yahoo.co.jp/search/EX%E5%90%88%E9%87%91%20%E3%83%9E%E3%82%B8%E3%83%B3%E3%82%AC%E3%83%BC%201969%20%E5%8E%9F%E4%BD%9C%E3%82%AB%E3%83%A9%E3%83%BC/0/?pf=10000
A87: 1743 | B87: ViXion2 | C87: 1 | D87: 90000 | E87: 980 | F87: Fedex 0.5kg | G87: https://www.ebay.com/sch/i.html?_nkw=ViXion2%20auto%20focus%20eyewear&_sacat=0&_from=R40&_sop=15&rt=nc | H87: https://jp.mercari.com/item/m11961995450 | N87: https://jp.mercari.com/search?keyword=ViXion2%20%E3%82%AA%E3%83%BC%E3%83%88%E3%83%95%E3%82%A9%E3%83%BC%E3%82%AB%E3%82%B9%E3%82%A2%E3%82%A4%E3%82%A6%E3%82%A7%E3%82%A2&price_min=10000&sort=price&order=asc&status=on_sale | O87: https://fril.jp/s?query=ViXion2%20%E3%82%AA%E3%83%BC%E3%83%88%E3%83%95%E3%82%A9%E3%83%BC%E3%82%AB%E3%82%B9%E3%82%A2%E3%82%A4%E3%82%A6%E3%82%A7%E3%82%A2&min=10000&transaction=selling | P87: https://search.rakuten.co.jp/search/mall/ViXion2%20%E3%82%AA%E3%83%BC%E3%83%88%E3%83%95%E3%82%A9%E3%83%BC%E3%82%AB%E3%82%B9%E3%82%A2%E3%82%A4%E3%82%A6%E3%82%A7%E3%82%A2/?min=10000 | Q87: https://auctions.yahoo.co.jp/search/search?p=ViXion2%20%E3%82%AA%E3%83%BC%E3%83%88%E3%83%95%E3%82%A9%E3%83%BC%E3%82%AB%E3%82%B9%E3%82%A2%E3%82%A4%E3%82%A6%E3%82%A7%E3%82%A2&aucminprice=10000 | R87: https://shopping.yahoo.co.jp/search/ViXion2%20%E3%82%AA%E3%83%BC%E3%83%88%E3%83%95%E3%82%A9%E3%83%BC%E3%82%AB%E3%82%B9%E3%82%A2%E3%82%A4%E3%82%A6%E3%82%A7%E3%82%A2/0/?pf=10000
A88: 1744 | B88: オートフォーカスアイウェア ViXion01S | C88: 1 | D88: 34500 | E88: 430 | F88: Fedex 0.5kg | G88: https://www.ebay.com/sch/i.html?_nkw=ViXion%2001S%20auto%20focus%20eyewear&_sacat=0&_from=R40&_sop=15&rt=nc | H88: https://auctions.yahoo.co.jp/jp/auction/x1237668220 | I88: https://jp.mercari.com/item/m59346030203 | N88: https://jp.mercari.com/search?keyword=ViXion01S%20%E3%82%AA%E3%83%BC%E3%83%88%E3%83%95%E3%82%A9%E3%83%BC%E3%82%AB%E3%82%B9%E3%82%A2%E3%82%A4%E3%82%A6%E3%82%A7%E3%82%A2&price_min=10000&sort=price&order=asc&status=on_sale | O88: https://fril.jp/s?query=ViXion01S%20%E3%82%AA%E3%83%BC%E3%83%88%E3%83%95%E3%82%A9%E3%83%BC%E3%82%AB%E3%82%B9%E3%82%A2%E3%82%A4%E3%82%A6%E3%82%A7%E3%82%A2&min=10000&transaction=selling | P88: https://search.rakuten.co.jp/search/mall/ViXion01S%20%E3%82%AA%E3%83%BC%E3%83%88%E3%83%95%E3%82%A9%E3%83%BC%E3%82%AB%E3%82%B9%E3%82%A2%E3%82%A4%E3%82%A6%E3%82%A7%E3%82%A2/?min=10000 | Q88: https://auctions.yahoo.co.jp/search/search?p=ViXion01S%20%E3%82%AA%E3%83%BC%E3%83%88%E3%83%95%E3%82%A9%E3%83%BC%E3%82%AB%E3%82%B9%E3%82%A2%E3%82%A4%E3%82%A6%E3%82%A7%E3%82%A2&aucminprice=10000 | R88: https://shopping.yahoo.co.jp/search/ViXion01S%20%E3%82%AA%E3%83%BC%E3%83%88%E3%83%95%E3%82%A9%E3%83%BC%E3%82%AB%E3%82%B9%E3%82%A2%E3%82%A4%E3%82%A6%E3%82%A7%E3%82%A2/0/?pf=10000
A89: 1745 | B89: hololive 4th fes. ライブ生写真 コンプリート | C89: 1 | D89: 30000 | E89: 399 | F89: Fedex 1.0kg | G89: https://www.ebay.com/sch/i.html?_nkw=hololive%204th%20fes%20bromide&_sacat=0&_from=R40&_sop=15&rt=nc | H89: https://jp.mercari.com/item/m84897636100 | N89: https://jp.mercari.com/search?keyword=hololive%204th%20fes%20%E7%94%9F%E5%86%99%E7%9C%9F&price_min=10000&sort=price&order=asc&status=on_sale | O89: https://fril.jp/s?query=hololive%204th%20fes%20%E7%94%9F%E5%86%99%E7%9C%9F&min=10000&transaction=selling | P89: https://search.rakuten.co.jp/search/mall/hololive%204th%20fes%20%E7%94%9F%E5%86%99%E7%9C%9F/?min=10000 | Q89: https://auctions.yahoo.co.jp/search/search?p=hololive%204th%20fes%20%E7%94%9F%E5%86%99%E7%9C%9F&aucminprice=10000 | R89: https://shopping.yahoo.co.jp/search/hololive%204th%20fes%20%E7%94%9F%E5%86%99%E7%9C%9F/0/?pf=10000
A90: 1746 | B90: UNDONE ホロライブ 大空スバル 腕時計 置き時計セット | C90: 1 | D90: 79999 | E90: 870 | F90: Fedex 1.0kg | G90: https://www.ebay.com/sch/i.html?_nkw=UNDONE%20hololive%20Subaru%20watch&_sacat=0&_from=R40&_sop=15&rt=nc | H90: https://jp.mercari.com/item/m18111562559 | N90: https://jp.mercari.com/search?keyword=UNDONE%20%E3%83%9B%E3%83%AD%E3%83%A9%E3%82%A4%E3%83%96%20%E5%A4%A7%E7%A9%BA%E3%82%B9%E3%83%90%E3%83%AB%20%E8%85%95%E6%99%82%E8%A8%88&price_min=10000&sort=price&order=asc&status=on_sale | O90: https://fril.jp/s?query=UNDONE%20%E3%83%9B%E3%83%AD%E3%83%A9%E3%82%A4%E3%83%96%20%E5%A4%A7%E7%A9%BA%E3%82%B9%E3%83%90%E3%83%AB%20%E8%85%95%E6%99%82%E8%A8%88&min=10000&transaction=selling | P90: https://search.rakuten.co.jp/search/mall/UNDONE%20%E3%83%9B%E3%83%AD%E3%83%A9%E3%82%A4%E3%83%96%20%E5%A4%A7%E7%A9%BA%E3%82%B9%E3%83%90%E3%83%AB%20%E8%85%95%E6%99%82%E8%A8%88/?min=10000 | Q90: https://auctions.yahoo.co.jp/search/search?p=UNDONE%20%E3%83%9B%E3%83%AD%E3%83%A9%E3%82%A4%E3%83%96%20%E5%A4%A7%E7%A9%BA%E3%82%B9%E3%83%90%E3%83%AB%20%E8%85%95%E6%99%82%E8%A8%88&aucminprice=10000 | R90: https://shopping.yahoo.co.jp/search/UNDONE%20%E3%83%9B%E3%83%AD%E3%83%A9%E3%82%A4%E3%83%96%20%E5%A4%A7%E7%A9%BA%E3%82%B9%E3%83%90%E3%83%AB%20%E8%85%95%E6%99%82%E8%A8%88/0/?pf=10000
A91: 1747 | B91: コープスブライド レコード アナログ サントラ サウンドトラック 映画 | C91: 1 | D91: 28000 | E91: 380 | F91: Fedex 1.0kg | G91: https://www.ebay.com/sch/i.html?_nkw=Corpse%20Bride%20soundtrack%20LP&_sacat=0&_from=R40&_sop=15&rt=nc | H91: https://jp.mercari.com/item/m31765099863 | N91: https://jp.mercari.com/search?keyword=%E3%82%B3%E3%83%BC%E3%83%97%E3%82%B9%E3%83%96%E3%83%A9%E3%82%A4%E3%83%89%20%E3%82%B5%E3%83%B3%E3%83%88%E3%83%A9%20%E3%83%AC%E3%82%B3%E3%83%BC%E3%83%89&price_min=10000&sort=price&order=asc&status=on_sale | O91: https://fril.jp/s?query=%E3%82%B3%E3%83%BC%E3%83%97%E3%82%B9%E3%83%96%E3%83%A9%E3%82%A4%E3%83%89%20%E3%82%B5%E3%83%B3%E3%83%88%E3%83%A9%20%E3%83%AC%E3%82%B3%E3%83%BC%E3%83%89&min=10000&transaction=selling | P91: https://search.rakuten.co.jp/search/mall/%E3%82%B3%E3%83%BC%E3%83%97%E3%82%B9%E3%83%96%E3%83%A9%E3%82%A4%E3%83%89%20%E3%82%B5%E3%83%B3%E3%83%88%E3%83%A9%20%E3%83%AC%E3%82%B3%E3%83%BC%E3%83%89/?min=10000 | Q91: https://auctions.yahoo.co.jp/search/search?p=%E3%82%B3%E3%83%BC%E3%83%97%E3%82%B9%E3%83%96%E3%83%A9%E3%82%A4%E3%83%89%20%E3%82%B5%E3%83%B3%E3%83%88%E3%83%A9%20%E3%83%AC%E3%82%B3%E3%83%BC%E3%83%89&aucminprice=10000 | R91: https://shopping.yahoo.co.jp/search/%E3%82%B3%E3%83%BC%E3%83%97%E3%82%B9%E3%83%96%E3%83%A9%E3%82%A4%E3%83%89%20%E3%82%B5%E3%83%B3%E3%83%88%E3%83%A9%20%E3%83%AC%E3%82%B3%E3%83%BC%E3%83%89/0/?pf=10000
A92: 1748 | B92: WACKO MARIA JULIUS TART OPTICAL FDR46 | C92: 1 | D92: 48000 | E92: 570 | F92: Fedex 0.5kg | G92: https://www.ebay.com/sch/i.html?_nkw=Wacko%20Maria%20Julius%20Tart%20FDR&_sacat=0&_from=R40&_sop=15&rt=nc | H92: https://jp.mercari.com/item/m33937211038 | N92: https://jp.mercari.com/search?keyword=WACKO%20MARIA%20JULIUS%20TART%20OPTICAL%20FDR&price_min=10000&sort=price&order=asc&status=on_sale | O92: https://fril.jp/s?query=WACKO%20MARIA%20JULIUS%20TART%20OPTICAL%20FDR&min=10000&transaction=selling | P92: https://search.rakuten.co.jp/search/mall/WACKO%20MARIA%20JULIUS%20TART%20OPTICAL%20FDR/?min=10000 | Q92: https://auctions.yahoo.co.jp/search/search?p=WACKO%20MARIA%20JULIUS%20TART%20OPTICAL%20FDR&aucminprice=10000 | R92: https://shopping.yahoo.co.jp/search/WACKO%20MARIA%20JULIUS%20TART%20OPTICAL%20FDR/0/?pf=10000
A93: 1749 | B93: JULIUS TART OPTICAL BRYAN LIMITED 46□22 | C93: 1 | D93: 42222 | E93: 520 | F93: Fedex 0.5kg | G93: https://www.ebay.com/sch/i.html?_nkw=Julius%20Tart%20Optical%20Bryan&_sacat=0&_from=R40&_sop=15&rt=nc | H93: https://jp.mercari.com/item/m74377038632 | N93: https://jp.mercari.com/search?keyword=JULIUS%20TART%20OPTICAL%20BRYAN%20%E3%83%A1%E3%82%AC%E3%83%8D&price_min=10000&sort=price&order=asc&status=on_sale | O93: https://fril.jp/s?query=JULIUS%20TART%20OPTICAL%20BRYAN%20%E3%83%A1%E3%82%AC%E3%83%8D&min=10000&transaction=selling | P93: https://search.rakuten.co.jp/search/mall/JULIUS%20TART%20OPTICAL%20BRYAN%20%E3%83%A1%E3%82%AC%E3%83%8D/?min=10000 | Q93: https://auctions.yahoo.co.jp/search/search?p=JULIUS%20TART%20OPTICAL%20BRYAN%20%E3%83%A1%E3%82%AC%E3%83%8D&aucminprice=10000 | R93: https://shopping.yahoo.co.jp/search/JULIUS%20TART%20OPTICAL%20BRYAN%20%E3%83%A1%E3%82%AC%E3%83%8D/0/?pf=10000
A94: 1750 | B94: JULIUS TART OPTICAL BRYAN46-CHAMPAGNE | C94: 1 | D94: 39500 | E94: 490 | F94: Fedex 0.5kg | G94: https://www.ebay.com/sch/i.html?_nkw=Julius%20Tart%20Optical%20Bryan%20champagne&_sacat=0&_from=R40&_sop=15&rt=nc | H94: https://jp.mercari.com/item/m95339393406 | N94: https://jp.mercari.com/search?keyword=JULIUS%20TART%20OPTICAL%20BRYAN%20%E3%82%B7%E3%83%A3%E3%83%B3%E3%83%91%E3%83%B3&price_min=10000&sort=price&order=asc&status=on_sale | O94: https://fril.jp/s?query=JULIUS%20TART%20OPTICAL%20BRYAN%20%E3%82%B7%E3%83%A3%E3%83%B3%E3%83%91%E3%83%B3&min=10000&transaction=selling | P94: https://search.rakuten.co.jp/search/mall/JULIUS%20TART%20OPTICAL%20BRYAN%20%E3%82%B7%E3%83%A3%E3%83%B3%E3%83%91%E3%83%B3/?min=10000 | Q94: https://auctions.yahoo.co.jp/search/search?p=JULIUS%20TART%20OPTICAL%20BRYAN%20%E3%82%B7%E3%83%A3%E3%83%B3%E3%83%91%E3%83%B3&aucminprice=10000 | R94: https://shopping.yahoo.co.jp/search/JULIUS%20TART%20OPTICAL%20BRYAN%20%E3%82%B7%E3%83%A3%E3%83%B3%E3%83%91%E3%83%B3/0/?pf=10000
A95: 1751 | B95: Hazbin Hotel ハズビンホテル トレカ シークレット セラ 65/60 | C95: 1 | D95: 39900 | E95: 590 | F95: Fedex 0.5kg | G95: https://www.ebay.com/sch/i.html?_nkw=Hazbin%20Hotel%20Cherri%20secret%20card&_sacat=0&_from=R40&_sop=15&rt=nc | H95: https://jp.mercari.com/item/m45719078217 | N95: https://jp.mercari.com/search?keyword=%E3%83%8F%E3%82%BA%E3%83%93%E3%83%B3%E3%83%9B%E3%83%86%E3%83%AB%20%E3%83%88%E3%83%AC%E3%82%AB%20%E3%82%BB%E3%83%A9%2065/60%20%E3%82%B7%E3%83%BC%E3%82%AF%E3%83%AC%E3%83%83%E3%83%88&price_min=10000&sort=price&order=asc&status=on_sale | O95: https://fril.jp/s?query=%E3%83%8F%E3%82%BA%E3%83%93%E3%83%B3%E3%83%9B%E3%83%86%E3%83%AB%20%E3%83%88%E3%83%AC%E3%82%AB%20%E3%82%BB%E3%83%A9%2065/60%20%E3%82%B7%E3%83%BC%E3%82%AF%E3%83%AC%E3%83%83%E3%83%88&min=10000&transaction=selling | P95: https://search.rakuten.co.jp/search/mall/%E3%83%8F%E3%82%BA%E3%83%93%E3%83%B3%E3%83%9B%E3%83%86%E3%83%AB%20%E3%83%88%E3%83%AC%E3%82%AB%20%E3%82%BB%E3%83%A9%2065/60%20%E3%82%B7%E3%83%BC%E3%82%AF%E3%83%AC%E3%83%83%E3%83%88/?min=10000 | Q95: https://auctions.yahoo.co.jp/search/search?p=%E3%83%8F%E3%82%BA%E3%83%93%E3%83%B3%E3%83%9B%E3%83%86%E3%83%AB%20%E3%83%88%E3%83%AC%E3%82%AB%20%E3%82%BB%E3%83%A9%2065/60%20%E3%82%B7%E3%83%BC%E3%82%AF%E3%83%AC%E3%83%83%E3%83%88&aucminprice=10000 | R95: https://shopping.yahoo.co.jp/search/%E3%83%8F%E3%82%BA%E3%83%93%E3%83%B3%E3%83%9B%E3%83%86%E3%83%AB%20%E3%83%88%E3%83%AC%E3%82%AB%20%E3%82%BB%E3%83%A9%2065/60%20%E3%82%B7%E3%83%BC%E3%82%AF%E3%83%AC%E3%83%83%E3%83%88/0/?pf=10000
A96: 1752 | B96: DD衣装 雪ミク 2018 「タンチョウ巫女」セット | C96: 1 | D96: 52000 | E96: 590 | F96: Fedex 1.5kg | G96: https://www.ebay.com/sch/i.html?_nkw=VOLKS%20DD%20Snow%20Miku%20Tancho%20Miko&_sacat=0&_from=R40&_sop=15&rt=nc | H96: https://jp.mercari.com/shops/product/CwtofebLAWDid735UfRjvN | N96: https://jp.mercari.com/search?keyword=%E3%83%9C%E3%83%BC%E3%82%AF%E3%82%B9%20DD%20%E9%9B%AA%E3%83%9F%E3%82%AF%202018%20%E3%82%BF%E3%83%B3%E3%83%81%E3%83%A7%E3%82%A6%E5%B7%AB%E5%A5%B3&price_min=10000&sort=price&order=asc&status=on_sale | O96: https://fril.jp/s?query=%E3%83%9C%E3%83%BC%E3%82%AF%E3%82%B9%20DD%20%E9%9B%AA%E3%83%9F%E3%82%AF%202018%20%E3%82%BF%E3%83%B3%E3%83%81%E3%83%A7%E3%82%A6%E5%B7%AB%E5%A5%B3&min=10000&transaction=selling | P96: https://search.rakuten.co.jp/search/mall/%E3%83%9C%E3%83%BC%E3%82%AF%E3%82%B9%20DD%20%E9%9B%AA%E3%83%9F%E3%82%AF%202018%20%E3%82%BF%E3%83%B3%E3%83%81%E3%83%A7%E3%82%A6%E5%B7%AB%E5%A5%B3/?min=10000 | Q96: https://auctions.yahoo.co.jp/search/search?p=%E3%83%9C%E3%83%BC%E3%82%AF%E3%82%B9%20DD%20%E9%9B%AA%E3%83%9F%E3%82%AF%202018%20%E3%82%BF%E3%83%B3%E3%83%81%E3%83%A7%E3%82%A6%E5%B7%AB%E5%A5%B3&aucminprice=10000 | R96: https://shopping.yahoo.co.jp/search/%E3%83%9C%E3%83%BC%E3%82%AF%E3%82%B9%20DD%20%E9%9B%AA%E3%83%9F%E3%82%AF%202018%20%E3%82%BF%E3%83%B3%E3%83%81%E3%83%A7%E3%82%A6%E5%B7%AB%E5%A5%B3/0/?pf=10000
A97: 1753 | B97: VOLKS DD Snow Miku 2025 Crystal Snow セット | C97: 1 | D97: 28500 | E97: 399 | F97: Fedex 1.5kg | G97: https://www.ebay.com/sch/i.html?_nkw=VOLKS%20DD%20Snow%20Miku%202025&_sacat=0&_from=R40&_sop=15&rt=nc | H97: https://paypayfleamarket.yahoo.co.jp/item/z619695076 | I97: https://jp.mercari.com/item/m58200082675 | N97: https://jp.mercari.com/search?keyword=VOLKS%20DD%20%E9%9B%AA%E3%83%9F%E3%82%AF%202025%20Crystal%20Snow&price_min=10000&sort=price&order=asc&status=on_sale | O97: https://fril.jp/s?query=VOLKS%20DD%20%E9%9B%AA%E3%83%9F%E3%82%AF%202025%20Crystal%20Snow&min=10000&transaction=selling | P97: https://search.rakuten.co.jp/search/mall/VOLKS%20DD%20%E9%9B%AA%E3%83%9F%E3%82%AF%202025%20Crystal%20Snow/?min=10000 | Q97: https://auctions.yahoo.co.jp/search/search?p=VOLKS%20DD%20%E9%9B%AA%E3%83%9F%E3%82%AF%202025%20Crystal%20Snow&aucminprice=10000 | R97: https://shopping.yahoo.co.jp/search/VOLKS%20DD%20%E9%9B%AA%E3%83%9F%E3%82%AF%202025%20Crystal%20Snow/0/?pf=10000
