Workbook

Sheet Sheet1
D1: 商品名 | E1: 在庫数 | F1: 仕入価格 | G1: 販売価格 | H1: 見込送料1 | I1: 見込送料 契約金額 | J1: 1.落札手数料 12.35% | K1: 2.海外手数料 0.95% | L1: 3.落札手数料 固定$0.3 | M1: 1~3合計の 消費税（10%） | N1: 1~4合計 (eBay全手数料) | O1: 残高 | P1: 広告料 2.2% | Q1: 残高（6-7） | R1: Payoneer為替 手数料2% | S1: 残高（8-9） | T1: 残高 | U1: 関税額（予想） 20％想定 | V1: 関税込み 最終残高 | W1: 利益 | X1: 利益率 | Y1: 還付金 | Z1: 純利益 | AA1: 利益率 | AB1: ebay ページ | AC1: ebay 相場 | AD1: 最安値1 | AE1: 最安値2 | AF1: 最安値3 | AG1: 最安値4 | AH1: 最安値5 | AI1: 仕入れ先 まとめ→ | AJ1: メルカリ | AK1: ラクマ | AL1: 楽天市場 | AM1: ヤフオク | AN1: ヤフー ｼｮｯﾋﾟﾝｸﾞ
A2: usd-jpy | B2: =_xlfn.WEBSERVICE("https://api.excelapi.org/currency/rate?pair="&A2) -> 157.34 | C2: 1 | G2: 148 | H2: Fedex 1.5kg | I2: =IFERROR(VLOOKUP(H2,送料!$G$10:$H$28,2,FALSE),"") -> 5951 | J2: =(G2*1.08)*0.1235 -> 19.74024 | K2: =(G2*1.08)*0.0095 -> 1.51848 | L2: 0.3 | M2: =(J2+K2+L2)*0.1 -> 2.155872 | N2: =SUM(J2:M2) -> 23.714592 | O2: =G2-N2 -> 124.28541 | P2: =G2*0.022 -> 3.256 | Q2: =O2-P2 -> 121.02941 | R2: =Q2*0.02 -> 2.4205882 | S2: =Q2-R2 -> 118.60882 | T2: =$B$2*S2 -> 18661.912 | U2: =((G2*0.15)+4.5)/0.83 -> 32.168675 | V2: =(S2-U2)*$B$2 -> 13600.492 | W2: =IFERROR(V2-F2-I2,"") -> 7649.4924 | X2: =IFERROR(W2/(G2*J2),"") -> 2.6182944 | Y2: =IFERROR(F2*10/110,"") -> 0 | Z2: =IFERROR(W2+Y2,"") -> 7649.4924 | AA2: =IFERROR(Z2/(G2*J2),"") -> 2.6182944 | AB2: https://www.ebay.com/itm/287002688876?_skw=figma+Lancer+Altria&itmmeta=01M3PPCANC6F89BWKQY2PE4EW7&hash=item42d2b17d6c:g:z5sAAeSwrX9pOg36&itmprp=enc%3AAQALAAAA8GfYFPkwiKCW4ZNSs2u11xCKVE5Omwo2QZ5431uZVFIQp74IsjHzq6rj0zZV%2BSksi%2FVWcJjFZNgDuxv4UTOYyF5rOFsROxoDrprSFFrkHqsqa3fNBDepJxYsxk%2BHESsD0cbXHW2y5oCGBN8xEjvJiCxHNd2BIqxdT3BcOluTe8Afda5yo0V6yKOE4ChZB%2FvoKVxxv2fFxCs3tiEK8pm7lex7raRCZA9EcIBKLWXKINolZZ15jjv2m%2FoxPv9ngB%2BODTSYIVeVGphu4PcufSyHWXBe8kdEYovaUqIw7HD3M%2BD5gnYkOMg6fTHeBUluwPnm%2Bw%3D%3D%7Ctkp%3ABk9SR-yqsdadaA | AC2: https://www.ebay.com/sch/i.html?_nkw=Figma+Altria+Pendragon&_sacat=0&_from=R40&_sop=15
C3: 2 | G3: 346 | H3: Fedex 7.5kg | I3: =IFERROR(VLOOKUP(H3,送料!$G$10:$H$28,2,FALSE),"") -> 16789 | J3: =(G3*1.08)*0.1235 -> 46.14948 | K3: =(G3*1.08)*0.0095 -> 3.54996 | L3: 0.3 | M3: =(J3+K3+L3)*0.1 -> 4.999944 | N3: =SUM(J3:M3) -> 54.999384 | O3: =G3-N3 -> 291.00062 | P3: =G3*0.022 -> 7.612 | Q3: =O3-P3 -> 283.38862 | R3: =Q3*0.02 -> 5.6677723 | S3: =Q3-R3 -> 277.72084 | T3: =$B$2*S3 -> 43696.598 | U3: =((G3*0.15)+4.5)/0.83 -> 67.951807 | V3: =(S3-U3)*$B$2 -> 33005.06 | W3: =IFERROR(V3-F3-I3,"") -> 16216.06 | X3: =IFERROR(W3/(G3*J3),"") -> 1.0155526 | Y3: =IFERROR(F3*10/110,"") -> 0 | Z3: =IFERROR(W3+Y3,"") -> 16216.06 | AA3: =IFERROR(Z3/(G3*J3),"") -> 1.0155526 | AB3: https://www.ebay.com/itm/276056380894?_skw=Kamen+Rider+Premium&itmmeta=01M3PPND0WCFZJT0DK22ZRXE2W&hash=item40463e15de:g:-XYAAOSwRj5lCoX4&itmprp=enc%3AAQALAAAA0GfYFPkwiKCW4ZNSs2u11xDYBdMasoFu9fkvMGSrunEbAAhv4oYhPU2G1X4RjGF7c2ocvhQOOlTvf4%2Ff%2FEZ3FpGfjTTANMPjGAMM2a4At%2B%2F%2BB4cUIii6N4c1rhSGJFhTL%2BYIj7bof%2BoNcIhDirT9IgZWBJ%2FVOrCkYIInx1IPWPn2SgbOJWG3i5rnCApza9CtfOK0YjjILuP74g6qP%2BJAQizIFIU%2BmZDtnAjrniIyZGkDYGwFPEN0ej5ln%2Byf8PrcLSud2hYlw7aGnz724D2T2A8%3D%7Ctkp%3ABk9SR9rQ1dadaA | AC3: https://www.ebay.com/sch/i.html?_nkw=Kamen+Rider+Faiz+Premium+CSM&_sacat=0&_from=R40&_trksid=m570.l1313&_odkw=Figma+Altria+Pendragon&_osacat=0&_sop=15
C4: 3 | G4: 386 | H4: Fedex 7.5kg | I4: =IFERROR(VLOOKUP(H4,送料!$G$10:$H$28,2,FALSE),"") -> 16789 | J4: =(G4*1.08)*0.1235 -> 51.48468 | K4: =(G4*1.08)*0.0095 -> 3.96036 | L4: 0.3 | M4: =(J4+K4+L4)*0.1 -> 5.574504 | N4: =SUM(J4:M4) -> 61.319544 | O4: =G4-N4 -> 324.68046 | P4: =G4*0.022 -> 8.492 | Q4: =O4-P4 -> 316.18846 | R4: =Q4*0.02 -> 6.3237691 | S4: =Q4-R4 -> 309.86469 | T4: =$B$2*S4 -> 48754.11 | U4: =((G4*0.15)+4.5)/0.83 -> 75.180723 | V4: =(S4-U4)*$B$2 -> 36925.175 | W4: =IFERROR(V4-F4-I4,"") -> 20136.175 | X4: =IFERROR(W4/(G4*J4),"") -> 1.0132384 | Y4: =IFERROR(F4*10/110,"") -> 0 | Z4: =IFERROR(W4+Y4,"") -> 20136.175 | AA4: =IFERROR(Z4/(G4*J4),"") -> 1.0132384 | AB4: https://www.ebay.com/itm/287596320225?nordt=true&orig_cvip=true&rt=nc | AC4: https://www.ebay.com/sch/i.html?_nkw=CSM+Ghost+Driver&_sacat=0&_from=R40&_trksid=m570.l1313&_odkw=PREMIUM+DX+Magnum+Shooter+40X&_osacat=0&_sop=15
C5: 4 | G5: 232 | H5: Fedex 7.5kg | I5: =IFERROR(VLOOKUP(H5,送料!$G$10:$H$28,2,FALSE),"") -> 16789 | J5: =(G5*1.08)*0.1235 -> 30.94416 | K5: =(G5*1.08)*0.0095 -> 2.38032 | L5: 0.3 | M5: =(J5+K5+L5)*0.1 -> 3.362448 | N5: =SUM(J5:M5) -> 36.986928 | O5: =G5-N5 -> 195.01307 | P5: =G5*0.022 -> 5.104 | Q5: =O5-P5 -> 189.90907 | R5: =Q5*0.02 -> 3.7981814 | S5: =Q5-R5 -> 186.11089 | T5: =$B$2*S5 -> 29282.688 | U5: =((G5*0.15)+4.5)/0.83 -> 47.349398 | V5: =(S5-U5)*$B$2 -> 21832.733 | W5: =IFERROR(V5-F5-I5,"") -> 5043.7333 | X5: =IFERROR(W5/(G5*J5),"") -> 0.70256325 | Y5: =IFERROR(F5*10/110,"") -> 0 | Z5: =IFERROR(W5+Y5,"") -> 5043.7333 | AA5: =IFERROR(Z5/(G5*J5),"") -> 0.70256325 | AB5: https://www.ebay.com/itm/126764027482?nordt=true&orig_cvip=true&rt=nc | AC5: https://www.ebay.com/sch/i.html?_nkw=PS5%20Armored%20Core%20VI%20Rubicon&_sacat=0&_from=R40&_sop=15&rt=nc&_udlo=10000
C6: 5 | G6: 1030 | H6: Fedex 1.5kg | I6: =IFERROR(VLOOKUP(H6,送料!$G$10:$H$28,2,FALSE),"") -> 5951 | J6: =(G6*1.08)*0.1235 -> 137.3814 | K6: =(G6*1.08)*0.0095 -> 10.5678 | L6: 0.3 | M6: =(J6+K6+L6)*0.1 -> 14.82492 | N6: =SUM(J6:M6) -> 163.07412 | O6: =G6-N6 -> 866.92588 | P6: =G6*0.022 -> 22.66 | Q6: =O6-P6 -> 844.26588 | R6: =Q6*0.02 -> 16.885318 | S6: =Q6-R6 -> 827.38056 | T6: =$B$2*S6 -> 130180.06 | U6: =((G6*0.15)+4.5)/0.83 -> 191.56627 | V6: =(S6-U6)*$B$2 -> 100039.02 | W6: =IFERROR(V6-F6-I6,"") -> 94088.022 | X6: =IFERROR(W6/(G6*J6),"") -> 0.66491966 | Y6: =IFERROR(F6*10/110,"") -> 0 | Z6: =IFERROR(W6+Y6,"") -> 94088.022 | AA6: =IFERROR(Z6/(G6*J6),"") -> 0.66491966 | AB6: https://www.ebay.com/itm/298425371396?nordt=true&orig_cvip=true&rt=nc | AC6: https://www.ebay.com/sch/i.html?_nkw=ARMORED+CORE+TORCH+TORCH&_sacat=0&_from=R40&_sop=15
C7: 6 | I7: =IFERROR(VLOOKUP(H7,送料!$G$10:$H$28,2,FALSE),"") | J7: =(G7*1.08)*0.1235 -> 0 | K7: =(G7*1.08)*0.0095 -> 0 | L7: 0.3 | M7: =(J7+K7+L7)*0.1 -> 0.03 | N7: =SUM(J7:M7) -> 0.33 | O7: =G7-N7 -> -0.33 | P7: =G7*0.022 -> 0 | Q7: =O7-P7 -> -0.33 | R7: =Q7*0.02 -> -0.0066 | S7: =Q7-R7 -> -0.3234 | T7: =$B$2*S7 -> -50.883756 | U7: =((G7*0.15)+4.5)/0.83 -> 5.4216867 | V7: =(S7-U7)*$B$2 -> -903.93195 | W7: =IFERROR(V7-F7-I7,"") | X7: =IFERROR(W7/(G7*J7),"") | Y7: =IFERROR(F7*10/110,"") -> 0 | Z7: =IFERROR(W7+Y7,"") | AA7: =IFERROR(Z7/(G7*J7),"")
C8: 7 | I8: =IFERROR(VLOOKUP(H8,送料!$G$10:$H$28,2,FALSE),"") | J8: =(G8*1.08)*0.1235 -> 0 | K8: =(G8*1.08)*0.0095 -> 0 | L8: 0.3 | M8: =(J8+K8+L8)*0.1 -> 0.03 | N8: =SUM(J8:M8) -> 0.33 | O8: =G8-N8 -> -0.33 | P8: =G8*0.022 -> 0 | Q8: =O8-P8 -> -0.33 | R8: =Q8*0.02 -> -0.0066 | S8: =Q8-R8 -> -0.3234 | T8: =$B$2*S8 -> -50.883756 | U8: =((G8*0.15)+4.5)/0.83 -> 5.4216867 | V8: =(S8-U8)*$B$2 -> -903.93195 | W8: =IFERROR(V8-F8-I8,"") | X8: =IFERROR(W8/(G8*J8),"") | Y8: =IFERROR(F8*10/110,"") -> 0 | Z8: =IFERROR(W8+Y8,"") | AA8: =IFERROR(Z8/(G8*J8),"")
C9: 8 | I9: =IFERROR(VLOOKUP(H9,送料!$G$10:$H$28,2,FALSE),"") | J9: =(G9*1.08)*0.1235 -> 0 | K9: =(G9*1.08)*0.0095 -> 0 | L9: 0.3 | M9: =(J9+K9+L9)*0.1 -> 0.03 | N9: =SUM(J9:M9) -> 0.33 | O9: =G9-N9 -> -0.33 | P9: =G9*0.022 -> 0 | Q9: =O9-P9 -> -0.33 | R9: =Q9*0.02 -> -0.0066 | S9: =Q9-R9 -> -0.3234 | T9: =$B$2*S9 -> -50.883756 | U9: =((G9*0.15)+4.5)/0.83 -> 5.4216867 | V9: =(S9-U9)*$B$2 -> -903.93195 | W9: =IFERROR(V9-F9-I9,"") | X9: =IFERROR(W9/(G9*J9),"") | Y9: =IFERROR(F9*10/110,"") -> 0 | Z9: =IFERROR(W9+Y9,"") | AA9: =IFERROR(Z9/(G9*J9),"")
C10: 9 | I10: =IFERROR(VLOOKUP(H10,送料!$G$10:$H$28,2,FALSE),"") | J10: =(G10*1.08)*0.1235 -> 0 | K10: =(G10*1.08)*0.0095 -> 0 | L10: 0.3 | M10: =(J10+K10+L10)*0.1 -> 0.03 | N10: =SUM(J10:M10) -> 0.33 | O10: =G10-N10 -> -0.33 | P10: =G10*0.022 -> 0 | Q10: =O10-P10 -> -0.33 | R10: =Q10*0.02 -> -0.0066 | S10: =Q10-R10 -> -0.3234 | T10: =$B$2*S10 -> -50.883756 | U10: =((G10*0.15)+4.5)/0.83 -> 5.4216867 | V10: =(S10-U10)*$B$2 -> -903.93195 | W10: =IFERROR(V10-F10-I10,"") | X10: =IFERROR(W10/(G10*J10),"") | Y10: =IFERROR(F10*10/110,"") -> 0 | Z10: =IFERROR(W10+Y10,"") | AA10: =IFERROR(Z10/(G10*J10),"")
C11: 10 | I11: =IFERROR(VLOOKUP(H11,送料!$G$10:$H$28,2,FALSE),"") | J11: =(G11*1.08)*0.1235 -> 0 | K11: =(G11*1.08)*0.0095 -> 0 | L11: 0.3 | M11: =(J11+K11+L11)*0.1 -> 0.03 | N11: =SUM(J11:M11) -> 0.33 | O11: =G11-N11 -> -0.33 | P11: =G11*0.022 -> 0 | Q11: =O11-P11 -> -0.33 | R11: =Q11*0.02 -> -0.0066 | S11: =Q11-R11 -> -0.3234 | T11: =$B$2*S11 -> -50.883756 | U11: =((G11*0.15)+4.5)/0.83 -> 5.4216867 | V11: =(S11-U11)*$B$2 -> -903.93195 | W11: =IFERROR(V11-F11-I11,"") | X11: =IFERROR(W11/(G11*J11),"") | Y11: =IFERROR(F11*10/110,"") -> 0 | Z11: =IFERROR(W11+Y11,"") | AA11: =IFERROR(Z11/(G11*J11),"")
C12: 11 | I12: =IFERROR(VLOOKUP(H12,送料!$G$10:$H$28,2,FALSE),"") | J12: =(G12*1.08)*0.1235 -> 0 | K12: =(G12*1.08)*0.0095 -> 0 | L12: 0.3 | M12: =(J12+K12+L12)*0.1 -> 0.03 | N12: =SUM(J12:M12) -> 0.33 | O12: =G12-N12 -> -0.33 | P12: =G12*0.022 -> 0 | Q12: =O12-P12 -> -0.33 | R12: =Q12*0.02 -> -0.0066 | S12: =Q12-R12 -> -0.3234 | T12: =$B$2*S12 -> -50.883756 | U12: =((G12*0.15)+4.5)/0.83 -> 5.4216867 | V12: =(S12-U12)*$B$2 -> -903.93195 | W12: =IFERROR(V12-F12-I12,"") | X12: =IFERROR(W12/(G12*J12),"") | Y12: =IFERROR(F12*10/110,"") -> 0 | Z12: =IFERROR(W12+Y12,"") | AA12: =IFERROR(Z12/(G12*J12),"")
C13: 12 | I13: =IFERROR(VLOOKUP(H13,送料!$G$10:$H$28,2,FALSE),"") | J13: =(G13*1.08)*0.1235 -> 0 | K13: =(G13*1.08)*0.0095 -> 0 | L13: 0.3 | M13: =(J13+K13+L13)*0.1 -> 0.03 | N13: =SUM(J13:M13) -> 0.33 | O13: =G13-N13 -> -0.33 | P13: =G13*0.022 -> 0 | Q13: =O13-P13 -> -0.33 | R13: =Q13*0.02 -> -0.0066 | S13: =Q13-R13 -> -0.3234 | T13: =$B$2*S13 -> -50.883756 | U13: =((G13*0.15)+4.5)/0.83 -> 5.4216867 | V13: =(S13-U13)*$B$2 -> -903.93195 | W13: =IFERROR(V13-F13-I13,"") | X13: =IFERROR(W13/(G13*J13),"") | Y13: =IFERROR(F13*10/110,"") -> 0 | Z13: =IFERROR(W13+Y13,"") | AA13: =IFERROR(Z13/(G13*J13),"")
C14: 13 | I14: =IFERROR(VLOOKUP(H14,送料!$G$10:$H$28,2,FALSE),"") | J14: =(G14*1.08)*0.1235 -> 0 | K14: =(G14*1.08)*0.0095 -> 0 | L14: 0.3 | M14: =(J14+K14+L14)*0.1 -> 0.03 | N14: =SUM(J14:M14) -> 0.33 | O14: =G14-N14 -> -0.33 | P14: =G14*0.022 -> 0 | Q14: =O14-P14 -> -0.33 | R14: =Q14*0.02 -> -0.0066 | S14: =Q14-R14 -> -0.3234 | T14: =$B$2*S14 -> -50.883756 | U14: =((G14*0.15)+4.5)/0.83 -> 5.4216867 | V14: =(S14-U14)*$B$2 -> -903.93195 | W14: =IFERROR(V14-F14-I14,"") | X14: =IFERROR(W14/(G14*J14),"") | Y14: =IFERROR(F14*10/110,"") -> 0 | Z14: =IFERROR(W14+Y14,"") | AA14: =IFERROR(Z14/(G14*J14),"")
C15: 14 | I15: =IFERROR(VLOOKUP(H15,送料!$G$10:$H$28,2,FALSE),"") | J15: =(G15*1.08)*0.1235 -> 0 | K15: =(G15*1.08)*0.0095 -> 0 | L15: 0.3 | M15: =(J15+K15+L15)*0.1 -> 0.03 | N15: =SUM(J15:M15) -> 0.33 | O15: =G15-N15 -> -0.33 | P15: =G15*0.022 -> 0 | Q15: =O15-P15 -> -0.33 | R15: =Q15*0.02 -> -0.0066 | S15: =Q15-R15 -> -0.3234 | T15: =$B$2*S15 -> -50.883756 | U15: =((G15*0.15)+4.5)/0.83 -> 5.4216867 | V15: =(S15-U15)*$B$2 -> -903.93195 | W15: =IFERROR(V15-F15-I15,"") | X15: =IFERROR(W15/(G15*J15),"") | Y15: =IFERROR(F15*10/110,"") -> 0 | Z15: =IFERROR(W15+Y15,"") | AA15: =IFERROR(Z15/(G15*J15),"")
C16: 15 | I16: =IFERROR(VLOOKUP(H16,送料!$G$10:$H$28,2,FALSE),"") | J16: =(G16*1.08)*0.1235 -> 0 | K16: =(G16*1.08)*0.0095 -> 0 | L16: 0.3 | M16: =(J16+K16+L16)*0.1 -> 0.03 | N16: =SUM(J16:M16) -> 0.33 | O16: =G16-N16 -> -0.33 | P16: =G16*0.022 -> 0 | Q16: =O16-P16 -> -0.33 | R16: =Q16*0.02 -> -0.0066 | S16: =Q16-R16 -> -0.3234 | T16: =$B$2*S16 -> -50.883756 | U16: =((G16*0.15)+4.5)/0.83 -> 5.4216867 | V16: =(S16-U16)*$B$2 -> -903.93195 | W16: =IFERROR(V16-F16-I16,"") | X16: =IFERROR(W16/(G16*J16),"") | Y16: =IFERROR(F16*10/110,"") -> 0 | Z16: =IFERROR(W16+Y16,"") | AA16: =IFERROR(Z16/(G16*J16),"")
C17: 16 | I17: =IFERROR(VLOOKUP(H17,送料!$G$10:$H$28,2,FALSE),"") | J17: =(G17*1.08)*0.1235 -> 0 | K17: =(G17*1.08)*0.0095 -> 0 | L17: 0.3 | M17: =(J17+K17+L17)*0.1 -> 0.03 | N17: =SUM(J17:M17) -> 0.33 | O17: =G17-N17 -> -0.33 | P17: =G17*0.022 -> 0 | Q17: =O17-P17 -> -0.33 | R17: =Q17*0.02 -> -0.0066 | S17: =Q17-R17 -> -0.3234 | T17: =$B$2*S17 -> -50.883756 | U17: =((G17*0.15)+4.5)/0.83 -> 5.4216867 | V17: =(S17-U17)*$B$2 -> -903.93195 | W17: =IFERROR(V17-F17-I17,"") | X17: =IFERROR(W17/(G17*J17),"") | Y17: =IFERROR(F17*10/110,"") -> 0 | Z17: =IFERROR(W17+Y17,"") | AA17: =IFERROR(Z17/(G17*J17),"")
C18: 17 | I18: =IFERROR(VLOOKUP(H18,送料!$G$10:$H$28,2,FALSE),"") | J18: =(G18*1.08)*0.1235 -> 0 | K18: =(G18*1.08)*0.0095 -> 0 | L18: 0.3 | M18: =(J18+K18+L18)*0.1 -> 0.03 | N18: =SUM(J18:M18) -> 0.33 | O18: =G18-N18 -> -0.33 | P18: =G18*0.022 -> 0 | Q18: =O18-P18 -> -0.33 | R18: =Q18*0.02 -> -0.0066 | S18: =Q18-R18 -> -0.3234 | T18: =$B$2*S18 -> -50.883756 | U18: =((G18*0.15)+4.5)/0.83 -> 5.4216867 | V18: =(S18-U18)*$B$2 -> -903.93195 | W18: =IFERROR(V18-F18-I18,"") | X18: =IFERROR(W18/(G18*J18),"") | Y18: =IFERROR(F18*10/110,"") -> 0 | Z18: =IFERROR(W18+Y18,"") | AA18: =IFERROR(Z18/(G18*J18),"")
... C24: 23 | I24: =IFERROR(VLOOKUP(H24,送料!$G$10:$H$28,2,FALSE),"") | J24: =(G24*1.08)*0.1235 -> 0 | K24: =(G24*1.08)*0.0095 -> 0 | L24: 0.3 | M24: =(J24+K24+L24)*0.1 -> 0.03 | N24: =SUM(J24:M24) -> 0.33 | O24: =G24-N24 -> -0.33 | P24: =G24*0.022 -> 0 | Q24: =O24-P24 -> -0.33 | R24: =Q24*0.02 -> -0.0066 | S24: =Q24-R24 -> -0.3234 | T24: =$B$2*S24 -> -50.883756 | U24: =((G24*0.15)+4.5)/0.83 -> 5.4216867 | V24: =(S24-U24)*$B$2 -> -903.93195 | W24: =IFERROR(V24-F24-I24,"") | X24: =IFERROR(W24/(G24*J24),"") | Y24: =IFERROR(F24*10/110,"") -> 0 | Z24: =IFERROR(W24+Y24,"") | AA24: =IFERROR(Z24/(G24*J24),"")
C25: 24 | J25: =(G25*1.08)*0.1235 -> 0 | K25: =(G25*1.08)*0.0095 -> 0 | L25: 0.3 | M25: =(J25+K25+L25)*0.1 -> 0.03 | N25: =SUM(J25:M25) -> 0.33 | O25: =G25-N25 -> -0.33 | P25: =G25*0.022 -> 0 | Q25: =O25-P25 -> -0.33 | R25: =Q25*0.02 -> -0.0066 | S25: =Q25-R25 -> -0.3234 | T25: =$B$2*S25 -> -50.883756 | U25: =((G25*0.15)+4.5)/0.83 -> 5.4216867 | V25: =(S25-U25)*$B$2 -> -903.93195 | W25: =IFERROR(V25-F25-I25,"") -> -903.93195 | X25: =IFERROR(W25/(G25*J25),"") | Y25: =IFERROR(F25*10/110,"") -> 0 | Z25: =IFERROR(W25+Y25,"") -> -903.93195 | AA25: =IFERROR(Z25/(G25*J25),"")
C26: 25 | J26: =(G26*1.08)*0.1235 -> 0 | K26: =(G26*1.08)*0.0095 -> 0 | L26: 0.3 | M26: =(J26+K26+L26)*0.1 -> 0.03 | N26: =SUM(J26:M26) -> 0.33 | O26: =G26-N26 -> -0.33 | P26: =G26*0.022 -> 0 | Q26: =O26-P26 -> -0.33 | R26: =Q26*0.02 -> -0.0066 | S26: =Q26-R26 -> -0.3234 | T26: =$B$2*S26 -> -50.883756 | U26: =((G26*0.15)+4.5)/0.83 -> 5.4216867 | V26: =(S26-U26)*$B$2 -> -903.93195 | W26: =IFERROR(V26-F26-I26,"") -> -903.93195 | X26: =IFERROR(W26/(G26*J26),"") | Y26: =IFERROR(F26*10/110,"") -> 0 | Z26: =IFERROR(W26+Y26,"") -> -903.93195 | AA26: =IFERROR(Z26/(G26*J26),"")
C27: 26 | J27: =(G27*1.08)*0.1235 -> 0 | K27: =(G27*1.08)*0.0095 -> 0 | L27: 0.3 | M27: =(J27+K27+L27)*0.1 -> 0.03 | N27: =SUM(J27:M27) -> 0.33 | O27: =G27-N27 -> -0.33 | P27: =G27*0.022 -> 0 | Q27: =O27-P27 -> -0.33 | R27: =Q27*0.02 -> -0.0066 | S27: =Q27-R27 -> -0.3234 | T27: =$B$2*S27 -> -50.883756 | U27: =((G27*0.15)+4.5)/0.83 -> 5.4216867 | V27: =(S27-U27)*$B$2 -> -903.93195 | W27: =IFERROR(V27-F27-I27,"") -> -903.93195 | X27: =IFERROR(W27/(G27*J27),"") | Y27: =IFERROR(F27*10/110,"") -> 0 | Z27: =IFERROR(W27+Y27,"") -> -903.93195 | AA27: =IFERROR(Z27/(G27*J27),"")
C28: 27 | J28: =(G28*1.08)*0.1235 -> 0 | K28: =(G28*1.08)*0.0095 -> 0 | L28: 0.3 | M28: =(J28+K28+L28)*0.1 -> 0.03 | N28: =SUM(J28:M28) -> 0.33 | O28: =G28-N28 -> -0.33 | P28: =G28*0.022 -> 0 | Q28: =O28-P28 -> -0.33 | R28: =Q28*0.02 -> -0.0066 | S28: =Q28-R28 -> -0.3234 | T28: =$B$2*S28 -> -50.883756 | U28: =((G28*0.15)+4.5)/0.83 -> 5.4216867 | V28: =(S28-U28)*$B$2 -> -903.93195 | W28: =IFERROR(V28-F28-I28,"") -> -903.93195 | X28: =IFERROR(W28/(G28*J28),"") | Y28: =IFERROR(F28*10/110,"") -> 0 | Z28: =IFERROR(W28+Y28,"") -> -903.93195 | AA28: =IFERROR(Z28/(G28*J28),"")
C29: 28 | J29: =(G29*1.08)*0.1235 -> 0 | K29: =(G29*1.08)*0.0095 -> 0 | L29: 0.3 | M29: =(J29+K29+L29)*0.1 -> 0.03 | N29: =SUM(J29:M29) -> 0.33 | O29: =G29-N29 -> -0.33 | P29: =G29*0.022 -> 0 | Q29: =O29-P29 -> -0.33 | R29: =Q29*0.02 -> -0.0066 | S29: =Q29-R29 -> -0.3234 | T29: =$B$2*S29 -> -50.883756 | U29: =((G29*0.15)+4.5)/0.83 -> 5.4216867 | V29: =(S29-U29)*$B$2 -> -903.93195 | W29: =IFERROR(V29-F29-I29,"") -> -903.93195 | X29: =IFERROR(W29/(G29*J29),"") | Y29: =IFERROR(F29*10/110,"") -> 0 | Z29: =IFERROR(W29+Y29,"") -> -903.93195 | AA29: =IFERROR(Z29/(G29*J29),"")
C30: 29 | J30: =(G30*1.08)*0.1235 -> 0 | K30: =(G30*1.08)*0.0095 -> 0 | L30: 0.3 | M30: =(J30+K30+L30)*0.1 -> 0.03 | N30: =SUM(J30:M30) -> 0.33 | O30: =G30-N30 -> -0.33 | P30: =G30*0.022 -> 0 | Q30: =O30-P30 -> -0.33 | R30: =Q30*0.02 -> -0.0066 | S30: =Q30-R30 -> -0.3234 | T30: =$B$2*S30 -> -50.883756 | U30: =((G30*0.15)+4.5)/0.83 -> 5.4216867 | V30: =(S30-U30)*$B$2 -> -903.93195 | W30: =IFERROR(V30-F30-I30,"") -> -903.93195 | X30: =IFERROR(W30/(G30*J30),"") | Y30: =IFERROR(F30*10/110,"") -> 0 | Z30: =IFERROR(W30+Y30,"") -> -903.93195 | AA30: =IFERROR(Z30/(G30*J30),"")
C31: 30 | J31: =(G31*1.08)*0.1235 -> 0 | K31: =(G31*1.08)*0.0095 -> 0 | L31: 0.3 | M31: =(J31+K31+L31)*0.1 -> 0.03 | N31: =SUM(J31:M31) -> 0.33 | O31: =G31-N31 -> -0.33 | P31: =G31*0.022 -> 0 | Q31: =O31-P31 -> -0.33 | R31: =Q31*0.02 -> -0.0066 | S31: =Q31-R31 -> -0.3234 | T31: =$B$2*S31 -> -50.883756 | U31: =((G31*0.15)+4.5)/0.83 -> 5.4216867 | V31: =(S31-U31)*$B$2 -> -903.93195 | W31: =IFERROR(V31-F31-I31,"") -> -903.93195 | X31: =IFERROR(W31/(G31*J31),"") | Y31: =IFERROR(F31*10/110,"") -> 0 | Z31: =IFERROR(W31+Y31,"") -> -903.93195 | AA31: =IFERROR(Z31/(G31*J31),"")
C32: 31 | J32: =(G32*1.08)*0.1235 -> 0 | K32: =(G32*1.08)*0.0095 -> 0 | L32: 0.3 | M32: =(J32+K32+L32)*0.1 -> 0.03 | N32: =SUM(J32:M32) -> 0.33 | O32: =G32-N32 -> -0.33 | P32: =G32*0.022 -> 0 | Q32: =O32-P32 -> -0.33 | R32: =Q32*0.02 -> -0.0066 | S32: =Q32-R32 -> -0.3234 | T32: =$B$2*S32 -> -50.883756 | U32: =((G32*0.15)+4.5)/0.83 -> 5.4216867 | V32: =(S32-U32)*$B$2 -> -903.93195 | W32: =IFERROR(V32-F32-I32,"") -> -903.93195 | X32: =IFERROR(W32/(G32*J32),"") | Y32: =IFERROR(F32*10/110,"") -> 0 | Z32: =IFERROR(W32+Y32,"") -> -903.93195 | AA32: =IFERROR(Z32/(G32*J32),"")
C33: 32 | J33: =(G33*1.08)*0.1235 -> 0 | K33: =(G33*1.08)*0.0095 -> 0 | L33: 0.3 | M33: =(J33+K33+L33)*0.1 -> 0.03 | N33: =SUM(J33:M33) -> 0.33 | O33: =G33-N33 -> -0.33 | P33: =G33*0.022 -> 0 | Q33: =O33-P33 -> -0.33 | R33: =Q33*0.02 -> -0.0066 | S33: =Q33-R33 -> -0.3234 | T33: =$B$2*S33 -> -50.883756 | U33: =((G33*0.15)+4.5)/0.83 -> 5.4216867 | V33: =(S33-U33)*$B$2 -> -903.93195 | W33: =IFERROR(V33-F33-I33,"") -> -903.93195 | X33: =IFERROR(W33/(G33*J33),"") | Y33: =IFERROR(F33*10/110,"") -> 0 | Z33: =IFERROR(W33+Y33,"") -> -903.93195 | AA33: =IFERROR(Z33/(G33*J33),"")
C34: 33 | J34: =(G34*1.08)*0.1235 -> 0 | K34: =(G34*1.08)*0.0095 -> 0 | L34: 0.3 | M34: =(J34+K34+L34)*0.1 -> 0.03 | N34: =SUM(J34:M34) -> 0.33 | O34: =G34-N34 -> -0.33 | P34: =G34*0.022 -> 0 | Q34: =O34-P34 -> -0.33 | R34: =Q34*0.02 -> -0.0066 | S34: =Q34-R34 -> -0.3234 | T34: =$B$2*S34 -> -50.883756 | U34: =((G34*0.15)+4.5)/0.83 -> 5.4216867 | V34: =(S34-U34)*$B$2 -> -903.93195 | W34: =IFERROR(V34-F34-I34,"") -> -903.93195 | X34: =IFERROR(W34/(G34*J34),"") | Y34: =IFERROR(F34*10/110,"") -> 0 | Z34: =IFERROR(W34+Y34,"") -> -903.93195 | AA34: =IFERROR(Z34/(G34*J34),"")
C35: 34 | J35: =(G35*1.08)*0.1235 -> 0 | K35: =(G35*1.08)*0.0095 -> 0 | L35: 0.3 | M35: =(J35+K35+L35)*0.1 -> 0.03 | N35: =SUM(J35:M35) -> 0.33 | O35: =G35-N35 -> -0.33 | P35: =G35*0.022 -> 0 | Q35: =O35-P35 -> -0.33 | R35: =Q35*0.02 -> -0.0066 | S35: =Q35-R35 -> -0.3234 | T35: =$B$2*S35 -> -50.883756 | U35: =((G35*0.15)+4.5)/0.83 -> 5.4216867 | V35: =(S35-U35)*$B$2 -> -903.93195 | W35: =IFERROR(V35-F35-I35,"") -> -903.93195 | X35: =IFERROR(W35/(G35*J35),"") | Y35: =IFERROR(F35*10/110,"") -> 0 | Z35: =IFERROR(W35+Y35,"") -> -903.93195 | AA35: =IFERROR(Z35/(G35*J35),"")
C36: 35 | J36: =(G36*1.08)*0.1235 -> 0 | K36: =(G36*1.08)*0.0095 -> 0 | L36: 0.3 | M36: =(J36+K36+L36)*0.1 -> 0.03 | N36: =SUM(J36:M36) -> 0.33 | O36: =G36-N36 -> -0.33 | P36: =G36*0.022 -> 0 | Q36: =O36-P36 -> -0.33 | R36: =Q36*0.02 -> -0.0066 | S36: =Q36-R36 -> -0.3234 | T36: =$B$2*S36 -> -50.883756 | U36: =((G36*0.15)+4.5)/0.83 -> 5.4216867 | V36: =(S36-U36)*$B$2 -> -903.93195 | W36: =IFERROR(V36-F36-I36,"") -> -903.93195 | X36: =IFERROR(W36/(G36*J36),"") | Y36: =IFERROR(F36*10/110,"") -> 0 | Z36: =IFERROR(W36+Y36,"") -> -903.93195 | AA36: =IFERROR(Z36/(G36*J36),"")
... C41: 40 | J41: =(G41*1.08)*0.1235 -> 0 | K41: =(G41*1.08)*0.0095 -> 0 | L41: 0.3 | M41: =(J41+K41+L41)*0.1 -> 0.03 | N41: =SUM(J41:M41) -> 0.33 | O41: =G41-N41 -> -0.33 | P41: =G41*0.022 -> 0 | Q41: =O41-P41 -> -0.33 | R41: =Q41*0.02 -> -0.0066 | S41: =Q41-R41 -> -0.3234 | T41: =$B$2*S41 -> -50.883756 | U41: =((G41*0.15)+4.5)/0.83 -> 5.4216867 | V41: =(S41-U41)*$B$2 -> -903.93195 | W41: =IFERROR(V41-F41-I41,"") -> -903.93195 | X41: =IFERROR(W41/(G41*J41),"") | Y41: =IFERROR(F41*10/110,"") -> 0 | Z41: =IFERROR(W41+Y41,"") -> -903.93195 | AA41: =IFERROR(Z41/(G41*J41),"")

Sheet 送料
B2: 旧 | D2: A | E2: D | F2: E | H2: F | I2: G | J2: H | K2: I | L2: J | M2: K | N2: M | O2: N | P2: O | Q2: Q | R2: R | S2: S | T2: T | U2: U | V2: V | W2: W | X2: X | Y2: Y | Z2: Z
B3: ～2024年まで | C3: エンベロープ 0.5kg | D3: 2094 | E3: 2491 | F3: 1774 | G3: エンベロープ 0.5kg | H3: 1803 | I3: 2175 | J3: 1848 | K3: 1865 | L3: 1694 | M3: 1340 | N3: 1802 | O3: 2092 | P3: 1479 | Q3: 1363 | R3: 1445 | S3: 1629 | T3: 1840 | U3: 2465 | V3: 1281 | W3: 1402 | X3: 1581 | Y3: 1545 | Z3: 1658
C4: パック 0.5kg | D4: 2141 | E4: 3698 | F4: 2046 | G4: パック 0.5kg | H4: 2076 | I4: 2220 | J4: 2050 | K4: 2065 | L4: 1913 | M4: 1364 | N4: 1977 | O4: 2213 | P4: 1684 | Q4: 1394 | R4: 1476 | S4: 1665 | T4: 1884 | U4: 2536 | V4: 1305 | W4: 1429 | X4: 1613 | Y4: 1580 | Z4: 1690
C5: パック 1.0kg | D5: 2633 | E5: 4450 | F5: 2416 | G5: パック 1.0kg | H5: 2451 | I5: 2816 | J5: 2223 | K5: 2245 | L5: 2392 | M5: 1669 | N5: 2064 | O5: 2654 | P5: 2015 | Q5: 1663 | R5: 1763 | S5: 1992 | T5: 2223 | U5: 3045 | V5: 1596 | W5: 1749 | X5: 1978 | Y5: 1889 | Z5: 2074
C6: パック 1.5kg | D6: 3115 | E6: 5283 | F6: 2836 | G6: パック 1.5kg | H6: 2881 | I6: 3564 | J6: 2857 | K6: 2915 | L6: 3099 | M6: 2009 | N6: 2658 | O6: 3069 | P6: 2442 | Q6: 1958 | R6: 2071 | S6: 2327 | T6: 2574 | U6: 3643 | V6: 1924 | W6: 2100 | X6: 2363 | Y6: 2212 | Z6: 2473
C7: パック 2.0kg | D7: 3460 | E7: 6010 | F7: 3157 | G7: パック 2.0kg | H7: 3204 | I7: 4254 | J7: 3408 | K7: 3404 | L7: 3630 | M7: 2222 | N7: 3168 | O7: 3377 | P7: 2761 | Q7: 2146 | R7: 2271 | S7: 2554 | T7: 2804 | U7: 4135 | V7: 2127 | W7: 2324 | X7: 2619 | Y7: 2427 | Z7: 2742
C8: パック 2.5kg | D8: 3943 | E8: 6887 | F8: 3589 | G8: パック 2.5kg | H8: 3641 | I8: 5025 | J8: 4046 | K8: 4019 | L8: 4261 | M8: 2563 | N8: 3766 | O8: 3820 | P8: 3207 | Q8: 2460 | R8: 2598 | S8: 2912 | T8: 3164 | U8: 4763 | V8: 2458 | W8: 2677 | X8: 3005 | Y8: 2770 | Z8: 3143
B9: 2025/8/30～ | C9: Fedex 0.5kg | D9: 2523 | E9: 5323 | F9: 1999 | G9: Fedex 0.5kg | H9: 4474 | I9: 3580 | J9: 2142 | K9: 2158 | L9: 2995 | M9: 1630 | N9: 2065 | O9: 2944 | P9: 2360 | Q9: 1788 | R9: 1914 | S9: 2170 | T9: 2751 | U9: 3071 | V9: 1522 | W9: 1692 | X9: 1692 | Y9: 1914 | Z9: 1904
B10: 黄色のところ | C10: Fedex 1.0kg | D10: 3336 | E10: 5907 | F10: 2226 | G10: Fedex 1.0kg | H10: 5279 | I10: 4152 | J10: 2386 | K10: 2407 | L10: 3320 | M10: 1717 | N10: 2243 | O10: 2816 | P10: 2745 | Q10: 1965 | R10: 2050 | S10: 2392 | T10: 2792 | U10: 3571 | V10: 1691 | W10: 1800 | X10: 2037 | Y10: 2050 | Z10: 2135
C11: Fedex 1.5kg | D11: 3857 | E11: 7011 | F11: 2552 | G11: Fedex 1.5kg | H11: 5951 | I11: 5201 | J11: 2729 | K11: 2753 | L11: 4140 | M11: 2031 | N11: 2517 | O11: 3185 | P11: 3307 | Q11: 2294 | R11: 2390 | S11: 2774 | T11: 3267 | U11: 4274 | V11: 2003 | W11: 2125 | X11: 2391 | Y11: 2390 | Z11: 2503
C12: Fedex 2.0kg | D12: 4277 | E12: 7826 | F12: 2670 | G12: Fedex 2.0kg | H12: 6627 | I12: 6100 | J12: 2906 | K12: 2948 | L12: 4704 | M12: 2186 | N12: 2600 | O12: 3463 | P12: 3669 | Q12: 2428 | R12: 2535 | S12: 2955 | T12: 3616 | U12: 4777 | V12: 2202 | W12: 2335 | X12: 2602 | Y12: 2535 | Z12: 2731
C13: Fedex 2.5kg | D13: 4799 | E13: 8940 | F13: 3056 | G13: Fedex 2.5kg | H13: 7340 | I13: 7172 | J13: 3390 | K13: 3502 | L13: 5537 | M13: 2495 | N13: 3042 | O13: 3897 | P13: 4233 | Q13: 2760 | R13: 2878 | S13: 3339 | T13: 4134 | U13: 5489 | V13: 2513 | W13: 2659 | X13: 2954 | Y13: 2878 | Z13: 3096
C14: Fedex 3.0kg | D14: 5164 | E14: 9948 | F14: 3542 | G14: Fedex 3.0kg | H14: 9602 | I14: 8089 | J14: 3771 | K14: 3953 | L14: 6282 | M14: 2672 | N14: 3379 | O14: 4322 | P14: 4691 | Q14: 3049 | R14: 3180 | S14: 3698 | T14: 4543 | U14: 6092 | V14: 2692 | W14: 2849 | X14: 3168 | Y14: 3180 | Z14: 3321
C15: Fedex 3.5kg | D15: 5692 | E15: 10166 | F15: 3325 | G15: Fedex 3.5kg | H15: 10966 | I15: 8870 | J15: 3867 | K15: 4084 | L15: 7049 | M15: 2790 | N15: 3351 | O15: 4595 | P15: 4906 | Q15: 3151 | R15: 3267 | S15: 3827 | T15: 5008 | U15: 6301 | V15: 2826 | W15: 2987 | X15: 3351 | Y15: 3265 | Z15: 3490
C16: Fedex 4.0kg | D16: 6064 | E16: 11092 | F16: 3709 | G16: Fedex 4.0kg | H16: 12329 | I16: 9764 | J16: 4213 | K16: 4492 | L16: 7789 | M16: 2958 | N16: 3646 | O16: 4997 | P16: 5334 | Q16: 3416 | R16: 3542 | S16: 4157 | T16: 5415 | U16: 6861 | V16: 2996 | W16: 3168 | X16: 3558 | Y16: 3540 | Z16: 3708
C17: Fedex 4.5kg | D17: 6536 | E17: 12118 | F17: 4193 | G17: Fedex 4.5kg | H17: 13693 | I17: 10759 | J17: 4658 | K17: 4999 | L17: 8628 | M17: 3226 | N17: 4041 | O17: 5501 | P17: 5862 | Q17: 3780 | R17: 3918 | S17: 4586 | T17: 5922 | U17: 7520 | V17: 3267 | W17: 3450 | X17: 3865 | Y17: 3915 | Z17: 4025
C18: Fedex 5.0kg | D18: 6907 | E18: 13045 | F18: 4577 | G18: Fedex 5.0kg | H18: 15056 | I18: 11653 | J18: 5004 | K18: 5406 | L18: 9368 | M18: 3393 | N18: 4335 | O18: 5904 | P18: 6289 | Q18: 4045 | R18: 4193 | S18: 4916 | T18: 6329 | U18: 8080 | V18: 3437 | W18: 3632 | X18: 4073 | Y18: 4191 | Z18: 4242
C19: Fedex 5.5kg | D19: 8558 | E19: 13782 | F19: 5715 | G19: Fedex 5.5kg | H19: 15205 | I19: 13932 | J19: 6086 | K19: 6861 | L19: 12913 | M19: 3582 | N19: 5099 | O19: 6627 | P19: 7203 | Q19: 4620 | R19: 4454 | S19: 5656 | T19: 7856 | U19: 9244 | V19: 3580 | W19: 3709 | X19: 4630 | Y19: 4380 | Z19: 4282
C20: Fedex 6.0kg | D20: 8827 | E20: 14364 | F20: 5840 | G20: Fedex 6.0kg | H20: 15600 | I20: 14201 | J20: 6268 | K20: 6996 | L20: 13171 | M20: 3682 | N20: 5248 | O20: 6774 | P20: 7495 | Q20: 4718 | R20: 4548 | S20: 5779 | T20: 8025 | U20: 9625 | V20: 3680 | W20: 3814 | X20: 4765 | Y20: 4470 | Z20: 4407
C21: Fedex 6.5kg | D21: 9196 | E21: 15045 | F21: 6065 | G21: Fedex 6.5kg | H21: 15997 | I21: 14569 | J21: 6549 | K21: 7230 | L21: 13529 | M21: 3884 | N21: 5497 | O21: 7020 | P21: 7886 | Q21: 4915 | R21: 4742 | S21: 6002 | T21: 8293 | U21: 10106 | V21: 3880 | W21: 4019 | X21: 5002 | Y21: 4662 | Z21: 4631
C22: Fedex 7.0kg | D22: 9465 | E22: 15627 | F22: 6191 | G22: Fedex 7.0kg | H22: 16392 | I22: 14838 | J22: 6731 | K22: 7365 | L22: 13786 | M22: 3984 | N22: 5647 | O22: 7166 | P22: 8178 | Q22: 5013 | R22: 4835 | S22: 6124 | T22: 8461 | U22: 10487 | V22: 3982 | W22: 4124 | X22: 5138 | Y22: 4754 | Z22: 4756
... C48: Fedex 20.0kg | D48: 15777 | E48: 29481 | F48: 16223 | G48: Fedex 20.0kg | H48: 31283 | I48: 39064 | J48: 17825 | K48: 19858 | L48: 39335 | M48: 10631 | N48: 14902 | O48: 12981 | P48: 16977 | Q48: 10679 | R48: 12694 | S48: 12180 | T48: 14162 | U48: 26386 | V48: 10370 | W48: 10862 | X48: 11664 | Y48: 12622 | Z48: 12631
C49: 20.5 | D49: 15877 | E49: 29974 | F49: 16516 | G49: Fedex 21.0kg | H49: 31715 | I49: 39642 | J49: 17959 | K49: 20195 | L49: 39928 | M49: 10731 | N49: 15030 | O49: 13200 | P49: 17290 | Q49: 10873 | R49: 12911 | S49: 12391 | T49: 14262 | U49: 26834 | V49: 10470 | W49: 10962 | X49: 11764 | Y49: 12838 | Z49: 12731
G50: Fedex 22.0kg | H50: 33042
G51: Fedex 23.0kg | H51: 34448
G52: Fedex 24.0kg | H52: 35823
G53: Fedex 25.0kg | H53: 37199
G54: Fedex 26.0kg | H54: 38574
G55: Fedex 27.0kg | H55: 39950
G56: Fedex 28.0kg | H56: 41325
G57: Fedex 29.0kg | H57: 42701
G58: Fedex 30.0kg | H58: 44076
G59: Fedex 31.0kg | H59: 45452
G60: Fedex 32.0kg | H60: 46827
G61: Fedex 33.0kg | H61: 48203
... G68: Fedex 40.0kg | H68: 57831
